Workbook

Sheet ADM
A1: Análise de indicadores | C1: Jan | D1: Fev | E1: Mar | F1: Abr | G1: Mai | H1: Jun | I1: Jul | J1: Ago | K1: Set | L1: Out | M1: Nov | N1: Dez | O1: Total
A2: Efetivo Inicial (Un) | C2: 3 | D2: 3 | E2: 3 | F2: 3 | G2: 3 | H2: 3 | I2: 3 | J2: 4 | K2: 3 | L2: 5 | M2: 6 | N2: 5 | O2: 3.6666667
A3: Afastamentos + Faltas (dias) | C3: 0 | D3: 5 | E3: 0 | F3: 2 | G3: 0 | H3: 0 | I3: 6 | J3: 2 | K3: 1 | L3: 2 | M3: 3 | N3: 1 | O3: 1.8333333
A4: Novas Contratações (Un) | C4: 0 | D4: 0 | E4: 0 | F4: 0 | G4: 1 | H4: 0 | I4: 1 | J4: 0 | K4: 2 | L4: 1 | M4: 0 | N4: 1 | O4: 0.5
A5: Desligamentos (Un) | C5: 0 | D5: 0 | E5: 0 | F5: 0 | G5: 1 | H5: 0 | I5: 0 | J5: 1 | K5: 0 | L5: 0 | M5: 1 | N5: 1 | O5: 0.33333333
A6: Efetivo Final (Un) | C6: 3 | D6: 3 | E6: 3 | F6: 3 | G6: 3 | H6: 3 | I6: 4 | J6: 3 | K6: 5 | L6: 6 | M6: 5 | N6: 5 | O6: 3.8333333
A7: Efetivo Médio | C7: 3 | D7: 3 | E7: 3 | F7: 3 | G7: 3 | H7: 3 | I7: 3.5 | J7: 3.5 | K7: 4 | L7: 5.5 | M7: 5.5 | N7: 5 | O7: 3.75
A8: Férias (dias não produtivos) | C8: 5 | D8: 0 | E8: 5 | F8: 0 | G8: 0 | H8: 0 | I8: 0 | J8: 0 | K8: 0 | L8: 0 | M8: 0 | N8: 0 | O8: 0.83333333
A9: Colaboradores de Férias (Un) | C9: 1 | D9: 0 | E9: 1 | F9: 0 | G9: 0 | H9: 0 | I9: 0 | J9: 0 | K9: 0 | L9: 0 | M9: 0 | N9: 0 | O9: 0.16666667
A10: Dias Úteis | C10: 22 | D10: 21 | E10: 20 | F10: 21 | G10: 21 | H10: 20 | I10: 23 | J10: 22 | K10: 21 | L10: 23 | M10: 21 | N10: 21 | O10: 21.333333
A11: Dias Programados | C11: 66 | D11: 63 | E11: 60 | F11: 63 | G11: 63 | H11: 60 | I11: 80.5 | J11: 77 | K11: 84 | L11: 126.5 | M11: 115.5 | N11: 105 | O11: 80.291667
A12: Dias Produtivos | C12: 61 | D12: 63 | E12: 55 | F12: 63 | G12: 63 | H12: 60 | I12: 80.5 | J12: 77 | K12: 84 | L12: 126.5 | M12: 115.5 | N12: 105 | O12: 79.458333
A13: Dias não Produtivos | C13: 5 | D13: 5 | E13: 5 | F13: 2 | G13: 0 | H13: 0 | I13: 6 | J13: 2 | K13: 1 | L13: 2 | M13: 3 | N13: 1 | O13: 2.6666667
... A21: Salário Per Capto (R$) | C21: 2671.0667 | D21: 2671.0667 | E21: 2671.0667 | F21: 2671.0667 | G21: 2664.7967 | H21: 2837.7333 | I21: 2600.3429 | J21: 2574.8571 | K21: 3293.3325 | L21: 3184.1782 | M21: 2620.3636 | N21: 2829.066 | O21: 2774.0781
A22: Valor de Tributos | C22: =#REF! -> #REF! | D22: =#REF! -> #REF! | E22: =#REF! -> #REF! | F22: =#REF! -> #REF! | G22: 481.42 | H22: =#REF! -> #REF! | I22: =#REF! -> #REF! | J22: =#REF! -> #REF! | K22: =#REF! -> #REF! | L22: =#REF! -> #REF! | M22: 1040 | N22: 1040 | O22: =#REF! -> #REF!
A23: INSS Patronal | O23: 0
A24: FGTS | C24: =#REF! -> #REF! | D24: =#REF! -> #REF! | E24: =#REF! -> #REF! | F24: =#REF! -> #REF! | G24: 481.42 | H24: =#REF! -> #REF! | I24: =#REF! -> #REF! | J24: =#REF! -> #REF! | K24: =#REF! -> #REF! | L24: =#REF! -> #REF! | M24: 1040 | N24: 1040 | O24: =#REF! -> #REF!
A25: Encargos sobre a Folha (%) | G25: 0.060219729 | M25: 0.072162087 | N25: 0.073522498 | O25: 0.017158693

Sheet ADM 2025
A1: Análise de indicadores | C1: Jan | D1: Fev | E1: Mar | F1: Abr | G1: Mai | H1: Jun | I1: Jul | J1: Ago | K1: Set | L1: Out | M1: Nov | N1: Dez | O1: Total
A2: Efetivo Inicial (Un) | C2: 5 | D2: 6 | E2: 6 | F2: 6 | G2: 6 | H2: 6 | I2: 4 | J2: 5 | K2: 5 | L2: 4 | M2: 4 | N2: 4 | O2: =AVERAGE(C2:N2) -> 5.0833333
A3: Afastamentos + Faltas (dias) | C3: 3 | D3: 0 | E3: 1 | F3: 0 | G3: 5 | H3: 0 | I3: 0 | J3: 0 | K3: 0 | L3: 0 | M3: 0 | N3: 0 | O3: =AVERAGE(C3:N3) -> 0.75
A4: Novas Contratações (Un) | C4: 1 | D4: 2 | E4: 2 | F4: 1 | G4: 0 | H4: 0 | I4: 1 | J4: 0 | K4: 0 | L4: 0 | M4: 1 | N4: 1 | O4: =AVERAGE(C4:N4) -> 0.75
A5: Desligamentos (Un) | C5: 0 | D5: 2 | E5: 2 | F5: 1 | G5: 0 | H5: 2 | I5: 0 | J5: 0 | K5: 1 | L5: 0 | M5: 1 | N5: 2 | O5: =AVERAGE(C5:N5) -> 0.91666667
A6: Efetivo Final (Un) | C6: =C2+C4-C5 -> 6 | D6: =D2+D4-D5 -> 6 | E6: =E2+E4-E5 -> 6 | F6: =F2+F4-F5 -> 6 | G6: =G2+G4-G5 -> 6 | H6: =H2+H4-H5 -> 4 | I6: =I2+I4-I5 -> 5 | J6: =J2+J4-J5 -> 5 | ... N6: =N2+N4-N5 -> 3 | O6: =AVERAGE(C6:N6) -> 4.9166667
A7: Efetivo Médio | C7: =(C2+C6)/2 -> 5.5 | D7: =(D2+D6)/2 -> 6 | E7: =(E2+E6)/2 -> 6 | F7: =(F2+F6)/2 -> 6 | G7: =(G2+G6)/2 -> 6 | H7: =(H2+H6)/2 -> 5 | I7: =(I2+I6)/2 -> 4.5 | J7: =(J2+J6)/2 -> 5 | ... N7: =(N2+N6)/2 -> 3.5 | O7: =AVERAGE(C7:N7) -> 5
A8: Férias (dias não produtivos) | C8: ='Janeiro 25'!U15 -> 0 | D8: 0 | E8: 0 | F8: 0 | G8: 0 | H8: 0 | I8: 0 | J8: 0 | K8: 0 | L8: 13 | M8: 0 | N8: 0 | O8: =AVERAGE(C8:N8) -> 1.0833333
A9: Colaboradores de Férias (Un) | C9: ='Janeiro 25'!U16 -> 0 | D9: 0 | E9: 0 | F9: 0 | G9: 0 | H9: 0 | I9: 0 | J9: 0 | K9: 0 | L9: 1 | M9: 0 | N9: 0 | O9: =AVERAGE(C9:N9) -> 0.083333333
A10: Dias Úteis | C10: =#REF! -> #REF! | D10: 20 | E10: 21 | F10: 19 | G10: 20 | H10: 20 | I10: 23 | J10: 21 | K10: 22 | L10: 23 | M10: 21 | N10: 22 | O10: =AVERAGE(C10:N10) -> #REF!
A11: Dias Programados | C11: =C10*C7 -> #REF! | D11: =D10*D7 -> 120 | E11: =E10*E7 -> 126 | F11: =F10*F7 -> 114 | G11: =G10*G7 -> 120 | H11: =H10*H7 -> 100 | I11: =I10*I7 -> 103.5 | J11: =J10*J7 -> 105 | ... N11: =N10*N7 -> 77 | O11: =AVERAGE(C11:N11) -> #REF!
A12: Dias Produtivos | C12: =C11-(C8+C3) -> #REF! | D12: =D11-(D8+D3) -> 120 | E12: =E11-(E8+E3) -> 125 | F12: =F11-(F8+F3) -> 114 | G12: =G11-(G8+G3) -> 115 | H12: =H11-(H8+H3) -> 100 | I12: =I11-(I8+I3) -> 103.5 | J12: =J11-(J8+J3) -> 105 | ... N12: =N11-(N8+N3) -> 77 | O12: =AVERAGE(C12:N12) -> #REF!
A13: Dias não Produtivos | C13: =C8+C3 -> 3 | D13: =D8+D3 -> 0 | E13: =E8+E3 -> 1 | F13: =F8+F3 -> 0 | G13: =G8+G3 -> 5 | H13: =H8+H3 -> 0 | I13: =I8+I3 -> 0 | J13: =J8+J3 -> 0 | ... N13: =N8+N3 -> 0 | O13: =AVERAGE(C13:N13) -> 1.8333333
A14: Horas Programadas | C14: =(C6*8.8)*C10 -> #REF! | D14: =(D6*8.8)*D10 -> 1056 | E14: =(E6*8.8)*E10 -> 1108.8 | F14: =(F6*8.8)*F10 -> 1003.2 | G14: =(G6*8.8)*G10 -> 1056 | H14: =(H6*8.8)*H10 -> 704 | I14: =(I6*8.8)*I10 -> 1012 | J14: =(J6*8.8)*J10 -> 924 | ... N14: =(N6*8.8)*N10 -> 580.8 | O14: =AVERAGE(C14:N14) -> #REF!
A15: Horas não Produtivas | C15: =C13*8.8 -> 26.4 | D15: =D13*8.8 -> 0 | E15: =E13*8.8 -> 8.8 | F15: =F13*8.8 -> 0 | G15: =G13*8.8 -> 44 | H15: =H13*8.8 -> 0 | I15: =I13*8.8 -> 0 | J15: =J13*8.8 -> 0 | ... N15: =N13*8.8 -> 0 | O15: =AVERAGE(C15:N15) -> 16.133333
A16: Efetivo Pessoal Mês | C16: =(C14-C15)/(8.8*C10) -> #REF! | D16: =(D14-D15)/(8.8*D10) -> 6 | E16: =(E14-E15)/(8.8*E10) -> 5.952381 | F16: =(F14-F15)/(8.8*F10) -> 6 | G16: =(G14-G15)/(8.8*G10) -> 5.75 | H16: =(H14-H15)/(8.8*H10) -> 4 | I16: =(I14-I15)/(8.8*I10) -> 5 | J16: =(J14-J15)/(8.8*J10) -> 5 | ... N16: =(N14-N15)/(8.8*N10) -> 3 | O16: =AVERAGE(C16:N16) -> #REF!
A17: Taxa de Absenteísmo | C17: =IFERROR((C15/C14),"") | D17: =IFERROR((D15/D14),"") -> 0 | E17: =IFERROR((E15/E14),"") -> 0.0079365079 | F17: =IFERROR((F15/F14),"") -> 0 | G17: =IFERROR((G15/G14),"") -> 0.041666667 | H17: =IFERROR((H15/H14),"") -> 0 | I17: =IFERROR((I15/I14),"") -> 0 | J17: =IFERROR((J15/J14),"") -> 0 | ... N17: =IFERROR((N15/N14),"") -> 0 | O17: =SUM(C17:N17)/12 -> 0.01590896
A18: Taxa de Turnover | C18: =IFERROR((((C5+C4)/2)/C2),"") -> 0.1 | D18: =IFERROR((((D5+D4)/2)/D2),"") -> 0.33333333 | E18: =IFERROR((((E5+E4)/2)/E2),"") -> 0.33333333 | F18: =IFERROR((((F5+F4)/2)/F2),"") -> 0.16666667 | G18: =IFERROR((((G5+G4)/2)/G2),"") -> 0 | H18: =IFERROR((((H5+H4)/2)/H2),"") -> 0.16666667 | I18: =IFERROR((((I5+I4)/2)/I2),"") -> 0.125 | J18: =IFERROR((((J5+J4)/2)/J2),"") -> 0 | ... N18: =IFERROR((((N5+N4)/2)/N2),"") -> 0.375 | O18: =SUM(C18:N18)/12 -> 0.1625
A19: Folha Líquida (R$) | C19: ='Fopag Analitic'!D15 -> 13226.01 | D19: ='Fopag Analitic'!G15 -> 13130.21 | E19: ='Fopag Analitic'!J15 -> 11749.71 | F19: ='Fopag Analitic'!M15 -> 13076.92 | G19: ='Fopag Analitic'!P15 -> 14689.69 | H19: 10094.15 | I19: 12554.18 | J19: 14081.11 | K19: 11783.34 | L19: 9549.1 | M19: =11333.06+4679.17 -> 16012.23 | O19: =SUM(C19:N19) -> 139946.65
A20: Folha Bruta (R$) | C20: ='Fopag Analitic'!D14 -> 14480 | D20: ='Fopag Analitic'!G14 -> 14300 | E20: ='Fopag Analitic'!J14 -> 12800 | F20: ='Fopag Analitic'!M14 -> 14320 | G20: ='Fopag Analitic'!P14 -> 16000 | H20: 11000 | I20: 13733.33 | J20: 15400 | K20: 12900 | L20: 12900 | M20: =12700+4679.17 -> 17379.17 | O20: =SUM(C20:N20) -> 155212.5
A21: Salário Per Capto (R$) | C21: =IFERROR((C20/C7),"") -> 2632.7273 | D21: =IFERROR((D20/D7),"") -> 2383.3333 | E21: =IFERROR((E20/E7),"") -> 2133.3333 | F21: =IFERROR((F20/F7),"") -> 2386.6667 | G21: =IFERROR((G20/G7),"") -> 2666.6667 | H21: =IFERROR((H20/H7),"") -> 2200 | I21: =IFERROR((I20/I7),"") -> 3051.8511 | J21: =IFERROR((J20/J7),"") -> 3080 | ... M21: =IFERROR((M20/M7),"") -> 4344.7925 | O21: {=SUM(C21:N21/12)} -> 2580.9198
A22: Valor de Tributos | C22: =SUM(C23:C25) -> 4899.64 | D22: =SUM(D23:D25) -> 4836.1 | E22: =SUM(E23:E25) -> 4306.6 | F22: =SUM(F23:F25) -> 4843.16 | G22: =SUM(G23:G25) -> 5436.2 | H22: =SUM(H23:H25) -> 3671.2 | I22: =SUM(I23:I25) -> 4636.0655 | J22: =SUM(J23:J25) -> 5995 | ... M22: =SUM(M23:M25) -> 2122.33 | O22: =SUM(C22:N22) -> 50912.095
A23: INSS Patronal | O23: =SUM(C23:N23) -> 0
A24: FGTS | C24: ='Fopag Analitic'!D17 -> 1110.4 | D24: ='Fopag Analitic'!G17 -> 1096 | E24: ='Fopag Analitic'!J17 -> 976 | F24: ='Fopag Analitic'!M17 -> 1097.6 | G24: ='Fopag Analitic'!P17 -> 1232 | H24: ='Fopag Analitic'!S17 -> 832 | I24: ='Fopag Analitic'!V17 -> 1050.6664 | J24: 1184 | K24: 984 | L24: 924 | M24: =968+374.33 -> 1342.33 | O24: =SUM(C24:N24) -> 11828.996
A25: INSS Patronal | C25: ='Fopag Analitic'!D18+'Fopag Analitic'!D19+'Fopag Analitic'!D20 -> 3789.24 | D25: ='Fopag Analitic'!G18+'Fopag Analitic'!G19+'Fopag Analitic'!G20 -> 3740.1 | E25: ='Fopag Analitic'!J18+'Fopag Analitic'!J19+'Fopag Analitic'!J20 -> 3330.6 | F25: ='Fopag Analitic'!M18+'Fopag Analitic'!M19+'Fopag Analitic'!M20 -> 3745.56 | G25: ='Fopag Analitic'!P18+'Fopag Analitic'!P19+'Fopag Analitic'!P20 -> 4204.2 | H25: ='Fopag Analitic'!S18+'Fopag Analitic'!S19+'Fopag Analitic'!S20 -> 2839.2 | I25: ='Fopag Analitic'!V18+'Fopag Analitic'!V19+'Fopag Analitic'!V20 -> 3585.3991 | J25: 4811 | K25: 4128.9 | L25: 4128.9 | M25: ='Fopag 01 26'!B32 -> 780 | O25: =SUM(C25:N25) -> 39083.099
A26: Encargos sobre a Folha (%) | C26: =IFERROR((C22/C20),"") -> 0.33837293 | D26: =IFERROR((D22/D20),"") -> 0.33818881 | E26: =IFERROR((E22/E20),"") -> 0.33645313 | F26: =IFERROR((F22/F20),"") -> 0.3382095 | G26: =IFERROR((G22/G20),"") -> 0.3397625 | H26: =IFERROR((H22/H20),"") -> 0.33374545 | I26: =IFERROR((I22/I20),"") -> 0.33757767 | J26: =IFERROR((J22/J20),"") -> 0.38928571 | ... N26: =IFERROR((N22/N20),"") | O26: =SUM(C26:N26)/12 -> 0.30514678

Sheet Jan
H1: Atestados | M1: Faltas | O1: Férias
B2: Funcionário | C2: Nome do Funcionário | D2: Departamento | E2: Admissão | F2: Demissão | G2: Afastamento | H2: Início | I2: Fim | J2: Início | K2: Fim | L2: Dias | M2: Faltas | N2: Dias | O2: Início | P2: Fim | Q2: Dias | R2: Observação
B3: 2 | C3: LEANDRO PINHEIRO DOS SANTO | D3: PRODUCAO | E3: 44599 | L3: =(I3-H3) -> 0 | T3: Início Colab | U3: 3
B4: 1 | C4: LUCAS ANDRADE SILVA | D4: PRODUCAO | E4: 44599 | L4: =(I4-H4) -> 0 | T4: Admissão | U4: 0
B5: 3 | C5: SAMY HERCULANO PINTO | D5: PRODUCAO | E5: 44602 | L5: =(I5-H5) -> 0 | O5: 45306 | P5: 45310 | Q5: 5 | T5: Demissão | U5: 0
L6: =SUM(L3:L5) -> 0 | N6: =SUM(N3:N5) -> 0 | Q6: =SUM(Q3:Q5) -> 5 | T6: Fim Colab | U6: =U3+U4-U5 -> 3
T8: Sócio | U8: 2
T9: Total | U9: =U6+U8 -> 5
T11: Afastamentos
T12: Atestados | U12: =L6 -> 0
T13: Faltas | U13: =N6 -> 0
T15: Férias | U15: =Q6 -> 5
T16: Colaboradores | U16: 0
T18: Dias Úteis | U18: 22

Sheet Fev
H1: Atestados | M1: Faltas | O1: Férias
B2: Funcionário | C2: Nome do Funcionário | D2: Departamento | E2: Admissão | F2: Demissão | G2: Afastamento | H2: Início | I2: Fim | J2: Início | K2: Fim | L2: Dias | M2: Faltas | N2: Dias | O2: Início | P2: Fim | Q2: Dias | R2: Observação
B3: 2 | C3: LEANDRO PINHEIRO DOS SANTO | D3: PRODUCAO | E3: 44599 | H3: 45337 | I3: 45338 | L3: 2 | T3: Início Colab | U3: 3
B4: 1 | C4: LUCAS ANDRADE SILVA | D4: PRODUCAO | E4: 44599 | L4: =(I4-H4) -> 0 | T4: Admissão | U4: 0
B5: 3 | C5: SAMY HERCULANO PINTO | D5: PRODUCAO | E5: 44602 | H5: 45343 | I5: 45346 | L5: 3 | T5: Demissão | U5: 0
L6: =SUM(L3:L5) -> 5 | N6: =SUM(N3:N5) -> 0 | Q6: =SUM(Q3:Q5) -> 0 | T6: Fim Colab | U6: =U3+U4-U5 -> 3
T8: Sócio | U8: 2
T9: Total | U9: =U6+U8 -> 5
T11: Afastamentos
T12: Atestados | U12: =L6 -> 5
T13: Faltas | U13: =N6 -> 0
T15: Férias | U15: =Q6 -> 0
T16: Colaboradores | U16: 0
T18: Dias Úteis | U18: 21

Sheet Mar
H1: Atestados | M1: Faltas | O1: Férias
B2: Funcionário | C2: Nome do Funcionário | D2: Departamento | E2: Admissão | F2: Demissão | G2: Afastamento | H2: Início | I2: Fim | J2: Início | K2: Fim | L2: Dias | M2: Faltas | N2: Dias | O2: Início | P2: Fim | Q2: Dias | R2: Observação
B3: 2 | C3: LEANDRO PINHEIRO DOS SANTO | D3: PRODUCAO | E3: 44599 | L3: =(I3-H3) -> 0 | O3: 45369 | P3: 45375 | Q3: 5 | T3: Início Colab | U3: 3
B4: 1 | C4: LUCAS ANDRADE SILVA | D4: PRODUCAO | E4: 44599 | L4: =(I4-H4) -> 0 | T4: Admissão | U4: 0
B5: 3 | C5: SAMY HERCULANO PINTO | D5: PRODUCAO | E5: 44602 | L5: =(I5-H5) -> 0 | T5: Demissão | U5: 0
L6: =SUM(L3:L5) -> 0 | N6: =SUM(N3:N5) -> 0 | Q6: =SUM(Q3:Q5) -> 5 | T6: Fim Colab | U6: =U3+U4-U5 -> 3
T8: Sócio | U8: 2
T9: Total | U9: =U6+U8 -> 5
T11: Afastamentos
T12: Atestados | U12: =L6 -> 0
T13: Faltas | U13: =N6 -> 0
T15: Férias | U15: =Q6 -> 5
T16: Colaboradores | U16: 0
T18: Dias Úteis | U18: 20

Sheet Abril
H1: Atestados | M1: Faltas | O1: Férias
B2: Funcionário | C2: Nome do Funcionário | D2: Departamento | E2: Admissão | F2: Demissão | G2: Afastamento | H2: Início | I2: Fim | J2: Início | K2: Fim | L2: Dias | M2: Faltas | N2: Dias | O2: Início | P2: Fim | Q2: Dias | R2: Observação
B3: 2 | C3: LEANDRO PINHEIRO DOS SANTO | D3: PRODUCAO | E3: 44599 | L3: =(I3-H3) -> 0 | Q3: 0 | T3: Início Colab | U3: 3
B4: 1 | C4: LUCAS ANDRADE SILVA | D4: PRODUCAO | E4: 44599 | L4: =(I4-H4) -> 0 | T4: Admissão | U4: 0
B5: 3 | C5: SAMY HERCULANO PINTO | D5: PRODUCAO | E5: 44602 | H5: 45407 | I5: 45408 | L5: 2 | T5: Demissão | U5: 0
L6: =SUM(L3:L5) -> 2 | N6: =SUM(N3:N5) -> 0 | Q6: =SUM(Q3:Q5) -> 0 | T6: Fim Colab | U6: =U3+U4-U5 -> 3
T8: Sócio | U8: 2
T9: Total | U9: =U6+U8 -> 5
T11: Afastamentos
T12: Atestados | U12: =L6 -> 2
T13: Faltas | U13: =N6 -> 0
T15: Férias | U15: =Q6 -> 0
T16: Colaboradores | U16: 0
T18: Dias Úteis | U18: 20

Sheet Maio
H1: Atestados | M1: Faltas | O1: Férias
B2: Funcionário | C2: Nome do Funcionário | D2: Departamento | E2: Admissão | F2: Demissão | G2: Afastamento | H2: Início | I2: Fim | J2: Início | K2: Fim | L2: Dias | M2: Faltas | N2: Dias | O2: Início | P2: Fim | Q2: Dias | R2: Observação
B3: 2 | C3: LEANDRO PINHEIRO DOS SANTO | D3: ADM | E3: 44599 | L3: =(I3-H3) -> 0 | Q3: 0 | T3: Início Colab | U3: 3
B4: 1 | C4: LUCAS ANDRADE SILVA | D4: ADM | E4: 44599 | F4: 45443 | L4: =(I4-H4) -> 0 | R4: Termino do aviso 31/05/2024 | T4: Admissão | U4: 1
B5: 3 | C5: SAMY HERCULANO PINTO | D5: ADM | E5: 44602 | L5: 0 | T5: Demissão | U5: 1
B6: 4 | C6: GABRIELLY LOPES MACHADO | D6: ADM | E6: 45426 | L6: 0 | T6: Fim Colab | U6: =U3+U4-U5 -> 3
L7: =SUM(L3:L5) -> 0 | N7: =SUM(N3:N5) -> 0 | Q7: =SUM(Q3:Q5) -> 0
T8: Sócio | U8: 2
T9: Total | U9: =U6+U8 -> 5
T11: Afastamentos
T12: Atestados | U12: =L7 -> 0
T13: Faltas | U13: =N7 -> 0
T15: Férias | U15: =Q7 -> 0
T16: Colaboradores | U16: 0
T18: Dias Úteis | U18: 21

Sheet Junho
H1: Atestados | M1: Faltas | O1: Férias
B2: Funcionário | C2: Nome do Funcionário | D2: Departamento | E2: Admissão | F2: Demissão | G2: Afastamento | H2: Início | I2: Fim | J2: Início | K2: Fim | L2: Dias | M2: Faltas | N2: Dias | O2: Início | P2: Fim | Q2: Dias | R2: Observação
B3: 2 | C3: LEANDRO PINHEIRO DOS SANTO | D3: ADM | E3: 44599 | L3: =(I3-H3) -> 0 | Q3: 0 | T3: Início Colab | U3: 3
B4: 3 | C4: SAMY HERCULANO PINTO | D4: ADM | E4: 44602 | L4: 0 | Q4: 0 | T4: Admissão | U4: 0
B5: 4 | C5: GABRIELLY LOPES MACHADO | D5: ADM | E5: 45426 | L5: 0 | Q5: 0 | T5: Demissão | U5: 0
L6: =SUM(L3:L5) -> 0 | N6: =SUM(N3:N4) -> 0 | Q6: =SUM(Q3:Q4) -> 0 | T6: Fim Colab | U6: =U3+U4-U5 -> 3
T8: Sócio | U8: 2
T9: Total | U9: =U6+U8 -> 5
T11: Afastamentos
T12: Atestados | U12: =L6 -> 0
T13: Faltas | U13: =N6 -> 0
T15: Férias | U15: =Q6 -> 0
T16: Colaboradores | U16: 0
T18: Dias Úteis | U18: 20

Sheet Julho
H1: Atestados | M1: Faltas | O1: Férias
B2: Funcionário | C2: Nome do Funcionário | D2: Departamento | E2: Admissão | F2: Demissão | G2: Afastamento | H2: Início | I2: Fim | J2: Início | K2: Fim | L2: Dias | M2: Faltas | N2: Dias | O2: Início | P2: Fim | Q2: Dias | R2: Observação
B3: 2 | C3: LEANDRO PINHEIRO DOS SANTO | D3: ADM | E3: 44599 | L3: =(I3-H3) -> 0 | N3: 0 | Q3: 0 | T3: Início Colab | U3: 3
B4: 3 | C4: SAMY HERCULANO PINTO | D4: ADM | E4: 44602 | L4: 0 | N4: 0 | Q4: 0 | T4: Admissão | U4: 1
B5: 5 | C5: GABRIEL FONSECA DA SILVA | D5: ADM | E5: 45477 | L5: 0 | N5: 0 | Q5: 0 | T5: Demissão | U5: 0
B6: 4 | C6: GABRIELLY LOPES MACHADO | D6: ADM | E6: 45426 | H6: 45498 | I6: 45499 | J6: 45502 | K6: 45504 | L6: 5 | M6: 45483 | N6: 1 | Q6: 0 | T6: Fim Colab | U6: =U3+U4-U5 -> 4
L7: =SUM(L3:L6) -> 5 | N7: =SUM(N3:N6) -> 1 | Q7: =SUM(Q3:Q6) -> 0
T8: Sócio | U8: 2
T9: Total | U9: =U6+U8 -> 6
T11: Afastamentos
T12: Atestados | U12: =L7 -> 5
T13: Faltas | U13: =N7 -> 1
T15: Férias | U15: =Q7 -> 0
T16: Colaboradores | U16: 0
T18: Dias Úteis | U18: 23

Sheet Agosto
H1: Atestados | M1: Faltas | O1: Férias
B2: Funcionário | C2: Nome do Funcionário | D2: Departamento | E2: Admissão | F2: Demissão | G2: Afastamento | H2: Início | I2: Fim | J2: Início | K2: Fim | L2: Dias | M2: Faltas | N2: Dias | O2: Início | P2: Fim | Q2: Dias | R2: Observação
B3: 2 | C3: LEANDRO PINHEIRO DOS SANTO | D3: ADM | E3: 44599 | L3: =(I3-H3) -> 0 | N3: 0 | Q3: 0 | T3: Início Colab | U3: 4
B4: 3 | C4: SAMY HERCULANO PINTO | D4: ADM | E4: 44602 | H4: 45513 | I4: 45513 | L4: 1 | N4: 0 | Q4: 0 | T4: Admissão | U4: 0
B5: 5 | C5: GABRIEL FONSECA DA SILVA | D5: ADM | E5: 45477 | L5: 0 | M5: 45525 | N5: 1 | Q5: 0 | T5: Demissão | U5: 1
B6: 4 | C6: GABRIELLY LOPES MACHADO | D6: ADM | E6: 45426 | L6: 0 | N6: 0 | Q6: 0 | R6: Desligamento 02/08/2024 | T6: Fim Colab | U6: =U3+U4-U5 -> 3
L7: =SUM(L3:L6) -> 1 | N7: =SUM(N3:N6) -> 1 | Q7: =SUM(Q3:Q6) -> 0
T8: Sócio | U8: 2
T9: Total | U9: =U6+U8 -> 5
T11: Afastamentos
T12: Atestados | U12: =L7 -> 1
T13: Faltas | U13: =N7 -> 1
T15: Férias | U15: =Q7 -> 0
T16: Colaboradores | U16: 0
T18: Dias Úteis | U18: 22

Sheet Setembro
H1: Atestados | M1: Faltas | O1: Férias
B2: Funcionário | C2: Nome do Funcionário | D2: Departamento | E2: Admissão | F2: Demissão | G2: Afastamento | H2: Início | I2: Fim | J2: Início | K2: Fim | L2: Dias | M2: Faltas | N2: Dias | O2: Início | P2: Fim | Q2: Dias | R2: Observação
B3: 2 | C3: LEANDRO PINHEIRO DOS SANTO | D3: ADM | E3: 44599 | L3: =(I3-H3) -> 0 | N3: 0 | Q3: 0 | T3: Início Colab | U3: 3
B4: 3 | C4: SAMY HERCULANO PINTO | D4: ADM | E4: 44602 | L4: 0 | N4: 0 | O4: 45544 | P4: 45550 | Q4: 6 | T4: Admissão | U4: 2
B5: 5 | C5: GABRIEL FONSECA DA SILVA | D5: ADM | E5: 45477 | L5: =(I5-H5) -> 0 | N5: 0 | Q5: 0 | T5: Demissão | U5: 0
B6: 6 | C6: MAXSUEL MOREIRA REZENDE | D6: ADM | E6: 45539 | L6: 0 | M6: 45553 | N6: 1 | Q6: 0 | T6: Fim Colab | U6: =U3+U4-U5 -> 5
B7: 7 | C7: AUGUSTO CESAR DA SILVA FILHO | D7: ADM | E7: 45546 | L7: 0 | N7: 0 | Q7: 0
L8: =SUM(L3:L7) -> 0 | N8: =SUM(N3:N7) -> 1 | Q8: =SUM(Q3:Q7) -> 6 | T8: Sócio | U8: 2
T9: Total | U9: =U6+U8 -> 7
T11: Afastamentos
T12: Atestados | U12: =L8 -> 0
T13: Faltas | U13: =N8 -> 1
T15: Férias | U15: =Q8 -> 6
T16: Colaboradores | U16: 0
T18: Dias Úteis | U18: 21

Sheet Outubro
H1: Atestados | M1: Faltas | O1: Férias
B2: Funcionário | C2: Nome do Funcionário | D2: Departamento | E2: Admissão | F2: Demissão | G2: Afastamento | H2: Início | I2: Fim | J2: Início | K2: Fim | L2: Dias | M2: Faltas | N2: Dias | O2: Início | P2: Fim | Q2: Dias | R2: Observação
B3: 7 | C3: AUGUSTO CESAR DA SILVA FILHO | D3: ADM | E3: 45546 | L3: 0 | N3: 0 | Q3: 0 | T3: Início Colab | U3: 5
B4: 5 | C4: GABRIEL FONSECA DA SILVA | D4: ADM | E4: 45477 | L4: =(I4-H4) -> 0 | N4: 0 | Q4: 0 | T4: Admissão | U4: 1
B5: 2 | C5: LEANDRO PINHEIRO DOS SANTO | D5: ADM | E5: 44599 | L5: =(I5-H5) -> 0 | N5: 0 | Q5: 0 | T5: Demissão | U5: 0
B6: 6 | C6: MAXSUEL MOREIRA REZENDE | D6: ADM | E6: 45539 | H6: 45580 | I6: 45581 | L6: 2 | N6: 0 | Q6: 0 | T6: Fim Colab | U6: =U3+U4-U5 -> 6
B7: 8 | C7: RAFAELA REGINA TAMANHONI | D7: ADM | E7: 45567 | L7: 0 | N7: 0 | Q7: 0
B8: 3 | C8: SAMY HERCULANO PINTO | D8: ADM | E8: 44602 | L8: 0 | N8: 0 | Q8: 0 | T8: Sócio | U8: 2
L9: =SUM(L3:L8) -> 2 | N9: =SUM(N3:N8) -> 0 | Q9: =SUM(Q3:Q8) -> 0 | T9: Total | U9: =U6+U8 -> 8
T11: Afastamentos
T12: Atestados | U12: =L9 -> 2
T13: Faltas | U13: =N9 -> 0
T15: Férias | U15: =Q9 -> 0
T16: Colaboradores | U16: 0
T18: Dias Úteis | U18: 23

Sheet Novembro
H1: Atestados | M1: Faltas | O1: Férias
B2: Funcionário | C2: Nome do Funcionário | D2: Departamento | E2: Admissão | F2: Demissão | G2: Afastamento | H2: Início | I2: Fim | J2: Início | K2: Fim | L2: Dias | M2: Faltas | N2: Dias | O2: Início | P2: Fim | Q2: Dias | R2: Observação
B3: 7 | C3: AUGUSTO CESAR DA SILVA FILHO | D3: ADM | E3: 45546 | L3: 0 | N3: 0 | Q3: 0 | T3: Início Colab | U3: 5
B4: 5 | C4: GABRIEL FONSECA DA SILVA | D4: ADM | E4: 45477 | L4: =(I4-H4) -> 0 | N4: 0 | Q4: 0 | T4: Admissão | U4: 0
B5: 2 | C5: LEANDRO PINHEIRO DOS SANTO | D5: ADM | E5: 44599 | L5: =(I5-H5) -> 0 | N5: 0 | Q5: 0 | T5: Demissão | U5: 1
B6: 6 | C6: MAXSUEL MOREIRA REZENDE | D6: ADM | E6: 45539 | F6: 45621 | H6: 45617 | I6: 45618 | L6: 2 | N6: 0 | Q6: 0 | T6: Fim Colab | U6: =U3+U4-U5 -> 4
B7: 8 | C7: RAFAELA REGINA TAMANHONI | D7: ADM | E7: 45567 | H7: 45607 | I7: 45607 | L7: 1 | N7: 0 | Q7: 0
B8: 3 | C8: SAMY HERCULANO PINTO | D8: ADM | E8: 44602 | L8: 0 | N8: 0 | Q8: 0 | T8: Sócio | U8: 2
L9: =SUM(L3:L8) -> 3 | N9: =SUM(N3:N8) -> 0 | Q9: =SUM(Q3:Q8) -> 0 | T9: Total | U9: =U6+U8 -> 6
T11: Afastamentos
T12: Atestados | U12: =L9 -> 3
T13: Faltas | U13: =N9 -> 0
T15: Férias | U15: =Q9 -> 0
T16: Colaboradores | U16: 0
T18: Dias Úteis | U18: 21

Sheet Dezembro
H1: Atestados | M1: Faltas | O1: Férias
B2: Funcionário | C2: Nome do Funcionário | D2: Departamento | E2: Admissão | F2: Demissão | G2: Afastamento | H2: Início | I2: Fim | J2: Início | K2: Fim | L2: Dias | M2: Faltas | N2: Dias | O2: Início | P2: Fim | Q2: Dias | R2: Observação
B3: 7 | C3: AUGUSTO CESAR DA SILVA FILHO | D3: ADM | E3: 45546 | L3: 0 | N3: 0 | Q3: 0 | T3: Início Colab | U3: 5
B4: 5 | C4: GABRIEL FONSECA DA SILVA | D4: ADM | E4: 45477 | F4: 45644 | L4: 0 | M4: 45643 | N4: 1 | Q4: 0 | T4: Admissão | U4: 1
B5: 2 | C5: LEANDRO PINHEIRO DOS SANTO | D5: ADM | E5: 44599 | L5: 0 | N5: 0 | Q5: 0 | T5: Demissão | U5: 1
B6: 6 | C6: LORENA DIAS ALMEIDA | D6: ADM | E6: 45630 | L6: 0 | N6: 0 | Q6: 0 | T6: Fim Colab | U6: =U3+U4-U5 -> 5
B7: 8 | C7: RAFAELA REGINA TAMANHONI | D7: ADM | E7: 45567 | L7: 0 | N7: 0 | Q7: 0
B8: 3 | C8: SAMY HERCULANO PINTO | D8: ADM | E8: 44602 | L8: 0 | N8: 0 | Q8: 0 | T8: Sócio | U8: 2
L9: =SUM(L3:L8) -> 0 | N9: =SUM(N3:N8) -> 1 | Q9: =SUM(Q3:Q8) -> 0 | T9: Total | U9: =U6+U8 -> 7
T11: Afastamentos
T12: Atestados | U12: =L9 -> 0
T13: Faltas | U13: =N9 -> 1
T15: Férias | U15: =Q9 -> 0
T16: Colaboradores | U16: 0
T18: Dias Úteis | U18: 21

Sheet Custo Fopag 25
B2: Telamassas Adm 2025 | C2: Janeiro | D2: Fevereiro | E2: Março | F2: Abril | G2: Maio | H2: Junho | I2: Julho | J2: Agosto | K2: Setembro | L2: Outubro | M2: Novembro | N2: Dezembro | O2: Total | Q2: Período | R2: Faturamento | S2: Custo | T2: % | U2: Meta | V2: Colab | W2: Fat x Colab
B3: Salário | C3: ='Fopag Analitic'!D4 -> 14480 | D3: ='Fopag Analitic'!G4 -> 14300 | E3: ='Fopag Analitic'!J4 -> 12800 | F3: ='Fopag Analitic'!M4 -> 14320 | G3: ='Fopag Analitic'!P14 -> 16000 | H3: ='Fopag Analitic'!S14 -> 11000 | I3: 13733 | J3: 15400 | K3: 12900 | L3: 12900 | M3: 12900 | N3: 9900 | O3: =SUM(C3:N3) -> 160633 | Q3: 45658 | R3: 1738802 | S3: =C12 -> 63760.76 | T3: =S3/R3 -> 0.036669362 | U3: 0.03 | V3: ='Janeiro 25'!U6 -> 6 | W3: =R3/V3 -> 289800.33
B4: Pro Labore | C4: =18000+12500 -> 30500 | D4: =18000+12500 -> 30500 | E4: =18000+12500 -> 30500 | F4: =18000+12500 -> 30500 | G4: =18000+12500 -> 30500 | H4: =18000+12500 -> 30500 | I4: =18000+12500 -> 30500 | J4: =18000+12500 -> 30500 | K4: 30500 | L4: 30500 | M4: ='Fopag 01 26'!B22 -> 32570 | N4: 30500 | O4: =SUM(C4:N4) -> 368070 | Q4: 45689 | R4: 1630074 | S4: =D12 -> 63344.82 | T4: =S4/R4 -> 0.038860089 | U4: 0.03 | V4: ='Fevereiro 25'!U6 -> 6 | W4: =R4/V4 -> 271679
B5: FGTS | C5: ='Fopag Analitic'!D17 -> 1110.4 | D5: ='Fopag Analitic'!G17 -> 1096 | E5: ='Fopag Analitic'!J17 -> 976 | F5: ='Fopag Analitic'!M17 -> 1097.6 | G5: ='Fopag Analitic'!P17 -> 1232 | H5: ='Fopag Analitic'!S17 -> 832 | I5: 1051 | J5: 1232 | K5: 1032 | L5: 1032 | M5: 1032 | N5: 792 | O5: =SUM(C5:N5) -> 12515 | Q5: 45717 | R5: 1537894 | S5: =E12 -> 61036.72 | T5: =S5/R5 -> 0.039688509 | U5: 0.03 | V5: ='Março 25'!U6 -> 6 | W5: =R5/V5 -> 256315.67
B6: INSS+RAT+Terceiros | C6: 3898 | D6: 3740 | E6: ='Fopag Analitic'!J18+'Fopag Analitic'!J19+'Fopag Analitic'!J20 -> 3330.6 | F6: ='Fopag Analitic'!M18+'Fopag Analitic'!M19+'Fopag Analitic'!M20 -> 3745.56 | G6: ='Fopag Analitic'!P18+'Fopag Analitic'!P19+'Fopag Analitic'!P20 -> 4204.2 | H6: ='Fopag Analitic'!S18+'Fopag Analitic'!S19+'Fopag Analitic'!S20 -> 2839.2 | I6: 3585 | J6: 4811 | K6: 4128.9 | L6: 4129 | M6: 4129 | N6: 3310 | O6: =SUM(C6:N6) -> 45850.46 | Q6: 45748 | R6: 1645073 | S6: =F12 -> 63192.37 | T6: =S6/R6 -> 0.03841311 | U6: 0.03 | V6: ='Abril 25'!U5 -> 6 | W6: =R6/V6 -> 274178.83
B7: Provisões | C7: =C3*35.3% -> 5111.44 | D7: =D3*35.3% -> 5047.9 | E7: =E3*35.3% -> 4518.4 | F7: =F3*35.3% -> 5054.96 | G7: =G3*35.3% -> 5648 | H7: =H3*35.3% -> 3883 | I7: =I3*35.3% -> 4847.749 | J7: =J3*35.3% -> 5436.2 | ... M7: =M3*35.3% -> 4553.7 | N7: 2605 | O7: =SUM(C7:N7) -> 55813.749 | Q7: 45778 | R7: 1733520 | S7: =G12 -> 66367.95 | T7: =S7/R7 -> 0.038285079 | U7: 0.03 | V7: ='Maio 25'!U5 -> 6 | W7: =R7/V7 -> 288920
B8: Aj. Custo Diretoria | C8: ='Fopag Analitic'!D28 -> 4000 | D8: ='Fopag Analitic'!G28 -> 4000 | E8: ='Fopag Analitic'!J28 -> 4000 | F8: ='Fopag Analitic'!M28 -> 4000 | G8: ='Fopag Analitic'!P28 -> 4000 | H8: ='Fopag Analitic'!S28 -> 4000 | I8: 4000 | J8: 4000 | K8: 4000 | L8: 4000 | M8: 4000 | N8: 4000 | O8: =SUM(C8:N8) -> 48000 | Q8: 45809 | R8: 1503624 | S8: =H12 -> 57053.2 | T8: =S8/R8 -> 0.037943794 | U8: 0.03 | V8: ='Junho 25'!U5 -> 4 | W8: =R8/V8 -> 375906
B9: Alimentação | C9: ='Fopag Analitic'!D22 -> 3000 | D9: ='Fopag Analitic'!G22 -> 3000 | E9: ='Fopag Analitic'!J22 -> 3150 | F9: ='Fopag Analitic'!M22 -> 2725 | G9: ='Fopag Analitic'!P22 -> 3000 | H9: ='Fopag Analitic'!S22 -> 2000 | I9: 2525 | J9: 3675 | K9: 3080 | L9: 2660 | M9: 3080 | N9: 2520 | O9: =SUM(C9:N9) -> 34415 | Q9: 45839 | R9: 1724204 | S9: =I12 -> 62301.749 | T9: =S9/R9 -> 0.03613363 | U9: 0.03 | V9: ='Julho 25'!U5 -> 5 | W9: =R9/V9 -> 344840.8
B10: Transporte | C10: ='Fopag Analitic'!D23 -> 1134 | D10: ='Fopag Analitic'!G23 -> 1134 | E10: ='Fopag Analitic'!J23 -> 1234.8 | F10: ='Fopag Analitic'!M23 -> 1068.2 | G10: ='Fopag Analitic'!P23 -> 1176 | H10: ='Fopag Analitic'!S23 -> 784 | I10: 990 | J10: 1050 | K10: 880 | L10: 760 | M10: 880 | N10: 630 | O10: =SUM(C10:N10) -> 11721 | Q10: 45870 | R10: 1242847 | S10: =J12 -> 67020.2 | T10: =S10/R10 -> 0.053924739 | U10: 0.03 | V10: 5 | W10: =R10/V10 -> 248569.4
B11: Plano Saúde | C11: ='Fopag Analitic'!D24 -> 526.92 | D11: ='Fopag Analitic'!G24 -> 526.92 | E11: ='Fopag Analitic'!J24 -> 526.92 | F11: ='Fopag Analitic'!M24 -> 681.05 | G11: ='Fopag Analitic'!P24 -> 607.75 | H11: 1215 | I11: 1070 | J11: 916 | K11: 1562.32 | L11: 1369.63 | M11: 1215.5 | N11: 1216 | O11: =SUM(C11:N11) -> 11434.01 | Q11: 45901 | R11: 1940005 | S11: =K12 -> 62636.92 | T11: =S11/R11 -> 0.032286989 | U11: 0.03 | V11: 4 | W11: =R11/V11 -> 485001.25
B12: Total | C12: =SUM(C3:C11) -> 63760.76 | D12: =SUM(D3:D11) -> 63344.82 | E12: =SUM(E3:E11) -> 61036.72 | F12: =SUM(F3:F11) -> 63192.37 | G12: =SUM(G3:G11) -> 66367.95 | H12: =SUM(H3:H11) -> 57053.2 | I12: =SUM(I3:I11) -> 62301.749 | J12: =SUM(J3:J11) -> 67020.2 | ... O12: =SUM(O3:O11) -> 748452.22 | Q12: 45931 | R12: 2011406 | S12: =L12 -> 61904.33 | T12: =S12/R12 -> 0.030776646 | U12: 0.03 | V12: 4 | W12: =R12/V12 -> 502851.5
Q13: 45962 | R13: 1564054 | S13: =M12 -> 64360.2 | T13: =S13/R13 -> 0.041149602 | U13: 0.03 | V13: 4 | W13: =R13/V13 -> 391013.5
B14: Telamassas Adm 2025 | C14: Janeiro | D14: Fevereiro | E14: Março | F14: Abril | G14: Maio | H14: Junho | I14: Julho | J14: Agosto | K14: Setembro | L14: Outubro | M14: Novembro | N14: Dezembro | O14: Total | Q14: 45992 | R14: 1444984 | S14: =N12 -> 55473 | T14: =S14/R14 -> 0.038390044 | U14: 0.03 | V14: 3 | W14: =R14/V14 -> 481661.33
B15: Folha Líquida | C15: 13226 | D15: 13130.21 | E15: 11749.71 | F15: 13076.92 | G15: 14689.69 | H15: 10094.15 | I15: 12554.18 | J15: 14081 | K15: 11783.34 | L15: 9549.1 | M15: =11333.06+4679.17 -> 16012.23 | N15: =9037.22+3829.62 -> 12866.84 | O15: =SUM(C15:N15) -> 152813.37
B16: FGTS | C16: =C5 -> 1110.4 | D16: 1096 | E16: 976 | F16: 1097.6 | G16: 1232 | H16: 832 | I16: 1050.6664 | J16: 1232 | K16: 1032 | L16: 1032 | M16: 1032 | N16: =N5 -> 792 | O16: =SUM(C16:N16) -> 12514.666
B17: INSS Patronal | C17: =C6 -> 3898 | D17: =D6 -> 3740 | E17: 3330.6 | F17: 3745.56 | G17: 4204.2 | H17: 2839.2 | I17: 3585.3991 | J17: 4811.4 | K17: 4129 | L17: 4129 | M17: 4129 | N17: =N6 -> 3310 | O17: =SUM(C17:N17) -> 45851.359
B18: Pro Labore | C18: 30500 | D18: 30500 | E18: 30500 | F18: 30500 | G18: 30500 | H18: 30500 | I18: 30500 | J18: 30500 | K18: 30500 | L18: 30500 | M18: =M4 -> 32570 | N18: 30500 | O18: 0
B19: Aj. Custo Diretoria | C19: 4000 | D19: 4000 | E19: 4000 | F19: 4000 | G19: 4000 | H19: 4000 | I19: 4000 | J19: 4000 | K19: 4000 | L19: 4000 | M19: 4000 | N19: 4000 | O19: =SUM(C19:N19) -> 48000
B20: Alimentação | C20: 3000 | D20: 3000 | E20: 3150 | F20: 2725 | G20: 3000 | H20: 2000 | I20: 2525 | J20: =J9 -> 3675 | K20: 3080 | L20: 2660 | M20: =M9 -> 3080 | N20: =N9 -> 2520 | O20: =SUM(C20:N20) -> 34415
B21: Transporte | C21: 1134 | D21: 1134 | E21: 1234.8 | F21: 1068.2 | G21: 1176 | H21: 784 | I21: 989.8 | J21: =J10 -> 1050 | K21: 880 | L21: 760 | M21: =M10 -> 880 | N21: =N10 -> 630 | O21: =SUM(C21:N21) -> 11720.8
B22: Plano Saúde | C22: 526.92 | D22: 526.92 | E22: 526.92 | F22: 681.05 | G22: 607.75 | H22: 1070.14 | I22: 1070.14 | J22: =J11 -> 916 | K22: 1562 | L22: 1370 | M22: =M11 -> 1215.5 | N22: =N11 -> 1216 | O22: =SUM(C22:N22) -> 11289.34
B23: Total | C23: =SUM(C15:C22) -> 57395.32 | D23: =SUM(D15:D22) -> 57127.13 | E23: =SUM(E15:E22) -> 55468.03 | F23: =SUM(F15:F22) -> 56894.33 | G23: =SUM(G15:G22) -> 59409.64 | H23: =SUM(H15:H22) -> 52119.49 | I23: =SUM(I15:I22) -> 56275.185 | J23: =SUM(J15:J22) -> 60265.4 | ... N23: =SUM(N15:N22) -> 55834.84 | O23: =SUM(O15:O17) -> 211179.4
C24: =C23/R3 -> 0.033008543 | D24: =D23/R4 -> 0.035045728 | E24: =E23/R5 -> 0.036067525 | F24: =F23/R6 -> 0.034584684 | G24: =G23/R7 -> 0.034271102 | H24: =H23/R8 -> 0.034662582 | I24: =I23/R9 -> 0.032638357 | J24: =J23/R10 -> 0.048489798 | K24: =K23/R11 -> 0.029364017 | L24: =L23/R12 -> 0.026846942 | M24: =M23/R13 -> 0.040227978 | N24: =N23/R14 -> 0.038640456

Sheet Dezembro 25
H1: Atestados | M1: Faltas | O1: Férias
B2: Funcionário | C2: Nome do Funcionário | D2: Departamento | E2: Admissão | F2: Demissão | G2: Afastamento | H2: Início | I2: Fim | J2: Início | K2: Fim | L2: Dias | M2: Faltas | N2: Dias | O2: Início | P2: Fim | Q2: Dias | R2: Observação | T2: Início Colab | U2: 4
B3: 2 | C3: LEANDRO PINHEIRO DOS SANTO | D3: ADM | E3: 44599 | L3: 0 | N3: 0 | Q3: 0 | T3: Admissão | U3: 1
B4: 9 | C4: SAMUEL APOLINÁRIO | D4: ADM | E4: 45702 | L4: 0 | N4: 0 | Q4: 0 | T4: Demissão | U4: 2
B5: 11 | C5: SILVANIA BARBOSA ALVES | D5: ADM | E5: 45736 | L5: 0 | N5: 0 | Q5: 0 | T5: Fim Colab | U5: =U2+U3-U4 -> 3
B6: 11 | C6: TATIANI COOK | D6: ADM | E6: 45964 | F6: 46373 | L6: 0 | N6: 0 | Q6: 0
B7: 10 | C7: VIVIANE DA COSTA | D7: ADM | E7: 46364 | F7: 46371 | L7: 0 | N7: 0 | Q7: 0
L8: =SUM(L3:L4) -> 0 | N8: =SUM(N3:N4) -> 0 | Q8: =SUM(Q3:Q4) -> 0 | T8: Sócio | U8: 2
T9: Total | U9: =U5+U8 -> 5
T11: Afastamentos
T12: Atestados | U12: 0
T13: Faltas | U13: =N8 -> 0
T15: Férias | U15: =Q8 -> 0
T16: Colaboradores | U16: 0
T18: Dias Úteis | U18: 22

Sheet Rotatividade 2025
A1: Turnover (Rotatividade de Pessoal) | I1: Absenteísmo (Ausências no Trabalho) | V1: Análise de indicadores | X1: Jan | Y1: Fev | Z1: Mar | AA1: Abr | AB1: Mai | AC1: Jun | AD1: Jul | AE1: Ago | AF1: Set | AG1: Out | AH1: Nov | AI1: Dez
A2: Ano: | D2: 2025 | F2: Meta: | G2: 0.05 | I2: Ano: | L2: 2025 | M2: Meta: | N2: 0.045 | V2: Efetivo Inicial (Un) | X2: 5 | Y2: 6 | Z2: 6 | AA2: 6 | AB2: 6 | AC2: 6 | AD2: 4 | AE2: =AD6 -> 5 | AF2: 5 | AG2: 4 | AH2: 4 | AI2: 4
A3: Mês | B3: Admissões | C3: Desligamentos | D3: Colaboradores | E3: Turnover | F3: Média | G3: Meta | I3: Mês | J3: H Program | K3: H. N. Prod. | L3: Absenteísmo | M3: Média | N3: Meta | V3: Afastamentos + Faltas (dias) | X3: 3 | Y3: 0 | Z3: 1 | AA3: 0 | AB3: 5 | AC3: 0 | AD3: 0 | AE3: 0 | AF3: 0 | AG3: 0 | AH3: 0 | AI3: 0
A4: Jan | B4: 1 | C4: 0 | D4: 5 | E4: =IF($D4=0,0,((C4+B4)/2/D4)) -> 0.1 | F4: =AVERAGE(E4) -> 0.1 | G4: =$G$2 -> 0.05 | I4: Jan | J4: 1161.6 | K4: 26.4 | L4: =IFERROR((K4/J4),"") -> 0.022727273 | M4: =AVERAGE(L4) -> 0.022727273 | N4: =$N$2 -> 0.045 | V4: Novas Contratações (Un) | X4: 1 | Y4: 2 | Z4: 2 | AA4: 1 | AB4: 0 | AC4: 0 | AD4: 1 | AE4: 0 | AF4: 0 | AG4: 0 | AH4: 1 | AI4: 1
A5: Fev | B5: 2 | C5: 2 | D5: 6 | E5: =IF($D5=0,0,((C5+B5)/2/D5)) -> 0.33333333 | F5: =AVERAGE($E$4:$E5) -> 0.21666667 | G5: =$G$2 -> 0.05 | I5: Fev | J5: 1056 | K5: 0 | L5: =IFERROR((K5/J5),"") -> 0 | M5: =AVERAGE($L$4:$L5) -> 0.011363636 | N5: =$N$2 -> 0.045 | V5: Desligamentos (Un) | X5: 0 | Y5: 2 | Z5: 2 | AA5: 1 | AB5: 0 | AC5: 2 | AD5: 0 | AE5: 0 | AF5: 1 | AG5: 0 | AH5: 1 | AI5: 2
A6: Mar | B6: 2 | C6: 2 | D6: 6 | E6: =IF($D6=0,0,((C6+B6)/2/D6)) -> 0.33333333 | F6: =AVERAGE($E$4:$E6) -> 0.25555556 | G6: =$G$2 -> 0.05 | I6: Mar | J6: 1108.8 | K6: 8.8 | L6: =IFERROR((K6/J6),"") -> 0.0079365079 | M6: =AVERAGE($L$4:$L6) -> 0.01022126 | N6: =$N$2 -> 0.045 | V6: Efetivo Final (Un) | X6: =X2+X4-X5 -> 6 | Y6: =Y2+Y4-Y5 -> 6 | Z6: =Z2+Z4-Z5 -> 6 | AA6: =AA2+AA4-AA5 -> 6 | AB6: =AB2+AB4-AB5 -> 6 | AC6: =AC2+AC4-AC5 -> 4 | AD6: =AD2+AD4-AD5 -> 5 | AE6: =AE2+AE4-AE5 -> 5 | ... AI6: =AI2+AI4-AI5 -> 3
A7: Abr | B7: 1 | C7: 1 | D7: 6 | E7: =IF($D7=0,0,((C7+B7)/2/D7)) -> 0.16666667 | F7: =AVERAGE($E$4:$E7) -> 0.23333333 | G7: =$G$2 -> 0.05 | I7: Abr | J7: 1267.2 | K7: 0 | L7: =IFERROR((K7/J7),"") -> 0 | M7: =AVERAGE($L$4:$L7) -> 0.0076659452 | N7: =$N$2 -> 0.045 | V7: Efetivo Médio | X7: =(X2+X6)/2 -> 5.5 | Y7: =(Y2+Y6)/2 -> 6 | Z7: =(Z2+Z6)/2 -> 6 | AA7: =(AA2+AA6)/2 -> 6 | AB7: =(AB2+AB6)/2 -> 6 | AC7: =(AC2+AC6)/2 -> 5 | AD7: =(AD2+AD6)/2 -> 4.5 | AE7: =(AE2+AE6)/2 -> 5 | ... AI7: =(AI2+AI6)/2 -> 3.5
A8: Mai | B8: 0 | C8: 0 | D8: 6 | E8: =IF($D8=0,0,((C8+B8)/2/D8)) -> 0 | F8: =AVERAGE($E$4:$E8) -> 0.18666667 | G8: =$G$2 -> 0.05 | I8: Mai | J8: 1161.6 | K8: 44 | L8: =IFERROR((K8/J8),"") -> 0.037878788 | M8: =AVERAGE($L$4:$L8) -> 0.013708514 | N8: =$N$2 -> 0.045 | V8: Férias (dias não produtivos) | X8: ='Janeiro 25'!AP15 -> 0 | Y8: 0 | Z8: 0 | AA8: 0 | AB8: 0 | AC8: 0 | AD8: 0 | AE8: 0 | AF8: 0 | AG8: 13 | AH8: 0 | AI8: 0
A9: Jun | B9: 0 | C9: 2 | D9: 4 | E9: =IF($D9=0,0,((C9+B9)/2/D9)) -> 0.25 | F9: =AVERAGE($E$4:$E9) -> 0.19722222 | G9: =$G$2 -> 0.05 | I9: Jun | J9: 704 | K9: 0 | L9: =IFERROR((K9/J9),"") -> 0 | M9: =AVERAGE($L$4:$L9) -> 0.011423761 | N9: =$N$2 -> 0.045 | V9: Colaboradores de Férias (Un) | X9: ='Janeiro 25'!AP16 -> 0 | Y9: 0 | Z9: 0 | AA9: 0 | AB9: 0 | AC9: 0 | AD9: 0 | AE9: 0 | AF9: 0 | AG9: 1 | AH9: 0 | AI9: 0
A10: Jul | B10: 1 | C10: 0 | D10: 5 | E10: =IF($D10=0,0,((C10+B10)/2/D10)) -> 0.1 | F10: =AVERAGE($E$4:$E10) -> 0.18333333 | G10: =$G$2 -> 0.05 | I10: Jul | J10: 1012 | K10: 0 | L10: =IFERROR((K10/J10),"") -> 0 | M10: =AVERAGE($L$4:$L10) -> 0.0097917955 | N10: =$N$2 -> 0.045 | V10: Dias Úteis | X10: 22 | Y10: 20 | Z10: 21 | AA10: 24 | AB10: 22 | AC10: 20 | AD10: 23 | AE10: 21 | AF10: 22 | AG10: 23 | AH10: 21 | AI10: 22
A11: Ago | B11: 0 | C11: 0 | D11: 5 | E11: =IF($D11=0,0,((C11+B11)/2/D11)) -> 0 | F11: =AVERAGE($E$4:$E11) -> 0.16041667 | G11: =$G$2 -> 0.05 | I11: Ago | J11: 924 | K11: 0 | L11: =IFERROR((K11/J11),"") -> 0 | M11: =AVERAGE($L$4:$L11) -> 0.0085678211 | N11: =$N$2 -> 0.045 | V11: Dias Programados | X11: =X10*X7 -> 121 | Y11: =Y10*Y7 -> 120 | Z11: =Z10*Z7 -> 126 | AA11: =AA10*AA7 -> 144 | AB11: =AB10*AB7 -> 132 | AC11: =AC10*AC7 -> 100 | AD11: =AD10*AD7 -> 103.5 | AE11: =AE10*AE7 -> 105 | ... AI11: =AI10*AI7 -> 77
A12: Set | B12: 0 | C12: 1 | D12: 4 | E12: =IF($D12=0,0,((C12+B12)/2/D12)) -> 0.125 | F12: =AVERAGE($E$4:$E12) -> 0.15648148 | G12: =$G$2 -> 0.05 | I12: Set | J12: 774 | K12: 0 | L12: =IFERROR((K12/J12),"") -> 0 | M12: =AVERAGE($L$4:$L12) -> 0.0076158409 | N12: =$N$2 -> 0.045 | V12: Dias Produtivos | X12: =X11-X8 -> 121 | Y12: =Y11-Y8 -> 120 | Z12: =Z11-Z8 -> 126 | AA12: =AA11-AA8 -> 144 | AB12: =AB11-AB8 -> 132 | AC12: =AC11-AC8 -> 100 | AD12: =AD11-AD8 -> 103.5 | AE12: =AE11-AE8 -> 105 | ... AI12: =AI11-AI8 -> 77
A13: Out | B13: 0 | C13: 0 | D13: 4 | E13: =IF($D13=0,0,((C13+B13)/2/D13)) -> 0 | F13: =AVERAGE($E$4:$E13) -> 0.14083333 | G13: =$G$2 -> 0.05 | I13: Out | J13: 810 | K13: 114 | L13: =IFERROR((K13/J13),"") -> 0.14074074 | M13: =AVERAGE($L$4:$L13) -> 0.020928331 | N13: =$N$2 -> 0.045 | V13: Dias não Produtivos | X13: =X8+X3 -> 3 | Y13: =Y8+Y3 -> 0 | Z13: =Z8+Z3 -> 1 | AA13: =AA8+AA3 -> 0 | AB13: =AB8+AB3 -> 5 | AC13: =AC8+AC3 -> 0 | AD13: =AD8+AD3 -> 0 | AE13: =AE8+AE3 -> 0 | ... AI13: =AI8+AI3 -> 0
A14: Nov | B14: 1 | C14: 1 | D14: 4 | E14: =IF($D14=0,0,((C14+B14)/2/D14)) -> 0.25 | F14: =AVERAGE($E$4:$E14) -> 0.15075758 | G14: =$G$2 -> 0.05 | I14: Nov | J14: 739 | K14: 0 | L14: =IFERROR((K14/J14),"") -> 0 | M14: =AVERAGE($L$4:$L14) -> 0.019025755 | N14: =$N$2 -> 0.045 | V14: Horas Programadas | X14: =(X6*8.8)*X10 -> 1161.6 | Y14: =(Y6*8.8)*Y10 -> 1056 | Z14: =(Z6*8.8)*Z10 -> 1108.8 | AA14: =(AA6*8.8)*AA10 -> 1267.2 | AB14: =(AB6*8.8)*AB10 -> 1161.6 | AC14: =(AC6*8.8)*AC10 -> 704 | AD14: =(AD6*8.8)*AD10 -> 1012 | AE14: =(AE6*8.8)*AE10 -> 924 | ... AI14: =(AI6*8.8)*AI10 -> 580.8
A15: Dez | B15: 1 | C15: 2 | D15: 3 | E15: =IF($D15=0,0,((C15+B15)/2/D15)) -> 0.5 | F15: =AVERAGE($E$4:$E15) -> 0.17986111 | G15: =$G$2 -> 0.05 | I15: Dez | J15: =AI14 -> 580.8 | K15: =AI15 -> 0 | L15: =IFERROR((K15/J15),"") -> 0 | M15: =AVERAGE($L$4:$L15) -> 0.017440276 | N15: =$N$2 -> 0.045 | V15: Horas não Produtivas | X15: =X13*8.8 -> 26.4 | Y15: =Y13*8.8 -> 0 | Z15: =Z13*8.8 -> 8.8 | AA15: =AA13*8.8 -> 0 | AB15: =AB13*8.8 -> 44 | AC15: =AC13*8.8 -> 0 | AD15: =AD13*8.8 -> 0 | AE15: =AE13*8.8 -> 0 | ... AI15: =AI13*8.8 -> 0
A16: Cálculo: [(Nº de desligados + Nº de admitidos) / 2] / (Nº total de colaboradores). | V16: Efetivo Pessoal Mês | X16: =(X14-X15)/(8.8*X10) -> 5.8636364 | Y16: =(Y14-Y15)/(8.8*Y10) -> 6 | Z16: =(Z14-Z15)/(8.8*Z10) -> 5.952381 | AA16: =(AA14-AA15)/(8.8*AA10) -> 6 | AB16: =(AB14-AB15)/(8.8*AB10) -> 5.7727273 | AC16: =(AC14-AC15)/(8.8*AC10) -> 4 | AD16: =(AD14-AD15)/(8.8*AD10) -> 5 | AE16: =(AE14-AE15)/(8.8*AE10) -> 5 | ... AI16: =(AI14-AI15)/(8.8*AI10) -> 3
V17: Taxa de Absenteísmo | X17: =IFERROR((X15/X14),"") -> 0.022727273 | Y17: =IFERROR((Y15/Y14),"") -> 0 | Z17: =IFERROR((Z15/Z14),"") -> 0.0079365079 | AA17: =IFERROR((AA15/AA14),"") -> 0 | AB17: =IFERROR((AB15/AB14),"") -> 0.037878788 | AC17: =IFERROR((AC15/AC14),"") -> 0 | AD17: =IFERROR((AD15/AD14),"") -> 0 | AE17: =IFERROR((AE15/AE14),"") -> 0 | ... AI17: =IFERROR((AI15/AI14),"") -> 0

Sheet ADM_Cadastro
B2: Funcionário | C2: Nome do Funcionário | D2: Departamento | E2: Admissão | F2: Demissão
B3: 1 | C3: LEANDRO PINHEIRO DOS SANTO | D3: ADM | E3: 44599
B4: 2 | C4: SAMUEL APOLINÁRIO | D4: ADM | E4: 45702
B5: 3 | C5: SILVANIA BARBOSA ALVES | D5: ADM | E5: 45736
B6: 4 | C6: MANOELA SILVA | D6: ADM | E6: 46043
B7: 5 | C7: FELIPE ROCHA | D7: ADM | E7: 46055 | F7: 46129
B8: 6 | C8: HENRIQUE CAZEDEI | D8: ADM | E8: 46055

Sheet Rotatividade 2026
A1: Turnover (Rotatividade de Pessoal) | I1: Absenteísmo (Ausências no Trabalho) | Q1: Análise de indicadores | R1: Jan | S1: Fev | T1: Mar | U1: Abr | V1: Mai | W1: Jun | X1: Jul | Y1: Ago | Z1: Set | AA1: Out | AB1: Nov | AC1: Dez
A2: Ano: | D2: 2026 | F2: Meta: | G2: 0.05 | I2: Ano: | L2: 2026 | M2: Meta: | N2: 0.045 | Q2: Efetivo Inicial (Un) | R2: 3 | S2: =R6 -> 4 | T2: =S6 -> 6 | U2: =T6 -> 6 | V2: =U6 -> 5 | W2: =V6 -> 5 | X2: =W6 -> 5 | Y2: =X6 -> 5 | Z2: =Y6 -> 5 | ... AC2: =AB6 -> 5
A3: Mês | B3: Admissões | C3: Desligamentos | D3: Colaboradores | E3: Turnover | F3: Média | G3: Meta | I3: Mês | J3: H Program | K3: H. N. Prod. | L3: Absenteísmo | M3: Média | N3: Meta | Q3: Afastamentos + Faltas (dias) | R3: 0 | S3: 0 | T3: 0 | U3: 10
A4: Jan | B4: 1 | C4: 0 | D4: 4 | E4: =Table_46[[#This Row],[Desligamentos]]/Table_46[[#This Row],[Colaboradores]] -> 0 | F4: =AVERAGE(E4) -> 0 | G4: =$G$2 -> 0.05 | I4: Jan | J4: =R14 -> 739.2 | K4: =R15 -> 0 | L4: =IFERROR((K4/J4),"") -> 0 | M4: =AVERAGE(L4) -> 0 | N4: =$N$2 -> 0.045 | Q4: Novas Contratações (Un) | R4: 1 | S4: 2 | T4: 0 | U4: 0
A5: Fev | B5: 2 | C5: 0 | D5: 6 | E5: =Table_46[[#This Row],[Desligamentos]]/Table_46[[#This Row],[Colaboradores]] -> 0 | F5: =AVERAGE($E$4:$E5) -> 0 | G5: =$G$2 -> 0.05 | I5: Fev | J5: =S14 -> 1003.2 | K5: =S15 -> 0 | L5: =IFERROR((K5/J5),"") -> 0 | M5: =AVERAGE($L$4:$L5) -> 0 | N5: =$N$2 -> 0.045 | Q5: Desligamentos (Un) | R5: 0 | S5: 0 | T5: 0 | U5: 1
A6: Mar | B6: 0 | C6: 0 | D6: 6 | E6: =Table_46[[#This Row],[Desligamentos]]/Table_46[[#This Row],[Colaboradores]] -> 0 | F6: =AVERAGE($E$4:$E6) -> 0 | G6: =$G$2 -> 0.05 | I6: Mar | J6: =T14 -> 1161.6 | K6: =T15 -> 0 | L6: =IFERROR((K6/J6),"") -> 0 | M6: =AVERAGE($L$4:$L6) -> 0 | N6: =$N$2 -> 0.045 | Q6: Efetivo Final (Un) | R6: =R2+R4-R5 -> 4 | S6: =S2+S4-S5 -> 6 | T6: =T2+T4-T5 -> 6 | U6: =U2+U4-U5 -> 5 | V6: =V2+V4-V5 -> 5 | W6: =W2+W4-W5 -> 5 | X6: =X2+X4-X5 -> 5 | Y6: =Y2+Y4-Y5 -> 5 | ... AC6: =AC2+AC4-AC5 -> 5
A7: Abr | B7: 0 | C7: 1 | D7: 5 | E7: =Table_46[[#This Row],[Desligamentos]]/Table_46[[#This Row],[Colaboradores]] -> 0.2 | F7: =AVERAGE($E$4:$E7) -> 0.05 | G7: =$G$2 -> 0.05 | I7: Abr | J7: =U14 -> 880 | K7: =U15 -> 88 | L7: =IFERROR((K7/J7),"") -> 0.1 | M7: =AVERAGE($L$4:$L7) -> 0.025 | N7: =$N$2 -> 0.045 | Q7: Efetivo Médio | R7: =(R2+R6)/2 -> 3.5 | S7: =(S2+S6)/2 -> 5 | T7: =(T2+T6)/2 -> 6 | U7: =(U2+U6)/2 -> 5.5 | V7: =(V2+V6)/2 -> 5 | W7: =(W2+W6)/2 -> 5 | X7: =(X2+X6)/2 -> 5 | Y7: =(Y2+Y6)/2 -> 5 | ... AC7: =(AC2+AC6)/2 -> 5
A8: Mai | E8: =Table_46[[#This Row],[Desligamentos]]/Table_46[[#This Row],[Colaboradores]] -> #DIV/0! | F8: =AVERAGE($E$4:$E8) -> #DIV/0! | G8: =$G$2 -> 0.05 | I8: Mai | M8: =AVERAGE($L$4:$L8) -> 0.025 | N8: =$N$2 -> 0.045 | Q8: Férias (dias não produtivos) | R8: 0 | S8: 0 | T8: 0 | U8: 0
A9: Jun | E9: =Table_46[[#This Row],[Desligamentos]]/Table_46[[#This Row],[Colaboradores]] -> #DIV/0! | F9: =AVERAGE($E$4:$E9) -> #DIV/0! | G9: =$G$2 -> 0.05 | I9: Jun | M9: =AVERAGE($L$4:$L9) -> 0.025 | N9: =$N$2 -> 0.045 | Q9: Colaboradores de Férias (Un) | R9: 0 | S9: 0 | T9: 0 | U9: 0
A10: Jul | E10: =Table_46[[#This Row],[Desligamentos]]/Table_46[[#This Row],[Colaboradores]] -> #DIV/0! | F10: =AVERAGE($E$4:$E10) -> #DIV/0! | G10: =$G$2 -> 0.05 | I10: Jul | M10: =AVERAGE($L$4:$L10) -> 0.025 | N10: =$N$2 -> 0.045 | Q10: Dias Úteis | R10: 21 | S10: 19 | T10: 22 | U10: 20
A11: Ago | E11: =Table_46[[#This Row],[Desligamentos]]/Table_46[[#This Row],[Colaboradores]] -> #DIV/0! | F11: =AVERAGE($E$4:$E11) -> #DIV/0! | G11: =$G$2 -> 0.05 | I11: Ago | M11: =AVERAGE($L$4:$L11) -> 0.025 | N11: =$N$2 -> 0.045 | Q11: Dias Programados | R11: =R10*R7 -> 73.5 | S11: =S10*S7 -> 95 | T11: =T10*T7 -> 132 | U11: =U10*U7 -> 110
A12: Set | E12: =Table_46[[#This Row],[Desligamentos]]/Table_46[[#This Row],[Colaboradores]] -> #DIV/0! | F12: =AVERAGE($E$4:$E12) -> #DIV/0! | G12: =$G$2 -> 0.05 | I12: Set | M12: =AVERAGE($L$4:$L12) -> 0.025 | N12: =$N$2 -> 0.045 | Q12: Dias Produtivos | R12: =R11-R8 -> 73.5 | S12: =S11-S8 -> 95 | T12: =T11-T8 -> 132 | U12: =U11-U8 -> 110
A13: Out | E13: =Table_46[[#This Row],[Desligamentos]]/Table_46[[#This Row],[Colaboradores]] -> #DIV/0! | F13: =AVERAGE($E$4:$E13) -> #DIV/0! | G13: =$G$2 -> 0.05 | I13: Out | M13: =AVERAGE($L$4:$L13) -> 0.025 | N13: =$N$2 -> 0.045 | Q13: Dias não Produtivos | R13: =R8+R3 -> 0 | S13: =S8+S3 -> 0 | T13: =T8+T3 -> 0 | U13: =U8+U3 -> 10
A14: Nov | E14: =Table_46[[#This Row],[Desligamentos]]/Table_46[[#This Row],[Colaboradores]] -> #DIV/0! | F14: =AVERAGE($E$4:$E14) -> #DIV/0! | G14: =$G$2 -> 0.05 | I14: Nov | M14: =AVERAGE($L$4:$L14) -> 0.025 | N14: =$N$2 -> 0.045 | Q14: Horas Programadas | R14: =(R6*8.8)*R10 -> 739.2 | S14: =(S6*8.8)*S10 -> 1003.2 | T14: =(T6*8.8)*T10 -> 1161.6 | U14: =(U6*8.8)*U10 -> 880
A15: Dez | E15: =Table_46[[#This Row],[Desligamentos]]/Table_46[[#This Row],[Colaboradores]] -> #DIV/0! | F15: =AVERAGE($E$4:$E15) -> #DIV/0! | G15: =$G$2 -> 0.05 | I15: Dez | M15: =AVERAGE($L$4:$L15) -> 0.025 | N15: =$N$2 -> 0.045 | Q15: Horas não Produtivas | R15: =R13*8.8 -> 0 | S15: =S13*8.8 -> 0 | T15: =T13*8.8 -> 0 | U15: =U13*8.8 -> 88
A16: Cálculo: [(Nº de desligados + Nº de admitidos) / 2] / (Nº total de colaboradores). | Q16: Efetivo Pessoal Mês | R16: =(R14-R15)/(8.8*R10) -> 4 | S16: =(S14-S15)/(8.8*S10) -> 6 | T16: =(T14-T15)/(8.8*T10) -> 6 | U16: =(U14-U15)/(8.8*U10) -> 4.5

Sheet Janeiro 25
H1: Atestados | M1: Faltas | O1: Férias
B2: Funcionário | C2: Nome do Funcionário | D2: Departamento | E2: Admissão | F2: Demissão | G2: Afastamento | H2: Início | I2: Fim | J2: Início | K2: Fim | L2: Dias | M2: Faltas | N2: Dias | O2: Início | P2: Fim | Q2: Dias | R2: Observação
B3: 7 | C3: AUGUSTO CESAR DA SILVA FILHO | D3: ADM | E3: 45546 | L3: 0 | N3: 0 | Q3: 0 | T3: Início Colab | U3: 5
B4: 5 | C4: JOSE OLIVEIRA JUNIOR | D4: ADM | E4: 45667 | L4: 0 | N4: 0 | Q4: 0 | T4: Admissão | U4: 1
B5: 2 | C5: LEANDRO PINHEIRO DOS SANTO | D5: ADM | E5: 44599 | L5: 0 | N5: 0 | Q5: 0 | T5: Demissão | U5: 0
B6: 6 | C6: LORENA DIAS ALMEIDA | D6: ADM | E6: 45630 | L6: 0 | N6: 0 | Q6: 0 | T6: Fim Colab | U6: =U3+U4-U5 -> 6
B7: 8 | C7: RAFAELA REGINA TAMANHONI | D7: ADM | E7: 45567 | H7: 45686 | I7: 45688 | L7: 3 | N7: 0 | Q7: 0
B8: 3 | C8: SAMY HERCULANO PINTO | D8: ADM | E8: 44602 | L8: 0 | N8: 0 | Q8: 0 | T8: Sócio | U8: 2
L9: =SUM(L3:L8) -> 3 | N9: =SUM(N3:N8) -> 0 | Q9: =SUM(Q3:Q8) -> 0 | T9: Total | U9: =U6+U8 -> 8
T11: Afastamentos
T12: Atestados | U12: =L9 -> 3
T13: Faltas | U13: =N9 -> 0
T15: Férias | U15: =Q9 -> 0
T16: Colaboradores | U16: 0
T18: Dias Úteis | U18: 22

Sheet Fevereiro 25
H1: Atestados | M1: Faltas | O1: Férias
B2: Funcionário | C2: Nome do Funcionário | D2: Departamento | E2: Admissão | F2: Demissão | G2: Afastamento | H2: Início | I2: Fim | J2: Início | K2: Fim | L2: Dias | M2: Faltas | N2: Dias | O2: Início | P2: Fim | Q2: Dias | R2: Observação
B3: 4 | C3: AUGUSTO CESAR DA SILVA FILHO | D3: ADM | E3: 45546 | L3: 0 | N3: 0 | Q3: 0 | T3: Início Colab | U3: 6
B4: 5 | C4: JOSE OLIVEIRA JUNIOR | D4: ADM | E4: 45667 | F4: 45695 | L4: 0 | N4: 0 | Q4: 0 | T4: Admissão | U4: 2
B5: 2 | C5: LEANDRO PINHEIRO DOS SANTO | D5: ADM | E5: 44599 | L5: 0 | N5: 0 | Q5: 0 | T5: Demissão | U5: 2
B6: 6 | C6: LORENA DIAS ALMEIDA | D6: ADM | E6: 45630 | L6: 0 | N6: 0 | Q6: 0 | T6: Fim Colab | U6: =U3+U4-U5 -> 6
B7: 7 | C7: MARLY DA SILVA VALANDRO | D7: ADM | E7: 45693 | L7: 0 | N7: 0 | Q7: 0
B8: 8 | C8: RAFAELA REGINA TAMANHONI | D8: ADM | E8: 45567 | F8: 45691 | L8: 0 | N8: 0 | Q8: 0 | T8: Sócio | U8: 2
B9: 9 | C9: SAMUEL APOLINÁRIO | D9: ADM | E9: 45702 | L9: 0 | N9: 0 | Q9: 0 | T9: Total | U9: =U6+U8 -> 8
B10: 3 | C10: SAMY HERCULANO PINTO | D10: ADM | E10: 44602 | L10: 0 | N10: 0 | Q10: 0
L11: =SUM(L3:L10) -> 0 | N11: =SUM(N3:N10) -> 0 | Q11: =SUM(Q3:Q10) -> 0 | T11: Afastamentos
T12: Atestados | U12: =L11 -> 0
T13: Faltas | U13: =N11 -> 0
T15: Férias | U15: =Q11 -> 0
T16: Colaboradores | U16: 0
T18: Dias Úteis | U18: 20

Sheet Março 25
H1: Atestados | M1: Faltas | O1: Férias
B2: Funcionário | C2: Nome do Funcionário | D2: Departamento | E2: Admissão | F2: Demissão | G2: Afastamento | H2: Início | I2: Fim | J2: Início | K2: Fim | L2: Dias | M2: Faltas | N2: Dias | O2: Início | P2: Fim | Q2: Dias | R2: Observação
B3: 4 | C3: AUGUSTO CESAR DA SILVA FILHO | D3: ADM | E3: 45546 | F3: 45742 | L3: 0 | N3: 0 | Q3: 0 | T3: Início Colab | U3: 6
B4: 2 | C4: LEANDRO PINHEIRO DOS SANTO | D4: ADM | E4: 44599 | L4: 0 | N4: 0 | Q4: 0 | T4: Admissão | U4: 2
B5: 6 | C5: LORENA DIAS ALMEIDA | D5: ADM | E5: 45630 | F5: 45719 | L5: 0 | N5: 0 | Q5: 0 | R5: pedido de demissão | T5: Demissão | U5: 2
B6: 7 | C6: MARLY DA SILVA VALANDRO | D6: ADM | E6: 45693 | L6: 0 | N6: 0 | Q6: 0 | T6: Fim Colab | U6: =U3+U4-U5 -> 6
B7: 9 | C7: SAMUEL APOLINÁRIO | D7: ADM | E7: 45702 | L7: 0 | N7: 0 | Q7: 0
B8: 3 | C8: SAMY HERCULANO PINTO | D8: ADM | E8: 44602 | H8: 45741 | I8: 45741 | L8: 1 | N8: 0 | Q8: 0 | T8: Sócio | U8: 2
B9: 11 | C9: SILVANIA BARBOSA ALVES | D9: ADM | E9: 45736 | L9: 0 | N9: 0 | Q9: 0 | T9: Total | U9: =U6+U8 -> 8
B10: 10 | C10: VINICIUS ABRAO SACRAMENTO | D10: ADM | E10: 45734 | L10: 0 | N10: 0 | Q10: 0
L11: =SUM(L3:L8) -> 1 | N11: =SUM(N3:N8) -> 0 | Q11: =SUM(Q3:Q8) -> 0 | T11: Afastamentos
T12: Atestados | U12: =L11 -> 1
T13: Faltas | U13: =N11 -> 0
T15: Férias | U15: =Q11 -> 0
T16: Colaboradores | U16: 0
T18: Dias Úteis | U18: 21

Sheet Abril 25
H1: Atestados | M1: Faltas | O1: Férias
B2: Funcionário | C2: Nome do Funcionário | D2: Departamento | E2: Admissão | F2: Demissão | G2: Afastamento | H2: Início | I2: Fim | J2: Início | K2: Fim | L2: Dias | M2: Faltas | N2: Dias | O2: Início | P2: Fim | Q2: Dias | R2: Observação | T2: Início Colab | U2: ='Março 25'!U6 -> 6
B3: 2 | C3: LEANDRO PINHEIRO DOS SANTO | D3: ADM | E3: 44599 | L3: 0 | N3: 0 | Q3: 0 | T3: Admissão | U3: 1
B4: 11 | C4: DIOGO GAVA | D4: ADM | E4: 45770 | L4: 0 | N4: 0 | Q4: 0 | T4: Demissão | U4: 1
B5: 7 | C5: MARLY DA SILVA VALANDRO | D5: ADM | E5: 45693 | L5: 0 | N5: 0 | Q5: 0 | T5: Fim Colab | U5: =U2+U3-U4 -> 6
B6: 8 | C6: SAMUEL APOLINÁRIO | D6: ADM | E6: 45702 | L6: 0 | N6: 0 | Q6: 0
B7: 3 | C7: SAMY HERCULANO PINTO | D7: ADM | E7: 44602 | F7: 45760 | L7: 0 | N7: 0 | Q7: 0 | T7: Sócio | U7: 2
B8: 10 | C8: SILVANIA BARBOSA ALVES | D8: ADM | E8: 45736 | L8: 0 | N8: 0 | Q8: 0 | T8: Total | U8: =U5+U7 -> 8
B9: 9 | C9: VINICIUS ABRAO SACRAMENTO | D9: ADM | E9: 45734 | L9: 0 | N9: 0 | Q9: 0
L10: =SUM(L3:L7) -> 0 | N10: =SUM(N3:N7) -> 0 | Q10: =SUM(Q3:Q7) -> 0 | T10: Afastamentos
T11: Atestados | U11: =L10 -> 0
T12: Faltas | U12: =N10 -> 0
T14: Férias | U14: =Q10 -> 0
T15: Colaboradores | U15: 0
T17: Dias Úteis | U17: =#REF! -> #REF!

Sheet Maio 25
H1: Atestados | M1: Faltas | O1: Férias
B2: Funcionário | C2: Nome do Funcionário | D2: Departamento | E2: Admissão | F2: Demissão | G2: Afastamento | H2: Início | I2: Fim | J2: Início | K2: Fim | L2: Dias | M2: Faltas | N2: Dias | O2: Início | P2: Fim | Q2: Dias | R2: Observação | T2: Início Colab | U2: ='Abril 25'!U5 -> 6
B3: 2 | C3: LEANDRO PINHEIRO DOS SANTO | D3: ADM | E3: 44599 | L3: 0 | N3: 0 | Q3: 0 | T3: Admissão | U3: 0
B4: 11 | C4: DIOGO GAVA | D4: ADM | E4: 45770 | H4: 45804 | I4: 45805 | L4: 2 | N4: 0 | Q4: 0 | T4: Demissão | U4: 0
B5: 7 | C5: MARLY DA SILVA VALANDRO | D5: ADM | E5: 45693 | H5: 45782 | I5: 45784 | L5: 3 | N5: 0 | Q5: 0 | T5: Fim Colab | U5: =U2+U3-U4 -> 6
B6: 8 | C6: SAMUEL APOLINÁRIO | D6: ADM | E6: 45702 | L6: 0 | N6: 0 | Q6: 0
B7: 10 | C7: SILVANIA BARBOSA ALVES | D7: ADM | E7: 45736 | L7: 0 | N7: 0 | Q7: 0 | T7: Sócio | U7: 2
B8: 9 | C8: VINICIUS ABRAO SACRAMENTO | D8: ADM | E8: 45734 | L8: 0 | N8: 0 | Q8: 0 | T8: Total | U8: =U5+U7 -> 8
L9: =SUM(L3:L6) -> 5 | N9: =SUM(N3:N6) -> 0 | Q9: =SUM(Q3:Q6) -> 0
T10: Afastamentos
T11: Atestados | U11: 5
T12: Faltas | U12: =N9 -> 0
T14: Férias | U14: =Q9 -> 0
T15: Colaboradores | U15: 0
T17: Dias Úteis | U17: 20

Sheet Junho 25
H1: Atestados | M1: Faltas | O1: Férias
B2: Funcionário | C2: Nome do Funcionário | D2: Departamento | E2: Admissão | F2: Demissão | G2: Afastamento | H2: Início | I2: Fim | J2: Início | K2: Fim | L2: Dias | M2: Faltas | N2: Dias | O2: Início | P2: Fim | Q2: Dias | R2: Observação | T2: Início Colab | U2: ='Maio 25'!U5 -> 6
B3: 2 | C3: LEANDRO PINHEIRO DOS SANTO | D3: ADM | E3: 44599 | L3: 0 | N3: 0 | Q3: 0 | T3: Admissão | U3: 0
B4: 11 | C4: DIOGO GAVA | D4: ADM | E4: 45770 | F4: 45814 | L4: 0 | N4: 0 | Q4: 0 | T4: Demissão | U4: 2
B5: 7 | C5: MARLY DA SILVA VALANDRO | D5: ADM | E5: 45693 | F5: 45819 | L5: 0 | N5: 0 | Q5: 0 | T5: Fim Colab | U5: =U2+U3-U4 -> 4
B6: 9 | C6: SAMUEL APOLINÁRIO | D6: ADM | E6: 45702 | L6: 0 | N6: 0 | Q6: 0
B7: 11 | C7: SILVANIA BARBOSA ALVES | D7: ADM | E7: 45736 | L7: 0 | N7: 0 | Q7: 0 | T7: Sócio | U7: 2
B8: 10 | C8: VINICIUS ABRAO SACRAMENTO | D8: ADM | E8: 45734 | L8: 0 | N8: 0 | Q8: 0 | T8: Total | U8: =U5+U7 -> 6
L9: =SUM(L3:L6) -> 0 | N9: =SUM(N3:N6) -> 0 | Q9: =SUM(Q3:Q6) -> 0
T10: Afastamentos
T11: Atestados | U11: 0
T12: Faltas | U12: =N9 -> 0
T14: Férias | U14: =Q9 -> 0
T15: Colaboradores | U15: 0
T17: Dias Úteis | U17: 20

Sheet Julho 25
H1: Atestados | M1: Faltas | O1: Férias
B2: Funcionário | C2: Nome do Funcionário | D2: Departamento | E2: Admissão | F2: Demissão | G2: Afastamento | H2: Início | I2: Fim | J2: Início | K2: Fim | L2: Dias | M2: Faltas | N2: Dias | O2: Início | P2: Fim | Q2: Dias | R2: Observação | T2: Início Colab | U2: 4
B3: 12 | C3: FERNANDO DA SILVA SALARINI | D3: ADM | E3: 45861 | L3: 0 | N3: 0 | Q3: 0 | T3: Admissão | U3: 1
B4: 2 | C4: LEANDRO PINHEIRO DOS SANTO | D4: ADM | E4: 44599 | L4: 0 | N4: 0 | Q4: 0 | T4: Demissão | U4: 0
B5: 9 | C5: SAMUEL APOLINÁRIO | D5: ADM | E5: 45702 | L5: 0 | N5: 0 | Q5: 0 | T5: Fim Colab | U5: =U2+U3-U4 -> 5
B6: 11 | C6: SILVANIA BARBOSA ALVES | D6: ADM | E6: 45736 | L6: 0 | N6: 0 | Q6: 0
B7: 10 | C7: VINICIUS ABRAO SACRAMENTO | D7: ADM | E7: 45734 | L7: 0 | N7: 0 | Q7: 0 | T7: Sócio | U7: 2
L8: =SUM(L4:L5) -> 0 | N8: =SUM(N4:N5) -> 0 | Q8: =SUM(Q4:Q5) -> 0 | T8: Total | U8: =U5+U7 -> 7
T10: Afastamentos
T11: Atestados | U11: 0
T12: Faltas | U12: =N8 -> 0
T14: Férias | U14: =Q8 -> 0
T15: Colaboradores | U15: 0
T17: Dias Úteis | U17: 23

Sheet Outubro 2025
H1: Atestados | M1: Faltas | O1: Férias
B2: Funcionário | C2: Nome do Funcionário | D2: Departamento | E2: Admissão | F2: Demissão | G2: Afastamento | H2: Início | I2: Fim | J2: Início | K2: Fim | L2: Dias | M2: Faltas | N2: Dias | O2: Início | P2: Fim | Q2: Dias | R2: Observação | T2: Início Colab | U2: 4
B3: 2 | C3: LEANDRO PINHEIRO DOS SANTO | D3: ADM | E3: 44599 | L3: 0 | N3: 0 | Q3: 0 | T3: Admissão | U3: 1
B4: 9 | C4: SAMUEL APOLINÁRIO | D4: ADM | E4: 45702 | L4: 0 | N4: 0 | Q4: 0 | T4: Demissão | U4: 1
B5: 11 | C5: SILVANIA BARBOSA ALVES | D5: ADM | E5: 45736 | L5: 0 | N5: 0 | Q5: 0 | T5: Fim Colab | U5: =U2+U3-U4 -> 4
B6: 11 | C6: TATIANI | D6: ADM | E6: 45964 | L6: 0 | N6: 0 | Q6: 0
B7: 10 | C7: VINICIUS ABRAO SACRAMENTO | D7: ADM | E7: 45734 | F7: 45975 | L7: 0 | N7: 0 | Q7: 0
L8: =SUM(L3:L4) -> 0 | N8: =SUM(N3:N4) -> 0 | Q8: =SUM(Q3:Q4) -> 0 | T8: Sócio | U8: 2
T9: Total | U9: =U5+U8 -> 6
T11: Afastamentos
T12: Atestados | U12: 0
T13: Faltas | U13: =N8 -> 0
T15: Férias | U15: =Q8 -> 0
T16: Colaboradores | U16: 11
T18: Dias Úteis | U18: 21

Sheet Novembro 25
H1: Atestados | M1: Faltas | O1: Férias
B2: Funcionário | C2: Nome do Funcionário | D2: Departamento | E2: Admissão | F2: Demissão | G2: Afastamento | H2: Início | I2: Fim | J2: Início | K2: Fim | L2: Dias | M2: Faltas | N2: Dias | O2: Início | P2: Fim | Q2: Dias | R2: Observação | T2: Início Colab | U2: 4
B3: 2 | C3: LEANDRO PINHEIRO DOS SANTO | D3: ADM | E3: 44599 | L3: 0 | N3: 0 | Q3: 0 | T3: Admissão | U3: 1
B4: 9 | C4: SAMUEL APOLINÁRIO | D4: ADM | E4: 45702 | L4: 0 | N4: 0 | Q4: 0 | T4: Demissão | U4: 2
B5: 11 | C5: SILVANIA BARBOSA ALVES | D5: ADM | E5: 45736 | L5: 0 | N5: 0 | Q5: 0 | T5: Fim Colab | U5: =U2+U3-U4 -> 3
B6: 11 | C6: TATIANI | D6: ADM | E6: 45964 | F6: 46373 | L6: 0 | N6: 0 | Q6: 0
B7: 10 | C7: VIVIANE DA COSTA | D7: ADM | E7: 46364 | F7: 46371 | L7: 0 | N7: 0 | Q7: 0
L8: =SUM(L3:L4) -> 0 | N8: =SUM(N3:N4) -> 0 | Q8: =SUM(Q3:Q4) -> 0 | T8: Sócio | U8: 2
T9: Total | U9: =U5+U8 -> 5
T11: Afastamentos
T12: Atestados | U12: 0
T13: Faltas | U13: =N8 -> 0
T15: Férias | U15: =Q8 -> 0
T16: Colaboradores | U16: 0
T18: Dias Úteis | U18: 22

Sheet Janeiro 26
H1: Atestados | M1: Faltas | O1: Férias
B2: Funcionário | C2: Nome do Funcionário | D2: Departamento | E2: Admissão | F2: Demissão | G2: Afastamento | H2: Início | I2: Fim | J2: Início | K2: Fim | L2: Dias | M2: Faltas | N2: Dias | O2: Início | P2: Fim | Q2: Dias | R2: Observação | T2: Início Colab | U2: 3
B3: 2 | C3: LEANDRO PINHEIRO DOS SANTO | D3: ADM | E3: 44599 | L3: 0 | N3: 0 | Q3: 0 | T3: Admissão | U3: 1
B4: 9 | C4: SAMUEL APOLINÁRIO | D4: ADM | E4: 45702 | L4: 0 | N4: 0 | Q4: 0 | T4: Demissão | U4: 0
B5: 11 | C5: SILVANIA BARBOSA ALVES | D5: ADM | E5: 45736 | L5: 0 | N5: 0 | Q5: 0 | T5: Fim Colab | U5: =U2+U3-U4 -> 4
B6: 11 | C6: MANOELA SILVA | D6: ADM | E6: 46043 | L6: 0 | N6: 0 | Q6: 0
L7: =SUM(L3:L4) -> 0 | N7: =SUM(N3:N4) -> 0 | Q7: =SUM(Q3:Q4) -> 0
T8: Sócio | U8: 2
T9: Total | U9: =U5+U8 -> 6
T11: Afastamentos
T12: Atestados | U12: 0
T13: Faltas | U13: =N7 -> 0
T15: Férias | U15: =Q7 -> 0
T16: Colaboradores | U16: 0
T18: Dias Úteis | U18: 21

Sheet Fevereiro 26
H1: Atestados | M1: Faltas | O1: Férias
B2: Funcionário | C2: Nome do Funcionário | D2: Departamento | E2: Admissão | F2: Demissão | G2: Afastamento | H2: Início | I2: Fim | J2: Início | K2: Fim | L2: Dias | M2: Faltas | N2: Dias | O2: Início | P2: Fim | Q2: Dias | R2: Observação | T2: Início Colab | U2: 4
B3: 13 | C3: FELIPE ROCHA | D3: ADM | E3: 46055 | L3: 0 | N3: 0 | Q3: 0 | T3: Admissão | U3: 2
B4: 14 | C4: HENRIQUE CAZEDEI | D4: ADM | E4: 46055 | L4: 0 | N4: 0 | Q4: 0 | T4: Demissão | U4: 0
B5: 2 | C5: LEANDRO PINHEIRO DOS SANTO | D5: ADM | E5: 44599 | L5: 0 | N5: 0 | Q5: 0 | T5: Fim Colab | U5: =U2+U3-U4 -> 6
B6: 9 | C6: SAMUEL APOLINÁRIO | D6: ADM | E6: 45702 | L6: 0 | N6: 0 | Q6: 0
B7: 11 | C7: SILVANIA BARBOSA ALVES | D7: ADM | E7: 45736 | L7: 0 | N7: 0 | Q7: 0
B8: 12 | C8: MANOELA SILVA | D8: ADM | E8: 46043 | L8: 0 | N8: 0 | Q8: 0 | T8: Sócio | U8: 2
L9: =SUM(L5:L6) -> 0 | N9: =SUM(N5:N6) -> 0 | Q9: =SUM(Q5:Q6) -> 0 | T9: Total | U9: =U5+U8 -> 8
T11: Afastamentos
T12: Atestados | U12: 0
T13: Faltas | U13: =N9 -> 0
T15: Férias | U15: =Q9 -> 0
T16: Colaboradores | U16: 0
T18: Dias Úteis | U18: 20

Sheet ADM_Movimentações
B2: Funcionário | C2: Nome do Funcionário | D2: Departamento | E2: Admissão | F2: Demissão | G2: Afastamento | H2: Dias | I2: Faltas | J2: Dias | K2: Férias | L2: Dias | N2: Início Colab. | O2: 3 | Q2: Admissão | R2: =E9 -> 1 | T2: Faltas | U2: =J9 -> 13 | Y2: Janeiro 2026 | AE2: D. Produtivo | AF2: =(U8-U3-U2-R5) -> 60.5
B3: 2 | C3: LEANDRO PINHEIRO DOS SANTO | D3: ADM | H3: 0 | J3: 0 | L3: 0 | Q3: Demissão | R3: =F9 -> 0 | T3: Férias | U3: =L9 -> 0 | W3: Dom | X3: Seg | Y3: Ter | Z3: Qua | AA3: Qui | AB3: Sex | AC3: Sáb | AE3: D. N. Produt. | AF3: =U8-AF2 -> 13
B4: 9 | C4: SAMUEL APOLINÁRIO | D4: ADM | H4: 0 | J4: 0 | L4: 0 | Q4: Fim Colab | R4: =O2+R2-R3 -> 4 | T4: Colaboradores | U4: =K9 -> 0 | AA4: 46023 | AB4: 46024 | AC4: 46025 | AE4: Horas Program. | AF4: =(R4*8.8)*R7 -> 739.2
B5: 11 | C5: SILVANIA BARBOSA ALVES | D5: ADM | H5: 0 | J5: 0 | L5: 0 | Q5: Afastam. | R5: =H9 -> 0 | W5: 46026 | X5: 46027 | Y5: 46028 | Z5: 46029 | AA5: 46030 | AB5: 46031 | AC5: 46032 | AE5: H. N. Produtiva | AF5: =AF3*8.8 -> 114.4
B6: 11 | C6: MANOELA SILVA | D6: ADM | E6: 46043 | H6: 0 | I6: 01 a 20 | J6: 13 | L6: 0 | W6: 46033 | X6: 46034 | Y6: 46035 | Z6: 46036 | AA6: 46037 | AB6: 46038 | AC6: 46039 | AE6: Efetivo Pessoal | AF6: =(AF4-AF5)/(8.8*R7) -> 3.3809524
H7: 0 | J7: 0 | L7: 0 | Q7: Dias Úteis | R7: 21 | T7: Efet. Méd. | U7: =(O2+R4)/2 -> 3.5 | W7: 46040 | X7: 46041 | Y7: 46042 | Z7: 46043 | AA7: 46044 | AB7: 46045 | AC7: 46046
H8: 0 | J8: 0 | L8: 0 | Q8: Não Úteis | R8: 10 | T8: D. Program. | U8: =R7*U7 -> 73.5 | W8: 46047 | X8: 46048 | Y8: 46049 | Z8: 46050 | AA8: 46051 | AB8: 46052 | AC8: 46053
E9: =COUNTA(E3:E8) -> 1 | F9: =COUNTA(F3:F8) -> 0 | G9: =COUNTA(G3:G8) -> 0 | H9: =SUM(H3:H8) -> 0 | I9: =COUNTA(I3:I8) -> 1 | J9: =SUM(J3:J8) -> 13 | K9: =COUNTA(K3:K8) -> 0 | L9: =SUM(L3:L8) -> 0
B11: Funcionário | C11: Nome do Funcionário | D11: Departamento | E11: Admissão | F11: Demissão | G11: Afastamento | H11: Dias | I11: Faltas | J11: Dias | K11: Férias | L11: Dias | N11: Início Colab. | O11: =R4 -> 4 | Q11: Admissão | R11: =E18 -> 2 | T11: Faltas | U11: =J18 -> 0 | Y11: Fevereiro 2026 | AE11: D. Produtivo | AF11: =(U17-U12-U11-R14) -> 83
B12: 1 | C12: LEANDRO PINHEIRO DOS SANTO | D12: ADM | G12: 16 e 17 | H12: 2 | L12: 0 | Q12: Demissão | R12: =F18 -> 0 | T12: Férias | U12: =L18 -> 0 | W12: Dom | X12: Seg | Y12: Ter | Z12: Qua | AA12: Qui | AB12: Sex | AC12: Sáb | AE12: D. N. Produt. | AF12: =U17-AF11 -> 12
B13: 2 | C13: SAMUEL APOLINÁRIO | D13: ADM | G13: 16 e 17 | H13: 2 | J13: 0 | L13: 0 | Q13: Fim Colab | R13: =O11+R11-R12 -> 6 | T13: Colaboradores | U13: =K18 -> 0 | W13: 46054 | X13: 46055 | Y13: 46056 | Z13: 46057 | AA13: 46058 | AB13: 46059 | AC13: 46060 | AE13: Horas Program. | AF13: =(R13*8.8)*R16 -> 1003.2
B14: 3 | C14: SILVANIA BARBOSA ALVES | D14: ADM | G14: 16 e 17 | H14: 2 | J14: 0 | L14: 0 | Q14: Afastam. | R14: =H18 -> 12 | W14: 46061 | X14: 46062 | Y14: 46063 | Z14: 46064 | AA14: 46065 | AB14: 46066 | AC14: 46067 | AE14: H. N. Produtiva | AF14: =AF12*8.8 -> 105.6
B15: 4 | C15: MANOELA SILVA | D15: ADM | G15: 16 e 17 | H15: 2 | J15: 0 | L15: 0 | W15: 46068 | X15: 46069 | Y15: 46070 | Z15: 46071 | AA15: 46072 | AB15: 46073 | AC15: 46074 | AE15: Efetivo Pessoal | AF15: =(AF13-AF14)/(8.8*R16) -> 5.3684211
B16: 5 | C16: FELIPE ROCHA | D16: ADM | E16: 46055 | G16: 16 e 17 | H16: 2 | J16: 0 | L16: 0 | Q16: Dias Úteis | R16: 19 | T16: Efet. Méd. | U16: =(O11+R13)/2 -> 5 | W16: 46075 | X16: 46076 | Y16: 46077 | Z16: 46078 | AA16: 46079 | AB16: 46080 | AC16: 46081
B17: 6 | C17: HENRIQUE CAZEDEI | D17: ADM | E17: 46055 | G17: 16 e 17 | H17: 2 | J17: 0 | L17: 0 | Q17: Não Úteis | R17: 10 | T17: D. Program. | U17: =R16*U16 -> 95
E18: =COUNTA(E12:E17) -> 2 | F18: =COUNTA(F12:F17) -> 0 | G18: =COUNTA(G12:G17) -> 6 | H18: =SUM(H12:H17) -> 12 | I18: =COUNTA(I12:I17) -> 0 | J18: =SUM(J12:J17) -> 0 | K18: =COUNTA(K12:K17) -> 0 | L18: =SUM(L12:L17) -> 0
B20: Funcionário | C20: Nome do Funcionário | D20: Departamento | E20: Admissão | F20: Demissão | G20: Afastamento | H20: Dias | I20: Faltas | J20: Dias | K20: Férias | L20: Dias | N20: Início Colab. | O20: =R13 -> 6 | Q20: Admissão | R20: =E27 -> 0 | T20: Faltas | U20: =J27 -> 0 | Y20: Março 2026 | AE20: D. Produtivo | AF20: =(U26-U21-U20-R23) -> 132
B21: 1 | C21: LEANDRO PINHEIRO DOS SANTO | H21: 0 | J21: 0 | L21: 0 | Q21: Demissão | R21: =F27 -> 0 | T21: Férias | U21: =L27 -> 0 | W21: Dom | X21: Seg | Y21: Ter | Z21: Qua | AA21: Qui | AB21: Sex | AC21: Sáb | AE21: D. N. Produt. | AF21: =U26-AF20 -> 0
B22: 2 | C22: SAMUEL APOLINÁRIO | H22: 0 | J22: 0 | L22: 0 | Q22: Fim Colab | R22: =O20+R20-R21 -> 6 | T22: Colaboradores | U22: =K27 -> 0 | W22: 46082 | X22: 46083 | Y22: 46084 | Z22: 46085 | AA22: 46086 | AB22: 46087 | AC22: 46088 | AE22: Horas Program. | AF22: =(R22*8.8)*R25 -> 1161.6
B23: 3 | C23: SILVANIA BARBOSA ALVES | H23: 0 | J23: 0 | L23: 0 | Q23: Afastam. | R23: =H27 -> 0 | W23: 46089 | X23: 46090 | Y23: 46091 | Z23: 46092 | AA23: 46093 | AB23: 46094 | AC23: 46095 | AE23: H. N. Produtiva | AF23: =AF21*8.8 -> 0
B24: 4 | C24: MANOELA SILVA | H24: 0 | J24: 0 | L24: 0 | W24: 46096 | X24: 46097 | Y24: 46098 | Z24: 46099 | AA24: 46100 | AB24: 46101 | AC24: 46102 | AE24: Efetivo Pessoal | AF24: =(AF22-AF23)/(8.8*R25) -> 6
B25: 5 | C25: FELIPE ROCHA | H25: 0 | J25: 0 | L25: 0 | Q25: Dias Úteis | R25: 22 | T25: Efet. Méd. | U25: =(O20+R22)/2 -> 6 | W25: 46103 | X25: 46104 | Y25: 46105 | Z25: 46106 | AA25: 46107 | AB25: 46108 | AC25: 46109
B26: 6 | C26: HENRIQUE CAZEDEI | H26: 0 | J26: 0 | L26: 0 | Q26: Não Úteis | R26: 9 | T26: D. Program. | U26: =R25*U25 -> 132 | W26: 46110 | X26: 46111 | Y26: 46112
E27: =COUNTA(E21:E26) -> 0 | F27: =COUNTA(F21:F26) -> 0 | G27: =COUNTA(G21:G26) -> 0 | H27: =SUM(H21:H26) -> 0 | I27: =COUNTA(I21:I26) -> 0 | J27: =SUM(J21:J26) -> 0 | K27: =COUNTA(K21:K26) -> 0 | L27: =SUM(L21:L26) -> 0
B29: Funcionário | C29: Nome do Funcionário | D29: Departamento | E29: Admissão | F29: Demissão | G29: Afastamento | H29: Dias | I29: Faltas | J29: Dias | K29: Férias | L29: Dias | N29: Início Colab. | O29: =R22 -> 6 | Q29: Admissão | R29: =E36 -> 0 | T29: Faltas | U29: =J36 -> 9 | Y29: Abril 2026 | AE29: D. Produtivo | AF29: =(U35-U30-U29-R32) -> 101
B30: 1 | C30: LEANDRO PINHEIRO DOS SANTO | D30: ADM | H30: 0 | J30: 0 | L30: 0 | Q30: Demissão | R30: =F36 -> 1 | T30: Férias | U30: =L36 -> 0 | W30: Dom | X30: Seg | Y30: Ter | Z30: Qua | AA30: Qui | AB30: Sex | AC30: Sáb | AE30: D. N. Produt. | AF30: =U35-AF29 -> 9
B31: 2 | C31: SAMUEL APOLINÁRIO | D31: ADM | H31: 0 | J31: 0 | L31: 0 | Q31: Fim Colab | R31: =O29+R29-R30 -> 5 | T31: Colaboradores | U31: =K36 -> 0 | Z31: 46113 | AA31: 46114 | AB31: 46115 | AC31: 46116 | AE31: Horas Program. | AF31: =(R31*8.8)*R34 -> 880
B32: 3 | C32: SILVANIA BARBOSA ALVES | D32: ADM | H32: 0 | J32: 0 | L32: 0 | Q32: Afastam. | R32: =H36 -> 0 | W32: 46117 | X32: 46118 | Y32: 46119 | Z32: 46120 | AA32: 46121 | AB32: 46122 | AC32: 46123 | AE32: H. N. Produtiva | AF32: =AF30*8.8 -> 79.2
B33: 4 | C33: MANOELA SILVA | D33: ADM | H33: 0 | J33: 0 | L33: 0 | W33: 46124 | X33: 46125 | Y33: 46126 | Z33: 46127 | AA33: 46128 | AB33: 46129 | AC33: 46130 | AE33: Efetivo Pessoal | AF33: =(AF31-AF32)/(8.8*R34) -> 4.55
B34: 5 | C34: FELIPE ROCHA | D34: ADM | F34: 46129 | H34: 0 | I34: Até a saída | J34: 9 | L34: 0 | Q34: Dias Úteis | R34: 20 | T34: Efet. Méd. | U34: =(O29+R31)/2 -> 5.5 | W34: 46131 | X34: 46132 | Y34: 46133 | Z34: 46134 | AA34: 46135 | AB34: 46136 | AC34: 46137
B35: 6 | C35: HENRIQUE CAZEDEI | D35: ADM | H35: 0 | J35: 0 | L35: 0 | Q35: Não Úteis | R35: 10 | T35: D. Program. | U35: =R34*U34 -> 110 | W35: 46138 | X35: 46139 | Y35: 46140 | Z35: 46141 | AA35: 46142
E36: =COUNTA(E30:E35) -> 0 | F36: =COUNTA(F30:F35) -> 1 | G36: =COUNTA(G30:G35) -> 0 | H36: =SUM(H30:H35) -> 0 | I36: =COUNTA(I30:I35) -> 1 | J36: =SUM(J30:J35) -> 9 | K36: =COUNTA(K30:K35) -> 0 | L36: =SUM(L30:L35) -> 0
B38: Funcionário | C38: Nome do Funcionário | D38: Departamento | E38: Admissão | F38: Demissão | G38: Afastamento | H38: Dias | I38: Faltas | J38: Dias | K38: Férias | L38: Dias | N38: Início Colab. | O38: =R31 -> 5 | Q38: Admissão | R38: =E45 -> 0 | T38: Faltas | U38: =J45 -> 0 | Y38: Maio 2026 | AE38: D. Produtivo | AF38: =(U44-U39-U38-R41) -> 0
H39: 0 | J39: 0 | L39: 0 | Q39: Demissão | R39: =F45 -> 0 | T39: Férias | U39: =L45 -> 0 | W39: Dom | X39: Seg | Y39: Ter | Z39: Qua | AA39: Qui | AB39: Sex | AC39: Sáb | AE39: D. N. Produt. | AF39: =U44-AF38 -> 0
H40: 0 | J40: 0 | L40: 0 | Q40: Fim Colab | R40: =O38+R38-R39 -> 5 | T40: Colaboradores | U40: =K45 -> 0 | AB40: 46143 | AC40: 46144 | AE40: Horas Program. | AF40: =(R40*8.8)*R43 -> 0
H41: 0 | J41: 0 | L41: 0 | Q41: Afastam. | R41: =H45 -> 0 | W41: 46145 | X41: 46146 | Y41: 46147 | Z41: 46148 | AA41: 46149 | AB41: 46150 | AC41: 46151 | AE41: H. N. Produtiva | AF41: =AF39*8.8 -> 0
H42: 0 | J42: 0 | L42: 0 | W42: 46152 | X42: 46153 | Y42: 46154 | Z42: 46155 | AA42: 46156 | AB42: 46157 | AC42: 46158 | AE42: Efetivo Pessoal | AF42: =(AF40-AF41)/(8.8*R43) -> #DIV/0!
H43: 0 | J43: 0 | L43: 0 | Q43: Dias Úteis | T43: Efet. Méd. | U43: =(O38+R40)/2 -> 5 | W43: 46159 | X43: 46160 | Y43: 46161 | Z43: 46162 | AA43: 46163 | AB43: 46164 | AC43: 46165
H44: 0 | J44: 0 | L44: 0 | Q44: Não Úteis | T44: D. Program. | U44: =R43*U43 -> 0 | W44: 46166 | X44: 46167 | Y44: 46168 | Z44: 46169 | AA44: 46170 | AB44: 46171 | AC44: 46172
E45: =COUNTA(E39:E44) -> 0 | F45: =COUNTA(F39:F44) -> 0 | G45: =COUNTA(G39:G44) -> 0 | H45: =SUM(H39:H44) -> 0 | I45: =COUNTA(I39:I44) -> 0 | J45: =SUM(J39:J44) -> 0 | K45: =COUNTA(K39:K44) -> 0 | L45: =SUM(L39:L44) -> 0 | W45: 46173
B47: Funcionário | C47: Nome do Funcionário | D47: Departamento | E47: Admissão | F47: Demissão | G47: Afastamento | H47: Dias | I47: Faltas | J47: Dias | K47: Férias | L47: Dias | N47: Início Colab. | O47: =R40 -> 5 | Q47: Admissão | R47: =E54 -> 0 | T47: Faltas | U47: =J54 -> 0 | Y47: Junho 2026 | AE47: D. Produtivo | AF47: =(U53-U48-U47-R50) -> 0
H48: 0 | J48: 0 | L48: 0 | Q48: Demissão | R48: =F54 -> 0 | T48: Férias | U48: =L54 -> 0 | W48: Dom | X48: Seg | Y48: Ter | Z48: Qua | AA48: Qui | AB48: Sex | AC48: Sáb | AE48: D. N. Produt. | AF48: =U53-AF47 -> 0
H49: 0 | J49: 0 | L49: 0 | Q49: Fim Colab | R49: =O47+R47-R48 -> 5 | T49: Colaboradores | U49: =K54 -> 0 | X49: 46174 | Y49: 46175 | Z49: 46176 | AA49: 46177 | AB49: 46178 | AC49: 46179 | AE49: Horas Program. | AF49: =(R49*8.8)*R52 -> 0
H50: 0 | J50: 0 | L50: 0 | Q50: Afastam. | R50: =H54 -> 0 | W50: 46180 | X50: 46181 | Y50: 46182 | Z50: 46183 | AA50: 46184 | AB50: 46185 | AC50: 46186 | AE50: H. N. Produtiva | AF50: =AF48*8.8 -> 0
H51: 0 | J51: 0 | L51: 0 | W51: 46187 | X51: 46188 | Y51: 46189 | Z51: 46190 | AA51: 46191 | AB51: 46192 | AC51: 46193 | AE51: Efetivo Pessoal | AF51: =(AF49-AF50)/(8.8*R52) -> #DIV/0!
H52: 0 | J52: 0 | L52: 0 | Q52: Dias Úteis | T52: Efet. Méd. | U52: =(O47+R49)/2 -> 5 | W52: 46194 | X52: 46195 | Y52: 46196 | Z52: 46197 | AA52: 46198 | AB52: 46199 | AC52: 46200
H53: 0 | J53: 0 | L53: 0 | Q53: Não Úteis | T53: D. Program. | U53: =R52*U52 -> 0 | W53: 46201 | X53: 46202 | Y53: 46203
E54: =COUNTA(E48:E53) -> 0 | F54: =COUNTA(F48:F53) -> 0 | G54: =COUNTA(G48:G53) -> 0 | H54: =SUM(H48:H53) -> 0 | I54: =COUNTA(I48:I53) -> 0 | J54: =SUM(J48:J53) -> 0 | K54: =COUNTA(K48:K53) -> 0 | L54: =SUM(L48:L53) -> 0
B56: Funcionário | C56: Nome do Funcionário | D56: Departamento | E56: Admissão | F56: Demissão | G56: Afastamento | H56: Dias | I56: Faltas | J56: Dias | K56: Férias | L56: Dias | N56: Início Colab. | O56: =R49 -> 5 | Q56: Admissão | R56: =E63 -> 0 | T56: Faltas | U56: =J63 -> 0 | Y56: Julho 2026 | AE56: D. Produtivo | AF56: =(U62-U57-U56-R59) -> 0
H57: 0 | J57: 0 | L57: 0 | Q57: Demissão | R57: =F63 -> 0 | T57: Férias | U57: =L63 -> 0 | W57: Dom | X57: Seg | Y57: Ter | Z57: Qua | AA57: Qui | AB57: Sex | AC57: Sáb | AE57: D. N. Produt. | AF57: =U62-AF56 -> 0
H58: 0 | J58: 0 | L58: 0 | Q58: Fim Colab | R58: =O56+R56-R57 -> 5 | T58: Colaboradores | U58: =K63 -> 0 | Z58: 46204 | AA58: 46205 | AB58: 46206 | AC58: 46207 | AE58: Horas Program. | AF58: =(R58*8.8)*R61 -> 0
H59: 0 | J59: 0 | L59: 0 | Q59: Afastam. | R59: =H63 -> 0 | W59: 46208 | X59: 46209 | Y59: 46210 | Z59: 46211 | AA59: 46212 | AB59: 46213 | AC59: 46214 | AE59: H. N. Produtiva | AF59: =AF57*8.8 -> 0
H60: 0 | J60: 0 | L60: 0 | W60: 46215 | X60: 46216 | Y60: 46217 | Z60: 46218 | AA60: 46219 | AB60: 46220 | AC60: 46221 | AE60: Efetivo Pessoal | AF60: =(AF58-AF59)/(8.8*R61) -> #DIV/0!
H61: 0 | J61: 0 | L61: 0 | Q61: Dias Úteis | T61: Efet. Méd. | U61: =(O56+R58)/2 -> 5 | W61: 46222 | X61: 46223 | Y61: 46224 | Z61: 46225 | AA61: 46226 | AB61: 46227 | AC61: 46228
H62: 0 | J62: 0 | L62: 0 | Q62: Não Úteis | T62: D. Program. | U62: =R61*U61 -> 0 | W62: 46229 | X62: 46230 | Y62: 46231 | Z62: 46232 | AA62: 46233 | AB62: 46234
E63: =COUNTA(E57:E62) -> 0 | F63: =COUNTA(F57:F62) -> 0 | G63: =COUNTA(G57:G62) -> 0 | H63: =SUM(H57:H62) -> 0 | I63: =COUNTA(I57:I62) -> 0 | J63: =SUM(J57:J62) -> 0 | K63: =COUNTA(K57:K62) -> 0 | L63: =SUM(L57:L62) -> 0
B65: Funcionário | C65: Nome do Funcionário | D65: Departamento | E65: Admissão | F65: Demissão | G65: Afastamento | H65: Dias | I65: Faltas | J65: Dias | K65: Férias | L65: Dias | N65: Início Colab. | O65: =R58 -> 5 | Q65: Admissão | R65: =E72 -> 0 | T65: Faltas | U65: =J72 -> 0 | Y65: Agosto 2026 | AE65: D. Produtivo | AF65: =(U71-U66-U65-R68) -> 0
H66: 0 | J66: 0 | L66: 0 | Q66: Demissão | R66: =F72 -> 0 | T66: Férias | U66: =L72 -> 0 | W66: Dom | X66: Seg | Y66: Ter | Z66: Qua | AA66: Qui | AB66: Sex | AC66: Sáb | AE66: D. N. Produt. | AF66: =U71-AF65 -> 0
H67: 0 | J67: 0 | L67: 0 | Q67: Fim Colab | R67: =O65+R65-R66 -> 5 | T67: Colaboradores | U67: =K72 -> 0 | AC67: 46235 | AE67: Horas Program. | AF67: =(R67*8.8)*R70 -> 0
H68: 0 | J68: 0 | L68: 0 | Q68: Afastam. | R68: =H72 -> 0 | W68: 46236 | X68: 46237 | Y68: 46238 | Z68: 46239 | AA68: 46240 | AB68: 46241 | AC68: 46242 | AE68: H. N. Produtiva | AF68: =AF66*8.8 -> 0
H69: 0 | J69: 0 | L69: 0 | W69: 46243 | X69: 46244 | Y69: 46245 | Z69: 46246 | AA69: 46247 | AB69: 46248 | AC69: 46249 | AE69: Efetivo Pessoal | AF69: =(AF67-AF68)/(8.8*R70) -> #DIV/0!
H70: 0 | J70: 0 | L70: 0 | Q70: Dias Úteis | T70: Efet. Méd. | U70: =(O65+R67)/2 -> 5 | W70: 46250 | X70: 46251 | Y70: 46252 | Z70: 46253 | AA70: 46254 | AB70: 46255 | AC70: 46256
H71: 0 | J71: 0 | L71: 0 | Q71: Não Úteis | T71: D. Program. | U71: =R70*U70 -> 0 | W71: 46257 | X71: 46258 | Y71: 46259 | Z71: 46260 | AA71: 46261 | AB71: 46262 | AC71: 46263
E72: =COUNTA(E66:E71) -> 0 | F72: =COUNTA(F66:F71) -> 0 | G72: =COUNTA(G66:G71) -> 0 | H72: =SUM(H66:H71) -> 0 | I72: =COUNTA(I66:I71) -> 0 | J72: =SUM(J66:J71) -> 0 | K72: =COUNTA(K66:K71) -> 0 | L72: =SUM(L66:L71) -> 0 | W72: 46264 | X72: 46265
B74: Funcionário | C74: Nome do Funcionário | D74: Departamento | E74: Admissão | F74: Demissão | G74: Afastamento | H74: Dias | I74: Faltas | J74: Dias | K74: Férias | L74: Dias | N74: Início Colab. | O74: =R67 -> 5 | Q74: Admissão | R74: =E81 -> 0 | T74: Faltas | U74: =J81 -> 0
H75: 0 | J75: 0 | L75: 0 | Q75: Demissão | R75: =F81 -> 0 | T75: Férias | U75: =L81 -> 0 | Y75: Setembro 2026 | AE75: D. Produtivo | AF75: =(U81-U76-U75-R78) -> 0
H76: 0 | J76: 0 | L76: 0 | Q76: Fim Colab | R76: =O74+R74-R75 -> 5 | T76: Colaboradores | U76: =K81 -> 0 | W76: Dom | X76: Seg | Y76: Ter | Z76: Qua | AA76: Qui | AB76: Sex | AC76: Sáb | AE76: D. N. Produt. | AF76: =U81-AF75 -> 0
H77: 0 | J77: 0 | L77: 0 | Q77: Afastam. | R77: =H81 -> 0 | Y77: 46266 | Z77: 46267 | AA77: 46268 | AB77: 46269 | AC77: 46270 | AE77: Horas Program. | AF77: =(R77*8.8)*R80 -> 0
H78: 0 | J78: 0 | L78: 0 | W78: 46271 | X78: 46272 | Y78: 46273 | Z78: 46274 | AA78: 46275 | AB78: 46276 | AC78: 46277 | AE78: H. N. Produtiva | AF78: =AF76*8.8 -> 0
H79: 0 | J79: 0 | L79: 0 | Q79: Dias Úteis | T79: Efet. Méd. | U79: =(O74+R76)/2 -> 5 | W79: 46278 | X79: 46279 | Y79: 46280 | Z79: 46281 | AA79: 46282 | AB79: 46283 | AC79: 46284 | AE79: Efetivo Pessoal | AF79: =(AF77-AF78)/(8.8*R80) -> #DIV/0!
H80: 0 | J80: 0 | L80: 0 | Q80: Não Úteis | T80: D. Program. | U80: =R79*U79 -> 0 | W80: 46285 | X80: 46286 | Y80: 46287 | Z80: 46288 | AA80: 46289 | AB80: 46290 | AC80: 46291
E81: =COUNTA(E75:E80) -> 0 | F81: =COUNTA(F75:F80) -> 0 | G81: =COUNTA(G75:G80) -> 0 | H81: =SUM(H75:H80) -> 0 | I81: =COUNTA(I75:I80) -> 0 | J81: =SUM(J75:J80) -> 0 | K81: =COUNTA(K75:K80) -> 0 | L81: =SUM(L75:L80) -> 0 | W81: 46292 | X81: 46293 | Y81: 46294 | Z81: 46295
B83: Funcionário | C83: Nome do Funcionário | D83: Departamento | E83: Admissão | F83: Demissão | G83: Afastamento | H83: Dias | I83: Faltas | J83: Dias | K83: Férias | L83: Dias | N83: Início Colab. | O83: =R76 -> 5 | Q83: Admissão | R83: =E90 -> 0 | T83: Faltas | U83: =J90 -> 0 | Y83: Outubro 2026 | AE83: D. Produtivo | AF83: =(U89-U84-U83-R86) -> 0
H84: 0 | J84: 0 | L84: 0 | Q84: Demissão | R84: =F90 -> 0 | T84: Férias | U84: =L90 -> 0 | W84: Dom | X84: Seg | Y84: Ter | Z84: Qua | AA84: Qui | AB84: Sex | AC84: Sáb | AE84: D. N. Produt. | AF84: =U89-AF83 -> 0
H85: 0 | J85: 0 | L85: 0 | Q85: Fim Colab | R85: =O83+R83-R84 -> 5 | T85: Colaboradores | U85: =K90 -> 0 | AA85: 46296 | AB85: 46297 | AC85: 46298 | AE85: Horas Program. | AF85: =(R85*8.8)*R88 -> 0
H86: 0 | J86: 0 | L86: 0 | Q86: Afastam. | R86: =H90 -> 0 | W86: 46299 | X86: 46300 | Y86: 46301 | Z86: 46302 | AA86: 46303 | AB86: 46304 | AC86: 46305 | AE86: H. N. Produtiva | AF86: =AF84*8.8 -> 0
H87: 0 | J87: 0 | L87: 0 | W87: 46306 | X87: 46307 | Y87: 46308 | Z87: 46309 | AA87: 46310 | AB87: 46311 | AC87: 46312 | AE87: Efetivo Pessoal | AF87: =(AF85-AF86)/(8.8*R88) -> #DIV/0!
H88: 0 | J88: 0 | L88: 0 | Q88: Dias Úteis | T88: Efet. Méd. | U88: =(O83+R85)/2 -> 5 | W88: 46313 | X88: 46314 | Y88: 46315 | Z88: 46316 | AA88: 46317 | AB88: 46318 | AC88: 46319
H89: 0 | J89: 0 | L89: 0 | Q89: Não Úteis | T89: D. Program. | U89: =R88*U88 -> 0 | W89: 46320 | X89: 46321 | Y89: 46322 | Z89: 46323 | AA89: 46324 | AB89: 46325 | AC89: 46326
E90: =COUNTA(E84:E89) -> 0 | F90: =COUNTA(F84:F89) -> 0 | G90: =COUNTA(G84:G89) -> 0 | H90: =SUM(H84:H89) -> 0 | I90: =COUNTA(I84:I89) -> 0 | J90: =SUM(J84:J89) -> 0 | K90: =COUNTA(K84:K89) -> 0 | L90: =SUM(L84:L89) -> 0
B92: Funcionário | C92: Nome do Funcionário | D92: Departamento | E92: Admissão | F92: Demissão | G92: Afastamento | H92: Dias | I92: Faltas | J92: Dias | K92: Férias | L92: Dias | N92: Início Colab. | O92: =R85 -> 5 | Q92: Admissão | R92: =E99 -> 0 | T92: Faltas | U92: =J99 -> 0 | Y92: Novembro 2026 | AE92: D. Produtivo | AF92: =(U98-U93-U92-R95) -> 0
H93: 0 | J93: 0 | L93: 0 | Q93: Demissão | R93: =F99 -> 0 | T93: Férias | U93: =L99 -> 0 | W93: Dom | X93: Seg | Y93: Ter | Z93: Qua | AA93: Qui | AB93: Sex | AC93: Sáb | AE93: D. N. Produt. | AF93: =U98-AF92 -> 0
H94: 0 | J94: 0 | L94: 0 | Q94: Fim Colab | R94: =O92+R92-R93 -> 5 | T94: Colaboradores | U94: =K99 -> 0 | W94: 46327 | X94: 46328 | Y94: 46329 | Z94: 46330 | AA94: 46331 | AB94: 46332 | AC94: 46333 | AE94: Horas Program. | AF94: =(R94*8.8)*R97 -> 0
H95: 0 | J95: 0 | L95: 0 | Q95: Afastam. | R95: =H99 -> 0 | W95: 46334 | X95: 46335 | Y95: 46336 | Z95: 46337 | AA95: 46338 | AB95: 46339 | AC95: 46340 | AE95: H. N. Produtiva | AF95: =AF93*8.8 -> 0
H96: 0 | J96: 0 | L96: 0 | W96: 46341 | X96: 46342 | Y96: 46343 | Z96: 46344 | AA96: 46345 | AB96: 46346 | AC96: 46347 | AE96: Efetivo Pessoal | AF96: =(AF94-AF95)/(8.8*R97) -> #DIV/0!
H97: 0 | J97: 0 | L97: 0 | Q97: Dias Úteis | T97: Efet. Méd. | U97: =(O92+R94)/2 -> 5 | W97: 46348 | X97: 46349 | Y97: 46350 | Z97: 46351 | AA97: 46352 | AB97: 46353 | AC97: 46354
H98: 0 | J98: 0 | L98: 0 | Q98: Não Úteis | T98: D. Program. | U98: =R97*U97 -> 0 | W98: 46355 | X98: 46356
E99: =COUNTA(E93:E98) -> 0 | F99: =COUNTA(F93:F98) -> 0 | G99: =COUNTA(G93:G98) -> 0 | H99: =SUM(H93:H98) -> 0 | I99: =COUNTA(I93:I98) -> 0 | J99: =SUM(J93:J98) -> 0 | K99: =COUNTA(K93:K98) -> 0 | L99: =SUM(L93:L98) -> 0
B101: Funcionário | C101: Nome do Funcionário | D101: Departamento | E101: Admissão | F101: Demissão | G101: Afastamento | H101: Dias | I101: Faltas | J101: Dias | K101: Férias | L101: Dias | N101: Início Colab. | O101: =R94 -> 5 | Q101: Admissão | R101: =E108 -> 0 | T101: Faltas | U101: =J108 -> 0 | Y101: Dezembro 2026 | AE101: D. Produtivo | AF101: =(U107-U102-U101-R104) -> 0
H102: 0 | J102: 0 | L102: 0 | Q102: Demissão | R102: =F108 -> 0 | T102: Férias | U102: =L108 -> 0 | W102: Dom | X102: Seg | Y102: Ter | Z102: Qua | AA102: Qui | AB102: Sex | AC102: Sáb | AE102: D. N. Produt. | AF102: =U107-AF101 -> 0
H103: 0 | J103: 0 | L103: 0 | Q103: Fim Colab | R103: =O101+R101-R102 -> 5 | T103: Colaboradores | U103: =K108 -> 0 | Y103: 46357 | Z103: 46358 | AA103: 46359 | AB103: 46360 | AC103: 46361 | AE103: Horas Program. | AF103: =(R103*8.8)*R106 -> 0
H104: 0 | J104: 0 | L104: 0 | Q104: Afastam. | R104: =H108 -> 0 | W104: 46362 | X104: 46363 | Y104: 46364 | Z104: 46365 | AA104: 46366 | AB104: 46367 | AC104: 46368 | AE104: H. N. Produtiva | AF104: =AF102*8.8 -> 0
H105: 0 | J105: 0 | L105: 0 | W105: 46369 | X105: 46370 | Y105: 46371 | Z105: 46372 | AA105: 46373 | AB105: 46374 | AC105: 46375 | AE105: Efetivo Pessoal | AF105: =(AF103-AF104)/(8.8*R106) -> #DIV/0!
H106: 0 | J106: 0 | L106: 0 | Q106: Dias Úteis | T106: Efet. Méd. | U106: =(O101+R103)/2 -> 5 | W106: 46376 | X106: 46377 | Y106: 46378 | Z106: 46379 | AA106: 46380 | AB106: 46381 | AC106: 46382
H107: 0 | J107: 0 | L107: 0 | Q107: Não Úteis | T107: D. Program. | U107: =R106*U106 -> 0 | W107: 46383 | X107: 46384 | Y107: 46385 | Z107: 46386 | AA107: 46387
E108: =COUNTA(E102:E107) -> 0 | F108: =COUNTA(F102:F107) -> 0 | G108: =COUNTA(G102:G107) -> 0 | H108: =SUM(H102:H107) -> 0 | I108: =COUNTA(I102:I107) -> 0 | J108: =SUM(J102:J107) -> 0 | K108: =COUNTA(K102:K107) -> 0 | L108: =SUM(L102:L107) -> 0

Sheet Fopag 01 26
A2: FATURAMENTO | B2: 1908792
A3: COLABORADOR | B3: SALÁRIO | C3: PREMIOS | D3: AJ. CUSTO | E3: ALIMENTAÇÃO | F3: PLANO SAÚDE | G3: SUB. TOT. | H3: ENCARGOS | J3: SUB. TOT. | M3: PROJEÇÃO 13º / FÉRIAS | O3: SUB. TOT. | P3: TOTAL | Q3: %
H4: INSS | I4: FGTS | K4: Férias | L4: 1/3 Férias | M4: 13º SALÁRIO | N4: FÉRIAS + 1/3 | P4: GERAL | Q4: CUSTO
A5: Leandro dos Santos Pinheiro | B5: 4100 | C5: 0 | D5: 210 | E5: 840 | F5: 154.13 | G5: =SUM(B5:F5) -> 5304.13 | H5: =B5*28.8% -> 1180.8 | I5: =B5*8% -> 328 | J5: =SUM(H5:I5) -> 1508.8 | K5: =(B5/12)+((B5/12)*36.8%) -> 467.4 | L5: =(B5/12/3)+((B5/12/3)*36.8%) -> 155.8 | M5: =((B5/12)*36.8%)+(B5/12) -> 467.4 | N5: =K5+L5 -> 623.2 | O5: =SUM(M5:N5) -> 1090.6 | P5: =G5+J5+O5 -> 7903.53 | Q5: =P5/$B$2 -> 0.0041405926
A6: Manoela Siolva Caldeira | B6: 1900 | D6: 150 | E6: 600 | G6: =SUM(B6:F6) -> 2650 | H6: =B6*28.8% -> 547.2 | I6: =B6*8% -> 152 | J6: =SUM(H6:I6) -> 699.2 | K6: =B6/12 -> 158.33333 | L6: =K6/3 -> 52.777778 | M6: =((B6/12)*36.8%)+(B6/12) -> 216.6 | N6: =K6+L6 -> 211.11111 | O6: =SUM(M6:N6) -> 427.71111 | P6: =G6+J6+O6 -> 3776.9111 | Q6: =P6/$B$2 -> 0.0019786918
A7: Samuel Rodrigues de Souza | B7: 3700 | C7: 0 | D7: 210 | E7: 840 | F7: 154.13 | G7: =SUM(B7:F7) -> 4904.13 | H7: =B7*28.8% -> 1065.6 | I7: =B7*8% -> 296 | J7: =SUM(H7:I7) -> 1361.6 | K7: =B7/12 -> 308.33333 | L7: =K7/3 -> 102.77778 | M7: =((B7/12)*36.8%)+(B7/12) -> 421.8 | N7: =K7+L7 -> 411.11111 | O7: =SUM(M7:N7) -> 832.91111 | P7: =G7+J7+O7 -> 7098.6411 | Q7: =P7/$B$2 -> 0.0037189181
A8: Silvania Barbosa Alves | B8: 3600 | C8: 0 | D8: 210 | E8: 840 | F8: 453.62 | G8: =SUM(B8:F8) -> 5103.62 | H8: =B8*28.8% -> 1036.8 | I8: =B8*8% -> 288 | J8: =SUM(H8:I8) -> 1324.8 | K8: =B8/12 -> 300 | L8: =K8/3 -> 100 | M8: =((B8/12)*36.8%)+(B8/12) -> 410.4 | N8: =K8+L8 -> 400 | O8: =SUM(M8:N8) -> 810.4 | P8: =G8+J8+O8 -> 7238.82 | Q8: =P8/$B$2 -> 0.0037923566
A9: =COUNTA(A5:A8) -> 4 | B9: =SUM(B5:B8) -> 13300 | C9: =SUM(C5:C8) -> 0 | D9: =SUM(D5:D8) -> 780 | E9: =SUM(E5:E8) -> 3120 | F9: =SUM(F5:F8) -> 761.88 | G9: =SUM(G5:G8) -> 17961.88 | H9: =SUM(H5:H8) -> 3830.4 | I9: =SUM(I5:I8) -> 1064 | ... Q9: =SUM(Q5:Q8) -> 0.013630559
U10: INSS - Confirmação
A11: COLABORADOR | B11: SALÁRIO | C11: AJ. CUSTO | D11: TOTAL | E11: % | U11: Empregado | V11: 1180.42
D12: GERAL | E12: CUSTO | U12: Empresa | V12: =B32 -> 780
A13: Edmundo Vale | B13: 13348 | C13: 3000 | D13: =SUM(B13:C13) -> 16348 | E13: =D13/$B$2 -> 0.0085645791 | U13: Total | V13: =SUM(V11:V12) -> 1960.42
A14: Ricardo Oliveira | B14: 19222 | C14: 3000 | D14: =SUM(B14:C14) -> 22222 | E14: =D14/$B$2 -> 0.011641918
A15: =COUNTA(A13:A14) -> 2 | B15: =SUM(B13:B14) -> 32570 | C15: =SUM(C13:C14) -> 6000 | D15: =SUM(D13:D14) -> 38570 | E15: =AVERAGE(E13:E14) -> 0.010103249
A17: Desembolso Mensal
A18: Salário Líquido | B18: 11403.99 | C18: Fopag
A19: FGTS | B19: =I9 -> 1064
A20: INSS+RAT+TERC | B20: =H9 -> 3830.4
A21: Beneficios | B21: =C9+D9+E9+F9 -> 4661.88
A22: Pro Labore | B22: =B15 -> 32570
A23: Ajuda de Custo Diretoria | B23: =C15 -> 6000
A24: Total | B24: =SUM(B18:B23) -> 59530.27
A26: Custo Total
A27: Salários | B27: =B9 -> 13300
A28: FGTS | B28: =I9 -> 1064
A29: INSS Patronal (INSS+RAT+Terceiros) | B29: =H9 -> 3830.4
A30: Provisões | B30: =O9 -> 3161.6222
A31: Premiação | B31: =C9 -> 0
A32: Transporte | B32: =D9 -> 780
A33: Alimentação | B33: =E9 -> 3120
A34: Plano de Saúde | B34: =F9 -> 761.88
A35: Prolabore | B35: =B15 -> 32570
A36: Aj. Custo Diretoria | B36: =C15 -> 6000
A37: Total | B37: =SUM(B27:B36) -> 64587.902

Sheet Fopag 02 26
A2: FATURAMENTO | B2: 1434982
A3: COLABORADOR | B3: SALÁRIO | C3: PREMIOS | D3: AJ. CUSTO | E3: ALIMENTAÇÃO | F3: PLANO SAÚDE | G3: SUB. TOT. | H3: ENCARGOS | J3: SUB. TOT. | M3: PROJEÇÃO 13º / FÉRIAS | O3: SUB. TOT. | P3: TOTAL | Q3: %
H4: INSS | I4: FGTS | K4: Férias | L4: 1/3 Férias | M4: 13º SALÁRIO | N4: FÉRIAS + 1/3 | P4: GERAL | Q4: CUSTO
A5: Felipe Rocha | B5: 3000 | C5: 0 | D5: 200 | E5: 800 | F5: 0 | G5: =SUM(B5:F5) -> 4000 | H5: =B5*28.8% -> 864 | I5: =B5*8% -> 240 | J5: =SUM(H5:I5) -> 1104 | K5: =(B5/12)+((B5/12)*36.8%) -> 342 | L5: =(B5/12/3)+((B5/12/3)*36.8%) -> 114 | M5: =((B5/12)*36.8%)+(B5/12) -> 342 | N5: =K5+L5 -> 456 | O5: =SUM(M5:N5) -> 798 | P5: =G5+J5+O5 -> 5902 | Q5: =P5/$B$2 -> 0.0041129436
A6: Henrique Cazedey | B6: 3000 | C6: 0 | D6: 0 | E6: 0 | G6: =SUM(B6:F6) -> 3000 | H6: =B6*28.8% -> 864 | I6: =B6*8% -> 240 | J6: =SUM(H6:I6) -> 1104 | K6: =(B6/12)+((B6/12)*36.8%) -> 342 | L6: =(B6/12/3)+((B6/12/3)*36.8%) -> 114 | M6: =((B6/12)*36.8%)+(B6/12) -> 342 | N6: =K6+L6 -> 456 | O6: =SUM(M6:N6) -> 798 | P6: =G6+J6+O6 -> 4902 | Q6: =P6/$B$2 -> 0.0034160707
A7: Leandro dos Santos Pinheiro | B7: 4100 | C7: 0 | D7: 200 | E7: 800 | F7: 154.13 | G7: =SUM(B7:F7) -> 5254.13 | H7: =B7*28.8% -> 1180.8 | I7: =B7*8% -> 328 | J7: =SUM(H7:I7) -> 1508.8 | K7: =(B7/12)+((B7/12)*36.8%) -> 467.4 | L7: =(B7/12/3)+((B7/12/3)*36.8%) -> 155.8 | M7: =((B7/12)*36.8%)+(B7/12) -> 467.4 | N7: =K7+L7 -> 623.2 | O7: =SUM(M7:N7) -> 1090.6 | P7: =G7+J7+O7 -> 7853.53 | Q7: =P7/$B$2 -> 0.0054729119
A8: Manoela Siolva Caldeira | B8: 1900 | D8: 200 | E8: 800 | G8: =SUM(B8:F8) -> 2900 | H8: =B8*28.8% -> 547.2 | I8: =B8*8% -> 152 | J8: =SUM(H8:I8) -> 699.2 | K8: =B8/12 -> 158.33333 | L8: =K8/3 -> 52.777778 | M8: =((B8/12)*36.8%)+(B8/12) -> 216.6 | N8: =K8+L8 -> 211.11111 | O8: =SUM(M8:N8) -> 427.71111 | P8: =G8+J8+O8 -> 4026.9111 | Q8: =P8/$B$2 -> 0.002806245
A9: Samuel Rodrigues de Souza | B9: 3700 | C9: 0 | D9: 200 | E9: 800 | F9: 154.13 | G9: =SUM(B9:F9) -> 4854.13 | H9: =B9*28.8% -> 1065.6 | I9: =B9*8% -> 296 | J9: =SUM(H9:I9) -> 1361.6 | K9: =B9/12 -> 308.33333 | L9: =K9/3 -> 102.77778 | M9: =((B9/12)*36.8%)+(B9/12) -> 421.8 | N9: =K9+L9 -> 411.11111 | O9: =SUM(M9:N9) -> 832.91111 | P9: =G9+J9+O9 -> 7048.6411 | Q9: =P9/$B$2 -> 0.0049120066
A10: Silvania Barbosa Alves | B10: 3600 | C10: 0 | D10: 200 | E10: 800 | F10: 453.62 | G10: =SUM(B10:F10) -> 5053.62 | H10: =B10*28.8% -> 1036.8 | I10: =B10*8% -> 288 | J10: =SUM(H10:I10) -> 1324.8 | K10: =B10/12 -> 300 | L10: =K10/3 -> 100 | M10: =((B10/12)*36.8%)+(B10/12) -> 410.4 | N10: =K10+L10 -> 400 | O10: =SUM(M10:N10) -> 810.4 | P10: =G10+J10+O10 -> 7188.82 | Q10: =P10/$B$2 -> 0.0050096935
A11: =COUNTA(A6:A10) -> 5 | B11: =SUM(B5:B10) -> 19300 | C11: =SUM(C5:C10) -> 0 | D11: =SUM(D5:D10) -> 1000 | E11: =SUM(E5:E10) -> 4000 | F11: =SUM(F5:F10) -> 761.88 | G11: =SUM(G5:G10) -> 25061.88 | H11: =SUM(H5:H10) -> 5558.4 | I11: =SUM(I5:I10) -> 1544 | ... Q11: =SUM(Q5:Q10) -> 0.025729871
U12: INSS - Confirmação
A13: COLABORADOR | B13: SALÁRIO | C13: AJ. CUSTO | D13: TOTAL | E13: % | U13: Empregado | V13: 1180.42
D14: GERAL | E14: CUSTO | U14: Empresa | V14: =B34 -> 1000
A15: Edmundo Vale | B15: 13348 | C15: 3000 | D15: =SUM(B15:C15) -> 16348 | E15: =D15/$B$2 -> 0.011392477 | U15: Total | V15: =SUM(V13:V14) -> 2180.42
A16: Ricardo Oliveira | B16: 19222 | C16: 3000 | D16: =SUM(B16:C16) -> 22222 | E16: =D16/$B$2 -> 0.015485909
A17: =COUNTA(A15:A16) -> 2 | B17: =SUM(B15:B16) -> 32570 | C17: =SUM(C15:C16) -> 6000 | D17: =SUM(D15:D16) -> 38570 | E17: =AVERAGE(E15:E16) -> 0.013439193
A19: Desembolso Mensal
A20: Salário Líquido | B20: 17546.73 | C20: Fopag
A21: FGTS | B21: =I11 -> 1544
A22: INSS+RAT+TERC | B22: =H11 -> 5558.4
A23: Beneficios | B23: =C11+D11+E11+F11 -> 5761.88
A24: Pro Labore | B24: =B17 -> 32570
A25: Ajuda de Custo Diretoria | B25: =C17 -> 6000
A26: Total | B26: =SUM(B20:B25) -> 68981.01
A28: Custo Total
A29: Salários | B29: =B11 -> 19300
A30: FGTS | B30: =I11 -> 1544
A31: INSS Patronal (INSS+RAT+Terceiros) | B31: =H11 -> 5558.4
A32: Provisões | B32: =O11 -> 4757.6222
A33: Premiação | B33: =C11 -> 0
A34: Transporte | B34: =D11 -> 1000
A35: Alimentação | B35: =E11 -> 4000
A36: Plano de Saúde | B36: =F11 -> 761.88
A37: Prolabore | B37: =B17 -> 32570
A38: Aj. Custo Diretoria | B38: =C17 -> 6000
A39: Total | B39: =SUM(B29:B38) -> 75491.902

Sheet Fopag 03 26
A2: FATURAMENTO | B2: 1661970
A3: COLABORADOR | B3: SALÁRIO | C3: PREMIOS | D3: AJ. CUSTO | E3: ALIMENTAÇÃO | F3: PLANO SAÚDE | G3: SUB. TOT. | H3: ENCARGOS | J3: SUB. TOT. | M3: PROJEÇÃO 13º / FÉRIAS | O3: SUB. TOT. | P3: TOTAL | Q3: %
H4: INSS | I4: FGTS | K4: Férias | L4: 1/3 Férias | M4: 13º SALÁRIO | N4: FÉRIAS + 1/3 | P4: GERAL | Q4: CUSTO
A5: Felipe Rocha | B5: 3000 | C5: 0 | D5: 220 | E5: 880 | F5: 0 | G5: =SUM(B5:F5) -> 4100 | H5: =B5*28.8% -> 864 | I5: =B5*8% -> 240 | J5: =SUM(H5:I5) -> 1104 | K5: =(B5/12)+((B5/12)*36.8%) -> 342 | L5: =(B5/12/3)+((B5/12/3)*36.8%) -> 114 | M5: =((B5/12)*36.8%)+(B5/12) -> 342 | N5: =K5+L5 -> 456 | O5: =SUM(M5:N5) -> 798 | P5: =G5+J5+O5 -> 6002 | Q5: =P5/$B$2 -> 0.0036113769
A6: Henrique Cazedey | B6: 3000 | C6: 0 | D6: 0 | E6: 0 | G6: =SUM(B6:F6) -> 3000 | H6: =B6*28.8% -> 864 | I6: =B6*8% -> 240 | J6: =SUM(H6:I6) -> 1104 | K6: =(B6/12)+((B6/12)*36.8%) -> 342 | L6: =(B6/12/3)+((B6/12/3)*36.8%) -> 114 | M6: =((B6/12)*36.8%)+(B6/12) -> 342 | N6: =K6+L6 -> 456 | O6: =SUM(M6:N6) -> 798 | P6: =G6+J6+O6 -> 4902 | Q6: =P6/$B$2 -> 0.0029495117
A7: Leandro dos Santos Pinheiro | B7: 4100 | C7: 0 | D7: 220 | E7: 880 | F7: 154.13 | G7: =SUM(B7:F7) -> 5354.13 | H7: =B7*28.8% -> 1180.8 | I7: =B7*8% -> 328 | J7: =SUM(H7:I7) -> 1508.8 | K7: =(B7/12)+((B7/12)*36.8%) -> 467.4 | L7: =(B7/12/3)+((B7/12/3)*36.8%) -> 155.8 | M7: =((B7/12)*36.8%)+(B7/12) -> 467.4 | N7: =K7+L7 -> 623.2 | O7: =SUM(M7:N7) -> 1090.6 | P7: =G7+J7+O7 -> 7953.53 | Q7: =P7/$B$2 -> 0.0047856038
A8: Manoela Siolva Caldeira | B8: 3000 | D8: 220 | E8: 880 | G8: =SUM(B8:F8) -> 4100 | H8: =B8*28.8% -> 864 | I8: =B8*8% -> 240 | J8: =SUM(H8:I8) -> 1104 | K8: =B8/12 -> 250 | L8: =K8/3 -> 83.333333 | M8: =((B8/12)*36.8%)+(B8/12) -> 342 | N8: =K8+L8 -> 333.33333 | O8: =SUM(M8:N8) -> 675.33333 | P8: =G8+J8+O8 -> 5879.3333 | Q8: =P8/$B$2 -> 0.0035375689
A9: Samuel Rodrigues de Souza | B9: 3700 | C9: 0 | D9: 220 | E9: 880 | F9: 154.13 | G9: =SUM(B9:F9) -> 4954.13 | H9: =B9*28.8% -> 1065.6 | I9: =B9*8% -> 296 | J9: =SUM(H9:I9) -> 1361.6 | K9: =B9/12 -> 308.33333 | L9: =K9/3 -> 102.77778 | M9: =((B9/12)*36.8%)+(B9/12) -> 421.8 | N9: =K9+L9 -> 411.11111 | O9: =SUM(M9:N9) -> 832.91111 | P9: =G9+J9+O9 -> 7148.6411 | Q9: =P9/$B$2 -> 0.0043013057
A10: Silvania Barbosa Alves | B10: 3600 | C10: 0 | D10: 220 | E10: 880 | F10: 453.62 | G10: =SUM(B10:F10) -> 5153.62 | H10: =B10*28.8% -> 1036.8 | I10: =B10*8% -> 288 | J10: =SUM(H10:I10) -> 1324.8 | K10: =B10/12 -> 300 | L10: =K10/3 -> 100 | M10: =((B10/12)*36.8%)+(B10/12) -> 410.4 | N10: =K10+L10 -> 400 | O10: =SUM(M10:N10) -> 810.4 | P10: =G10+J10+O10 -> 7288.82 | Q10: =P10/$B$2 -> 0.0043856508
A11: =COUNTA(A6:A10) -> 5 | B11: =SUM(B5:B10) -> 20400 | C11: =SUM(C5:C10) -> 0 | D11: =SUM(D5:D10) -> 1100 | E11: =SUM(E5:E10) -> 4400 | F11: =SUM(F5:F10) -> 761.88 | G11: =SUM(G5:G10) -> 26661.88 | H11: =SUM(H5:H10) -> 5875.2 | I11: =SUM(I5:I10) -> 1632 | ... Q11: =SUM(Q5:Q10) -> 0.023571018
U12: INSS - Confirmação
A13: COLABORADOR | B13: SALÁRIO | C13: AJ. CUSTO | D13: TOTAL | E13: % | U13: Empregado | V13: 1180.42
D14: GERAL | E14: CUSTO | U14: Empresa | V14: =H11 -> 5875.2
A15: Edmundo Vale | B15: 13348 | C15: 3000 | D15: =SUM(B15:C15) -> 16348 | E15: =D15/$B$2 -> 0.0098365193 | U15: Total | V15: =SUM(V13:V14) -> 7055.62
A16: Ricardo Oliveira | B16: 19222 | C16: 3000 | D16: =SUM(B16:C16) -> 22222 | E16: =D16/$B$2 -> 0.013370879
A17: =COUNTA(A15:A16) -> 2 | B17: =SUM(B15:B16) -> 32570 | C17: =SUM(C15:C16) -> 6000 | D17: =SUM(D15:D16) -> 38570 | E17: =AVERAGE(E15:E16) -> 0.011603699
A19: Desembolso Mensal
A20: Salário Líquido | B20: 17904.93 | C20: Fopag
A21: FGTS | B21: =I11 -> 1632
A22: INSS+RAT+TERC | B22: =H11 -> 5875.2
A23: Beneficios | B23: =C11+D11+E11+F11 -> 6261.88
A24: Pro Labore | B24: =B17 -> 32570
A25: Ajuda de Custo Diretoria | B25: =C17 -> 6000
A26: Total | B26: =SUM(B20:B25) -> 70244.01
A28: Custo Total
A29: Salários | B29: =B11 -> 20400
A30: FGTS | B30: =I11 -> 1632
A31: INSS Patronal (INSS+RAT+Terceiros) | B31: =H11 -> 5875.2
A32: Provisões | B32: =O11 -> 5005.2444
A33: Premiação | B33: =C11 -> 0
A34: Transporte | B34: =D11 -> 1100
A35: Alimentação | B35: =E11 -> 4400
A36: Plano de Saúde | B36: =F11 -> 761.88
A37: Prolabore | B37: =B17 -> 32570
A38: Aj. Custo Diretoria | B38: =C17 -> 6000
A39: Total | B39: =SUM(B29:B38) -> 77744.324

Sheet ADM_Fopag
B2: COLABORADOR | C2: Salários | D2: Prolabore | E2: Dist. Lucro | F2: Aj. Custo | G2: Alimentação | H2: Plano Saúde | I2: Sub. Total | J2: INSS | K2: RAT | L2: Terceiros | M2: FGTS | N2: T. Encargos | O2: Férias | P2: 1/3 Férias | Q2: FGTS Férias | R2: 13º Sal | S2: FGTS 13º Sal | T2: Aviso Prévio | U2: FGTS Av. | V2: Multa FGTS | W2: Patronal | X2: T. Provisão | Y2: Total | Z2: Custo Total | AA2: 46023
B3: Leandro dos Santos Pinheiro | C3: 4100 | F3: 210 | G3: 840 | H3: 154.13 | I3: =SUM(C3:H3) -> 5304.13 | J3: =C3*20% -> 820 | K3: =C3*1.5% -> 61.5 | L3: =C3*5.8% -> 237.8 | M3: =C3*8% -> 328 | N3: =SUM(J3:M3) -> 1447.3 | O3: =C3/12 -> 341.66667 | P3: =O3/3 -> 113.88889 | Q3: =(O3+P3)*8% -> 36.444444 | R3: =C3/12 -> 341.66667 | S3: =R3*8% -> 27.333333 | T3: =C3/12 -> 341.66667 | U3: =T3*8% -> 27.333333 | V3: =(M3+Q3+S3+U3)*50% -> 209.55556 | W3: =(O3+P3+R3+T3)*27.3% -> 310.91667 | X3: =SUM(O3:W3) -> 1750.4722 | Y3: =I3+N3+X3 -> 8501.9022 | Z3: Salário | AA3: =C11 -> 13300
B4: Manoela Siolva Caldeira | C4: 1900 | F4: 150 | G4: 600 | I4: =SUM(C4:H4) -> 2650 | J4: =C4*20% -> 380 | K4: =C4*1.5% -> 28.5 | L4: =C4*5.8% -> 110.2 | M4: =C4*8% -> 152 | N4: =SUM(J4:M4) -> 670.7 | O4: =C4/12 -> 158.33333 | P4: =O4/3 -> 52.777778 | Q4: =(O4+P4)*8% -> 16.888889 | R4: =C4/12 -> 158.33333 | S4: =R4*8% -> 12.666667 | T4: =C4/12 -> 158.33333 | U4: =T4*8% -> 12.666667 | V4: =(M4+Q4+S4+U4)*50% -> 97.111111 | W4: =(O4+P4+R4+T4)*27.3% -> 144.08333 | X4: =SUM(O4:W4) -> 811.19444 | Y4: =I4+N4+X4 -> 4131.8944 | Z4: Prolabore | AA4: =D11 -> 4863
B5: Samuel Rodrigues de Souza | C5: 3700 | F5: 210 | G5: 840 | H5: 154.13 | I5: =SUM(C5:H5) -> 4904.13 | J5: =C5*20% -> 740 | K5: =C5*1.5% -> 55.5 | L5: =C5*5.8% -> 214.6 | M5: =C5*8% -> 296 | N5: =SUM(J5:M5) -> 1306.1 | O5: =C5/12 -> 308.33333 | P5: =O5/3 -> 102.77778 | Q5: =(O5+P5)*8% -> 32.888889 | R5: =C5/12 -> 308.33333 | S5: =R5*8% -> 24.666667 | T5: =C5/12 -> 308.33333 | U5: =T5*8% -> 24.666667 | V5: =(M5+Q5+S5+U5)*50% -> 189.11111 | W5: =(O5+P5+R5+T5)*27.3% -> 280.58333 | X5: =SUM(O5:W5) -> 1579.6944 | Y5: =I5+N5+X5 -> 7789.9244 | Z5: Dist. Lucro | AA5: =E11 -> 27707
B6: Silvania Barbosa Alves | C6: 3600 | F6: 210 | G6: 840 | H6: 453.62 | I6: =SUM(C6:H6) -> 5103.62 | J6: =C6*20% -> 720 | K6: =C6*1.5% -> 54 | L6: =C6*5.8% -> 208.8 | M6: =C6*8% -> 288 | N6: =SUM(J6:M6) -> 1270.8 | O6: =C6/12 -> 300 | P6: =O6/3 -> 100 | Q6: =(O6+P6)*8% -> 32 | R6: =C6/12 -> 300 | S6: =R6*8% -> 24 | T6: =C6/12 -> 300 | U6: =T6*8% -> 24 | V6: =(M6+Q6+S6+U6)*50% -> 184 | W6: =(O6+P6+R6+T6)*27.3% -> 273 | X6: =SUM(O6:W6) -> 1537 | Y6: =I6+N6+X6 -> 7911.42 | Z6: Benefício | AA6: =SUM(F11:H11) -> 8661.88
I7: =SUM(C7:H7) -> 0 | J7: =C7*20% -> 0 | K7: =C7*1.5% -> 0 | L7: =C7*5.8% -> 0 | M7: =C7*8% -> 0 | N7: =SUM(J7:M7) -> 0 | O7: =C7/12 -> 0 | P7: =O7/3 -> 0 | Q7: =(O7+P7)*8% -> 0 | R7: =C7/12 -> 0 | S7: =R7*8% -> 0 | T7: =C7/12 -> 0 | U7: =T7*8% -> 0 | V7: =(M7+Q7+S7+U7)*50% -> 0 | W7: =(O7+P7+R7+T7)*27.3% -> 0 | X7: =SUM(O7:W7) -> 0 | Y7: =I7+N7+X7 -> 0 | Z7: Patronal | AA7: =SUM(J11:L11) -> 4165.83
I8: =SUM(C8:H8) -> 0 | J8: =C8*20% -> 0 | K8: =C8*1.5% -> 0 | L8: =C8*5.8% -> 0 | M8: =C8*8% -> 0 | N8: =SUM(J8:M8) -> 0 | O8: =C8/12 -> 0 | P8: =O8/3 -> 0 | Q8: =(O8+P8)*8% -> 0 | R8: =C8/12 -> 0 | S8: =R8*8% -> 0 | T8: =C8/12 -> 0 | U8: =T8*8% -> 0 | V8: =(M8+Q8+S8+U8)*50% -> 0 | W8: =(O8+P8+R8+T8)*27.3% -> 0 | X8: =SUM(O8:W8) -> 0 | Y8: =I8+N8+X8 -> 0 | Z8: FGTS | AA8: =M11 -> 1064
B9: Edmundo Vale | D9: 1621 | E9: 11727 | F9: 2000 | I9: =SUM(C9:H9) -> 15348 | J9: =1621*11% -> 178.31 | N9: =SUM(J9:M9) -> 178.31 | Y9: =I9+N9+X9 -> 15526.31 | Z9: Provisão | AA9: =SUM(O11:W11) -> 5678.3611
B10: Ricardo Oliveira | D10: =1621*2 -> 3242 | E10: 15980 | F10: 2000 | I10: =SUM(C10:H10) -> 21222 | J10: =3242*11% -> 356.62 | N10: =SUM(J10:M10) -> 356.62 | Y10: =I10+N10+X10 -> 21578.62 | Z10: Total | AA10: =SUM(AA3:AA9) -> 65440.071
C11: =SUM(C3:C10) -> 13300 | D11: =SUM(D3:D10) -> 4863 | E11: =SUM(E3:E10) -> 27707 | F11: =SUM(F3:F10) -> 4780 | G11: =SUM(G3:G10) -> 3120 | H11: =SUM(H3:H10) -> 761.88 | I11: =SUM(I3:I10) -> 54531.88 | J11: =SUM(J3:J10) -> 3194.93 | ... X11: =SUM(X3:X10) -> 5678.3611 | Y11: =I11+N11+X11 -> 65440.071
B13: COLABORADOR | C13: Salários | D13: Prêmio | E13: Dist. Lucro | F13: Aj. Custo | G13: Alimentação | H13: Plano Saúde | I13: Sub. Total | J13: INSS | K13: RAT | L13: Terceiros | M13: FGTS | N13: T. Encargos | O13: Férias | P13: 1/3 Férias | Q13: FGTS Férias | R13: 13º Sal | S13: FGTS 13º Sal | T13: Aviso Prévio | U13: FGTS Av. | V13: Multa FGTS | W13: Patronal | X13: T. Provisão | Y13: Total | Z13: Custo Total | AA13: 46054
B14: Felipe Rocha | C14: 3000 | F14: 200 | G14: 800 | H14: 0 | I14: =SUM(C14:H14) -> 4000 | J14: =C14*20% -> 600 | K14: =C14*1.5% -> 45 | L14: =C14*5.8% -> 174 | M14: =C14*8% -> 240 | N14: =SUM(J14:M14) -> 1059 | O14: =C14/12 -> 250 | P14: =O14/3 -> 83.333333 | Q14: =(O14+P14)*8% -> 26.666667 | R14: =C14/12 -> 250 | S14: =R14*8% -> 20 | T14: =C14/12 -> 250 | U14: =T14*8% -> 20 | V14: =(M14+Q14+S14+U14)*50% -> 153.33333 | W14: =(O14+P14+R14+T14)*27.3% -> 227.5 | X14: =SUM(O14:W14) -> 1280.8333 | Y14: =I14+N14+X14 -> 6339.8333 | Z14: Salário | AA14: =C22 -> 19300
B15: Henrique Cazedey | C15: 3000 | F15: 0 | G15: 0 | I15: =SUM(C15:H15) -> 3000 | J15: =C15*20% -> 600 | K15: =C15*1.5% -> 45 | L15: =C15*5.8% -> 174 | M15: =C15*8% -> 240 | N15: =SUM(J15:M15) -> 1059 | O15: =C15/12 -> 250 | P15: =O15/3 -> 83.333333 | Q15: =(O15+P15)*8% -> 26.666667 | R15: =C15/12 -> 250 | S15: =R15*8% -> 20 | T15: =C15/12 -> 250 | U15: =T15*8% -> 20 | V15: =(M15+Q15+S15+U15)*50% -> 153.33333 | W15: =(O15+P15+R15+T15)*27.3% -> 227.5 | X15: =SUM(O15:W15) -> 1280.8333 | Y15: =I15+N15+X15 -> 5339.8333 | Z15: Prolabore | AA15: =D22 -> 4863
B16: Leandro dos Santos Pinheiro | C16: 4100 | F16: 200 | G16: 800 | H16: 154.13 | I16: =SUM(C16:H16) -> 5254.13 | J16: =C16*20% -> 820 | K16: =C16*1.5% -> 61.5 | L16: =C16*5.8% -> 237.8 | M16: =C16*8% -> 328 | N16: =SUM(J16:M16) -> 1447.3 | O16: =C16/12 -> 341.66667 | P16: =O16/3 -> 113.88889 | Q16: =(O16+P16)*8% -> 36.444444 | R16: =C16/12 -> 341.66667 | S16: =R16*8% -> 27.333333 | T16: =C16/12 -> 341.66667 | U16: =T16*8% -> 27.333333 | V16: =(M16+Q16+S16+U16)*50% -> 209.55556 | W16: =(O16+P16+R16+T16)*27.3% -> 310.91667 | X16: =SUM(O16:W16) -> 1750.4722 | Y16: =I16+N16+X16 -> 8451.9022 | Z16: Dist. Lucro | AA16: =E22 -> 27707
B17: Manoela Siolva Caldeira | C17: 1900 | F17: 200 | G17: 800 | I17: =SUM(C17:H17) -> 2900 | J17: =C17*20% -> 380 | K17: =C17*1.5% -> 28.5 | L17: =C17*5.8% -> 110.2 | M17: =C17*8% -> 152 | N17: =SUM(J17:M17) -> 670.7 | O17: =C17/12 -> 158.33333 | P17: =O17/3 -> 52.777778 | Q17: =(O17+P17)*8% -> 16.888889 | R17: =C17/12 -> 158.33333 | S17: =R17*8% -> 12.666667 | T17: =C17/12 -> 158.33333 | U17: =T17*8% -> 12.666667 | V17: =(M17+Q17+S17+U17)*50% -> 97.111111 | W17: =(O17+P17+R17+T17)*27.3% -> 144.08333 | X17: =SUM(O17:W17) -> 811.19444 | Y17: =I17+N17+X17 -> 4381.8944 | Z17: Benefício | AA17: =SUM(F22:H22) -> 11761.88
B18: Samuel Rodrigues de Souza | C18: 3700 | F18: 200 | G18: 800 | H18: 154.13 | I18: =SUM(C18:H18) -> 4854.13 | J18: =C18*20% -> 740 | K18: =C18*1.5% -> 55.5 | L18: =C18*5.8% -> 214.6 | M18: =C18*8% -> 296 | N18: =SUM(J18:M18) -> 1306.1 | O18: =C18/12 -> 308.33333 | P18: =O18/3 -> 102.77778 | Q18: =(O18+P18)*8% -> 32.888889 | R18: =C18/12 -> 308.33333 | S18: =R18*8% -> 24.666667 | T18: =C18/12 -> 308.33333 | U18: =T18*8% -> 24.666667 | V18: =(M18+Q18+S18+U18)*50% -> 189.11111 | W18: =(O18+P18+R18+T18)*27.3% -> 280.58333 | X18: =SUM(O18:W18) -> 1579.6944 | Y18: =I18+N18+X18 -> 7739.9244 | Z18: Patronal | AA18: =SUM(J22:L22) -> 5803.83
B19: Silvania Barbosa Alves | C19: 3600 | F19: 200 | G19: 800 | H19: 453.62 | I19: =SUM(C19:H19) -> 5053.62 | J19: =C19*20% -> 720 | K19: =C19*1.5% -> 54 | L19: =C19*5.8% -> 208.8 | M19: =C19*8% -> 288 | N19: =SUM(J19:M19) -> 1270.8 | O19: =C19/12 -> 300 | P19: =O19/3 -> 100 | Q19: =(O19+P19)*8% -> 32 | R19: =C19/12 -> 300 | S19: =R19*8% -> 24 | T19: =C19/12 -> 300 | U19: =T19*8% -> 24 | V19: =(M19+Q19+S19+U19)*50% -> 184 | W19: =(O19+P19+R19+T19)*27.3% -> 273 | X19: =SUM(O19:W19) -> 1537 | Y19: =I19+N19+X19 -> 7861.42 | Z19: FGTS | AA19: =M22 -> 1544
B20: Edmundo Vale | D20: 1621 | E20: 11727 | F20: 3000 | I20: =SUM(C20:H20) -> 16348 | J20: =1621*11% -> 178.31 | N20: =SUM(J20:M20) -> 178.31 | Y20: =I20+N20+X20 -> 16526.31 | Z20: Provisão | AA20: =SUM(O22:W22) -> 8240.0278
B21: Ricardo Oliveira | D21: =1621*2 -> 3242 | E21: 15980 | F21: 3000 | I21: =SUM(C21:H21) -> 22222 | J21: =3242*11% -> 356.62 | N21: =SUM(J21:M21) -> 356.62 | Y21: =I21+N21+X21 -> 22578.62 | Z21: Total | AA21: =SUM(AA14:AA20) -> 79219.738
C22: =SUM(C14:C21) -> 19300 | D22: =SUM(D14:D21) -> 4863 | E22: =SUM(E14:E21) -> 27707 | F22: =SUM(F14:F21) -> 7000 | G22: =SUM(G14:G21) -> 4000 | H22: =SUM(H14:H21) -> 761.88 | I22: =SUM(I14:I21) -> 63631.88 | J22: =SUM(J14:J21) -> 4394.93 | ... X22: =SUM(X14:X21) -> 8240.0278 | Y22: =I22+N22+X22 -> 79219.738
B24: COLABORADOR | C24: Salários | D24: Prêmio | E24: Dist. Lucro | F24: Aj. Custo | G24: Alimentação | H24: Plano Saúde | I24: Sub. Total | J24: INSS | K24: RAT | L24: Terceiros | M24: FGTS | N24: T. Encargos | O24: Férias | P24: 1/3 Férias | Q24: FGTS Férias | R24: 13º Sal | S24: FGTS 13º Sal | T24: Aviso Prévio | U24: FGTS Av. | V24: Multa FGTS | W24: Patronal | X24: T. Provisão | Y24: Total | Z24: Custo Total | AA24: 46082
B25: Felipe Rocha | C25: 3000 | F25: 220 | G25: 880 | H25: 0 | I25: =SUM(C25:H25) -> 4100 | J25: =C25*20% -> 600 | K25: =C25*1.5% -> 45 | L25: =C25*5.8% -> 174 | M25: =C25*8% -> 240 | N25: =SUM(J25:M25) -> 1059 | O25: =C25/12 -> 250 | P25: =O25/3 -> 83.333333 | Q25: =(O25+P25)*8% -> 26.666667 | R25: =C25/12 -> 250 | S25: =R25*8% -> 20 | T25: =C25/12 -> 250 | U25: =T25*8% -> 20 | V25: =(M25+Q25+S25+U25)*50% -> 153.33333 | W25: =(O25+P25+R25+T25)*27.3% -> 227.5 | X25: =SUM(O25:W25) -> 1280.8333 | Y25: =I25+N25+X25 -> 6439.8333 | Z25: Salário | AA25: =C33 -> 20400
B26: Henrique Cazedey | C26: 3000 | F26: 0 | G26: 0 | I26: =SUM(C26:H26) -> 3000 | J26: =C26*20% -> 600 | K26: =C26*1.5% -> 45 | L26: =C26*5.8% -> 174 | M26: =C26*8% -> 240 | N26: =SUM(J26:M26) -> 1059 | O26: =C26/12 -> 250 | P26: =O26/3 -> 83.333333 | Q26: =(O26+P26)*8% -> 26.666667 | R26: =C26/12 -> 250 | S26: =R26*8% -> 20 | T26: =C26/12 -> 250 | U26: =T26*8% -> 20 | V26: =(M26+Q26+S26+U26)*50% -> 153.33333 | W26: =(O26+P26+R26+T26)*27.3% -> 227.5 | X26: =SUM(O26:W26) -> 1280.8333 | Y26: =I26+N26+X26 -> 5339.8333 | Z26: Prolabore | AA26: =D33 -> 4863
B27: Leandro dos Santos Pinheiro | C27: 4100 | F27: 220 | G27: 880 | H27: 154.13 | I27: =SUM(C27:H27) -> 5354.13 | J27: =C27*20% -> 820 | K27: =C27*1.5% -> 61.5 | L27: =C27*5.8% -> 237.8 | M27: =C27*8% -> 328 | N27: =SUM(J27:M27) -> 1447.3 | O27: =C27/12 -> 341.66667 | P27: =O27/3 -> 113.88889 | Q27: =(O27+P27)*8% -> 36.444444 | R27: =C27/12 -> 341.66667 | S27: =R27*8% -> 27.333333 | T27: =C27/12 -> 341.66667 | U27: =T27*8% -> 27.333333 | V27: =(M27+Q27+S27+U27)*50% -> 209.55556 | W27: =(O27+P27+R27+T27)*27.3% -> 310.91667 | X27: =SUM(O27:W27) -> 1750.4722 | Y27: =I27+N27+X27 -> 8551.9022 | Z27: Dist. Lucro | AA27: =E33 -> 27707
B28: Manoela Siolva Caldeira | C28: 3000 | F28: 220 | G28: 880 | I28: =SUM(C28:H28) -> 4100 | J28: =C28*20% -> 600 | K28: =C28*1.5% -> 45 | L28: =C28*5.8% -> 174 | M28: =C28*8% -> 240 | N28: =SUM(J28:M28) -> 1059 | O28: =C28/12 -> 250 | P28: =O28/3 -> 83.333333 | Q28: =(O28+P28)*8% -> 26.666667 | R28: =C28/12 -> 250 | S28: =R28*8% -> 20 | T28: =C28/12 -> 250 | U28: =T28*8% -> 20 | V28: =(M28+Q28+S28+U28)*50% -> 153.33333 | W28: =(O28+P28+R28+T28)*27.3% -> 227.5 | X28: =SUM(O28:W28) -> 1280.8333 | Y28: =I28+N28+X28 -> 6439.8333 | Z28: Benefício | AA28: =SUM(F33:H33) -> 12261.88
B29: Samuel Rodrigues de Souza | C29: 3700 | F29: 220 | G29: 880 | H29: 154.13 | I29: =SUM(C29:H29) -> 4954.13 | J29: =C29*20% -> 740 | K29: =C29*1.5% -> 55.5 | L29: =C29*5.8% -> 214.6 | M29: =C29*8% -> 296 | N29: =SUM(J29:M29) -> 1306.1 | O29: =C29/12 -> 308.33333 | P29: =O29/3 -> 102.77778 | Q29: =(O29+P29)*8% -> 32.888889 | R29: =C29/12 -> 308.33333 | S29: =R29*8% -> 24.666667 | T29: =C29/12 -> 308.33333 | U29: =T29*8% -> 24.666667 | V29: =(M29+Q29+S29+U29)*50% -> 189.11111 | W29: =(O29+P29+R29+T29)*27.3% -> 280.58333 | X29: =SUM(O29:W29) -> 1579.6944 | Y29: =I29+N29+X29 -> 7839.9244 | Z29: Patronal | AA29: =SUM(J33:L33) -> 6104.13
B30: Silvania Barbosa Alves | C30: 3600 | F30: 220 | G30: 880 | H30: 453.62 | I30: =SUM(C30:H30) -> 5153.62 | J30: =C30*20% -> 720 | K30: =C30*1.5% -> 54 | L30: =C30*5.8% -> 208.8 | M30: =C30*8% -> 288 | N30: =SUM(J30:M30) -> 1270.8 | O30: =C30/12 -> 300 | P30: =O30/3 -> 100 | Q30: =(O30+P30)*8% -> 32 | R30: =C30/12 -> 300 | S30: =R30*8% -> 24 | T30: =C30/12 -> 300 | U30: =T30*8% -> 24 | V30: =(M30+Q30+S30+U30)*50% -> 184 | W30: =(O30+P30+R30+T30)*27.3% -> 273 | X30: =SUM(O30:W30) -> 1537 | Y30: =I30+N30+X30 -> 7961.42 | Z30: FGTS | AA30: =M33 -> 1632
B31: Edmundo Vale | D31: 1621 | E31: 11727 | F31: 3000 | I31: =SUM(C31:H31) -> 16348 | J31: =1621*11% -> 178.31 | N31: =SUM(J31:M31) -> 178.31 | Y31: =I31+N31+X31 -> 16526.31 | Z31: Provisão | AA31: =SUM(O33:W33) -> 8709.6667
B32: Ricardo Oliveira | D32: =1621*2 -> 3242 | E32: 15980 | F32: 3000 | I32: =SUM(C32:H32) -> 22222 | J32: =3242*11% -> 356.62 | N32: =SUM(J32:M32) -> 356.62 | Y32: =I32+N32+X32 -> 22578.62 | Z32: Total | AA32: =SUM(AA25:AA31) -> 81677.677
C33: =SUM(C25:C32) -> 20400 | D33: =SUM(D25:D32) -> 4863 | E33: =SUM(E25:E32) -> 27707 | F33: =SUM(F25:F32) -> 7100 | G33: =SUM(G25:G32) -> 4400 | H33: =SUM(H25:H32) -> 761.88 | I33: =SUM(I25:I32) -> 65231.88 | J33: =SUM(J25:J32) -> 4614.93 | ... X33: =SUM(X25:X32) -> 8709.6667 | Y33: =I33+N33+X33 -> 81677.677
B35: COLABORADOR | C35: Salários | D35: Prêmio | E35: Dist. Lucro | F35: Aj. Custo | G35: Alimentação | H35: Plano Saúde | I35: Sub. Total | J35: INSS | K35: RAT | L35: Terceiros | M35: FGTS | N35: T. Encargos | O35: Férias | P35: 1/3 Férias | Q35: FGTS Férias | R35: 13º Sal | S35: FGTS 13º Sal | T35: Aviso Prévio | U35: FGTS Av. | V35: Multa FGTS | W35: Patronal | X35: T. Provisão | Y35: Total | Z35: Custo Total | AA35: 46113
B36: Felipe Rocha | C36: 1700 | D36: 0 | E36: 0 | F36: 190 | G36: 760 | H36: 0 | I36: =SUM(C36:H36) -> 2650 | J36: =C36*20% -> 340 | K36: =C36*1.5% -> 25.5 | L36: =C36*5.8% -> 98.6 | M36: =C36*8% -> 136 | N36: =SUM(J36:M36) -> 600.1 | O36: =C36/12 -> 141.66667 | P36: =O36/3 -> 47.222222 | Q36: =(O36+P36)*8% -> 15.111111 | R36: =C36/12 -> 141.66667 | S36: =R36*8% -> 11.333333 | T36: =C36/12 -> 141.66667 | U36: =T36*8% -> 11.333333 | V36: =(M36+Q36+S36+U36)*50% -> 86.888889 | W36: =(O36+P36+R36+T36)*27.3% -> 128.91667 | X36: =SUM(O36:W36) -> 725.80556 | Y36: =I36+N36+X36 -> 3975.9056 | Z36: Salário | AA36: =C44 -> 19100
B37: Henrique Cazedey | C37: 3000 | D37: 0 | E37: 0 | I37: =SUM(C37:H37) -> 3000 | J37: =C37*20% -> 600 | K37: =C37*1.5% -> 45 | L37: =C37*5.8% -> 174 | M37: =C37*8% -> 240 | N37: =SUM(J37:M37) -> 1059 | O37: =C37/12 -> 250 | P37: =O37/3 -> 83.333333 | Q37: =(O37+P37)*8% -> 26.666667 | R37: =C37/12 -> 250 | S37: =R37*8% -> 20 | T37: =C37/12 -> 250 | U37: =T37*8% -> 20 | V37: =(M37+Q37+S37+U37)*50% -> 153.33333 | W37: =(O37+P37+R37+T37)*27.3% -> 227.5 | X37: =SUM(O37:W37) -> 1280.8333 | Y37: =I37+N37+X37 -> 5339.8333 | Z37: Prolabore | AA37: =D44 -> 4863
B38: Leandro dos Santos Pinheiro | C38: 4100 | D38: 0 | E38: 0 | F38: 180 | G38: 720 | H38: 154.13 | I38: =SUM(C38:H38) -> 5154.13 | J38: =C38*20% -> 820 | K38: =C38*1.5% -> 61.5 | L38: =C38*5.8% -> 237.8 | M38: =C38*8% -> 328 | N38: =SUM(J38:M38) -> 1447.3 | O38: =C38/12 -> 341.66667 | P38: =O38/3 -> 113.88889 | Q38: =(O38+P38)*8% -> 36.444444 | R38: =C38/12 -> 341.66667 | S38: =R38*8% -> 27.333333 | T38: =C38/12 -> 341.66667 | U38: =T38*8% -> 27.333333 | V38: =(M38+Q38+S38+U38)*50% -> 209.55556 | W38: =(O38+P38+R38+T38)*27.3% -> 310.91667 | X38: =SUM(O38:W38) -> 1750.4722 | Y38: =I38+N38+X38 -> 8351.9022 | Z38: Dist. Lucro | AA38: =E44 -> 27707
B39: Manoela Siolva Caldeira | C39: 3000 | F39: 190 | G39: 760 | I39: =SUM(C39:H39) -> 3950 | J39: =C39*20% -> 600 | K39: =C39*1.5% -> 45 | L39: =C39*5.8% -> 174 | M39: =C39*8% -> 240 | N39: =SUM(J39:M39) -> 1059 | O39: =C39/12 -> 250 | P39: =O39/3 -> 83.333333 | Q39: =(O39+P39)*8% -> 26.666667 | R39: =C39/12 -> 250 | S39: =R39*8% -> 20 | T39: =C39/12 -> 250 | U39: =T39*8% -> 20 | V39: =(M39+Q39+S39+U39)*50% -> 153.33333 | W39: =(O39+P39+R39+T39)*27.3% -> 227.5 | X39: =SUM(O39:W39) -> 1280.8333 | Y39: =I39+N39+X39 -> 6289.8333 | Z39: Benefício | AA39: =SUM(F44:H44) -> 11361.88
B40: Samuel Rodrigues de Souza | C40: 3700 | D40: 0 | E40: 0 | F40: 180 | G40: 720 | H40: 154.13 | I40: =SUM(C40:H40) -> 4754.13 | J40: =C40*20% -> 740 | K40: =C40*1.5% -> 55.5 | L40: =C40*5.8% -> 214.6 | M40: =C40*8% -> 296 | N40: =SUM(J40:M40) -> 1306.1 | O40: =C40/12 -> 308.33333 | P40: =O40/3 -> 102.77778 | Q40: =(O40+P40)*8% -> 32.888889 | R40: =C40/12 -> 308.33333 | S40: =R40*8% -> 24.666667 | T40: =C40/12 -> 308.33333 | U40: =T40*8% -> 24.666667 | V40: =(M40+Q40+S40+U40)*50% -> 189.11111 | W40: =(O40+P40+R40+T40)*27.3% -> 280.58333 | X40: =SUM(O40:W40) -> 1579.6944 | Y40: =I40+N40+X40 -> 7639.9244 | Z40: Patronal | AA40: =SUM(J44:L44) -> 5749.23
B41: Silvania Barbosa Alves | C41: 3600 | D41: 0 | E41: 0 | F41: 180 | G41: 720 | H41: 453.62 | I41: =SUM(C41:H41) -> 4953.62 | J41: =C41*20% -> 720 | K41: =C41*1.5% -> 54 | L41: =C41*5.8% -> 208.8 | M41: =C41*8% -> 288 | N41: =SUM(J41:M41) -> 1270.8 | O41: =C41/12 -> 300 | P41: =O41/3 -> 100 | Q41: =(O41+P41)*8% -> 32 | R41: =C41/12 -> 300 | S41: =R41*8% -> 24 | T41: =C41/12 -> 300 | U41: =T41*8% -> 24 | V41: =(M41+Q41+S41+U41)*50% -> 184 | W41: =(O41+P41+R41+T41)*27.3% -> 273 | X41: =SUM(O41:W41) -> 1537 | Y41: =I41+N41+X41 -> 7761.42 | Z41: FGTS | AA41: =M44 -> 1528
B42: Edmundo Vale | D42: 1621 | E42: 11727 | F42: 3000 | I42: =SUM(C42:H42) -> 16348 | J42: =1621*11% -> 178.31 | N42: =SUM(J42:M42) -> 178.31 | Y42: =I42+N42+X42 -> 16526.31 | Z42: Provisão | AA42: =SUM(O44:W44) -> 8154.6389
B43: Ricardo Oliveira | D43: =1621*2 -> 3242 | E43: 15980 | F43: 3000 | I43: =SUM(C43:H43) -> 22222 | J43: =3242*11% -> 356.62 | N43: =SUM(J43:M43) -> 356.62 | Y43: =I43+N43+X43 -> 22578.62 | Z43: Total | AA43: =SUM(AA36:AA42) -> 78463.749
C44: =SUM(C36:C43) -> 19100 | D44: =SUM(D36:D43) -> 4863 | E44: =SUM(E36:E43) -> 27707 | F44: =SUM(F36:F43) -> 6920 | G44: =SUM(G36:G43) -> 3680 | H44: =SUM(H36:H43) -> 761.88 | I44: =SUM(I36:I43) -> 63031.88 | J44: =SUM(J36:J43) -> 4354.93 | ... X44: =SUM(X36:X43) -> 8154.6389 | Y44: =I44+N44+X44 -> 78463.749
B46: COLABORADOR | C46: Salários | D46: Prêmio | E46: Dist. Lucro | F46: Aj. Custo | G46: Alimentação | H46: Plano Saúde | I46: Sub. Total | J46: INSS | K46: RAT | L46: Terceiros | M46: FGTS | N46: T. Encargos | O46: Férias | P46: 1/3 Férias | Q46: FGTS Férias | R46: 13º Sal | S46: FGTS 13º Sal | T46: Aviso Prévio | U46: FGTS Av. | V46: Multa FGTS | W46: Patronal | X46: T. Provisão | Y46: Total | Z46: Custo Total | AA46: 46143
J47: =C47*20% -> 0 | K47: =C47*1.5% -> 0 | L47: =C47*5.8% -> 0 | M47: =C47*8% -> 0 | N47: =SUM(J47:M47) -> 0 | O47: =C47/12 -> 0 | P47: =O47/3 -> 0 | Q47: =(O47+P47)*8% -> 0 | R47: =C47/12 -> 0 | S47: =R47*8% -> 0 | T47: =C47/12 -> 0 | U47: =T47*8% -> 0 | V47: =(M47+Q47+S47+U47)*50% -> 0 | W47: =(O47+P47+R47+T47)*27.3% -> 0 | X47: =SUM(O47:W47) -> 0 | Y47: =I47+N47+X47 -> 0 | Z47: Salário | AA47: =C55 -> 0
J48: =C48*20% -> 0 | K48: =C48*1.5% -> 0 | L48: =C48*5.8% -> 0 | M48: =C48*8% -> 0 | N48: =SUM(J48:M48) -> 0 | O48: =C48/12 -> 0 | P48: =O48/3 -> 0 | Q48: =(O48+P48)*8% -> 0 | R48: =C48/12 -> 0 | S48: =R48*8% -> 0 | T48: =C48/12 -> 0 | U48: =T48*8% -> 0 | V48: =(M48+Q48+S48+U48)*50% -> 0 | W48: =(O48+P48+R48+T48)*27.3% -> 0 | X48: =SUM(O48:W48) -> 0 | Y48: =I48+N48+X48 -> 0 | Z48: Prolabore | AA48: =D55 -> 0
J49: =C49*20% -> 0 | K49: =C49*1.5% -> 0 | L49: =C49*5.8% -> 0 | M49: =C49*8% -> 0 | N49: =SUM(J49:M49) -> 0 | O49: =C49/12 -> 0 | P49: =O49/3 -> 0 | Q49: =(O49+P49)*8% -> 0 | R49: =C49/12 -> 0 | S49: =R49*8% -> 0 | T49: =C49/12 -> 0 | U49: =T49*8% -> 0 | V49: =(M49+Q49+S49+U49)*50% -> 0 | W49: =(O49+P49+R49+T49)*27.3% -> 0 | X49: =SUM(O49:W49) -> 0 | Y49: =I49+N49+X49 -> 0 | Z49: Dist. Lucro | AA49: =E55 -> 0
J50: =C50*20% -> 0 | K50: =C50*1.5% -> 0 | L50: =C50*5.8% -> 0 | M50: =C50*8% -> 0 | N50: =SUM(J50:M50) -> 0 | O50: =C50/12 -> 0 | P50: =O50/3 -> 0 | Q50: =(O50+P50)*8% -> 0 | R50: =C50/12 -> 0 | S50: =R50*8% -> 0 | T50: =C50/12 -> 0 | U50: =T50*8% -> 0 | V50: =(M50+Q50+S50+U50)*50% -> 0 | W50: =(O50+P50+R50+T50)*27.3% -> 0 | X50: =SUM(O50:W50) -> 0 | Y50: =I50+N50+X50 -> 0 | Z50: Benefício | AA50: =SUM(F55:H55) -> 0
J51: =C51*20% -> 0 | K51: =C51*1.5% -> 0 | L51: =C51*5.8% -> 0 | M51: =C51*8% -> 0 | N51: =SUM(J51:M51) -> 0 | O51: =C51/12 -> 0 | P51: =O51/3 -> 0 | Q51: =(O51+P51)*8% -> 0 | R51: =C51/12 -> 0 | S51: =R51*8% -> 0 | T51: =C51/12 -> 0 | U51: =T51*8% -> 0 | V51: =(M51+Q51+S51+U51)*50% -> 0 | W51: =(O51+P51+R51+T51)*27.3% -> 0 | X51: =SUM(O51:W51) -> 0 | Y51: =I51+N51+X51 -> 0 | Z51: Patronal | AA51: =SUM(J55:L55) -> 0
J52: =C52*20% -> 0 | K52: =C52*1.5% -> 0 | L52: =C52*5.8% -> 0 | M52: =C52*8% -> 0 | N52: =SUM(J52:M52) -> 0 | O52: =C52/12 -> 0 | P52: =O52/3 -> 0 | Q52: =(O52+P52)*8% -> 0 | R52: =C52/12 -> 0 | S52: =R52*8% -> 0 | T52: =C52/12 -> 0 | U52: =T52*8% -> 0 | V52: =(M52+Q52+S52+U52)*50% -> 0 | W52: =(O52+P52+R52+T52)*27.3% -> 0 | X52: =SUM(O52:W52) -> 0 | Y52: =I52+N52+X52 -> 0 | Z52: FGTS | AA52: =M55 -> 0
N53: =SUM(J53:M53) -> 0 | Y53: =I53+N53+X53 -> 0 | Z53: Provisão | AA53: =SUM(O55:W55) -> 0
N54: =SUM(J54:M54) -> 0 | Y54: =I54+N54+X54 -> 0 | Z54: Total | AA54: =SUM(AA47:AA53) -> 0
C55: =SUM(C47:C54) -> 0 | D55: =SUM(D47:D54) -> 0 | E55: =SUM(E47:E54) -> 0 | F55: =SUM(F47:F54) -> 0 | G55: =SUM(G47:G54) -> 0 | H55: =SUM(H47:H54) -> 0 | I55: =SUM(I47:I54) -> 0 | J55: =SUM(J47:J54) -> 0 | ... X55: =SUM(X47:X54) -> 0 | Y55: =I55+N55+X55 -> 0
B57: COLABORADOR | C57: Salários | D57: Prêmio | E57: Dist. Lucro | F57: Aj. Custo | G57: Alimentação | H57: Plano Saúde | I57: Sub. Total | J57: INSS | K57: RAT | L57: Terceiros | M57: FGTS | N57: T. Encargos | O57: Férias | P57: 1/3 Férias | Q57: FGTS Férias | R57: 13º Sal | S57: FGTS 13º Sal | T57: Aviso Prévio | U57: FGTS Av. | V57: Multa FGTS | W57: Patronal | X57: T. Provisão | Y57: Total | Z57: Custo Total | AA57: 46174
I58: =SUM(C58:H58) -> 0 | J58: =C58*20% -> 0 | K58: =C58*1.5% -> 0 | L58: =C58*5.8% -> 0 | M58: =C58*8% -> 0 | N58: =SUM(J58:M58) -> 0 | O58: =C58/12 -> 0 | P58: =O58/3 -> 0 | Q58: =(O58+P58)*8% -> 0 | R58: =C58/12 -> 0 | S58: =R58*8% -> 0 | T58: =C58/12 -> 0 | U58: =T58*8% -> 0 | V58: =(M58+Q58+S58+U58)*50% -> 0 | W58: =(O58+P58+R58+T58)*27.3% -> 0 | X58: =SUM(O58:W58) -> 0 | Y58: =I58+N58+X58 -> 0 | Z58: Salário | AA58: =C66 -> 0
I59: =SUM(C59:H59) -> 0 | J59: =C59*20% -> 0 | K59: =C59*1.5% -> 0 | L59: =C59*5.8% -> 0 | M59: =C59*8% -> 0 | N59: =SUM(J59:M59) -> 0 | O59: =C59/12 -> 0 | P59: =O59/3 -> 0 | Q59: =(O59+P59)*8% -> 0 | R59: =C59/12 -> 0 | S59: =R59*8% -> 0 | T59: =C59/12 -> 0 | U59: =T59*8% -> 0 | V59: =(M59+Q59+S59+U59)*50% -> 0 | W59: =(O59+P59+R59+T59)*27.3% -> 0 | X59: =SUM(O59:W59) -> 0 | Y59: =I59+N59+X59 -> 0 | Z59: Prolabore | AA59: =D66 -> 0
I60: =SUM(C60:H60) -> 0 | J60: =C60*20% -> 0 | K60: =C60*1.5% -> 0 | L60: =C60*5.8% -> 0 | M60: =C60*8% -> 0 | N60: =SUM(J60:M60) -> 0 | O60: =C60/12 -> 0 | P60: =O60/3 -> 0 | Q60: =(O60+P60)*8% -> 0 | R60: =C60/12 -> 0 | S60: =R60*8% -> 0 | T60: =C60/12 -> 0 | U60: =T60*8% -> 0 | V60: =(M60+Q60+S60+U60)*50% -> 0 | W60: =(O60+P60+R60+T60)*27.3% -> 0 | X60: =SUM(O60:W60) -> 0 | Y60: =I60+N60+X60 -> 0 | Z60: Dist. Lucro | AA60: =E66 -> 0
I61: =SUM(C61:H61) -> 0 | J61: =C61*20% -> 0 | K61: =C61*1.5% -> 0 | L61: =C61*5.8% -> 0 | M61: =C61*8% -> 0 | N61: =SUM(J61:M61) -> 0 | O61: =C61/12 -> 0 | P61: =O61/3 -> 0 | Q61: =(O61+P61)*8% -> 0 | R61: =C61/12 -> 0 | S61: =R61*8% -> 0 | T61: =C61/12 -> 0 | U61: =T61*8% -> 0 | V61: =(M61+Q61+S61+U61)*50% -> 0 | W61: =(O61+P61+R61+T61)*27.3% -> 0 | X61: =SUM(O61:W61) -> 0 | Y61: =I61+N61+X61 -> 0 | Z61: Benefício | AA61: =SUM(F66:H66) -> 0
I62: =SUM(C62:H62) -> 0 | J62: =C62*20% -> 0 | K62: =C62*1.5% -> 0 | L62: =C62*5.8% -> 0 | M62: =C62*8% -> 0 | N62: =SUM(J62:M62) -> 0 | O62: =C62/12 -> 0 | P62: =O62/3 -> 0 | Q62: =(O62+P62)*8% -> 0 | R62: =C62/12 -> 0 | S62: =R62*8% -> 0 | T62: =C62/12 -> 0 | U62: =T62*8% -> 0 | V62: =(M62+Q62+S62+U62)*50% -> 0 | W62: =(O62+P62+R62+T62)*27.3% -> 0 | X62: =SUM(O62:W62) -> 0 | Y62: =I62+N62+X62 -> 0 | Z62: Patronal | AA62: =SUM(J66:L66) -> 0
I63: =SUM(C63:H63) -> 0 | J63: =C63*20% -> 0 | K63: =C63*1.5% -> 0 | L63: =C63*5.8% -> 0 | M63: =C63*8% -> 0 | N63: =SUM(J63:M63) -> 0 | O63: =C63/12 -> 0 | P63: =O63/3 -> 0 | Q63: =(O63+P63)*8% -> 0 | R63: =C63/12 -> 0 | S63: =R63*8% -> 0 | T63: =C63/12 -> 0 | U63: =T63*8% -> 0 | V63: =(M63+Q63+S63+U63)*50% -> 0 | W63: =(O63+P63+R63+T63)*27.3% -> 0 | X63: =SUM(O63:W63) -> 0 | Y63: =I63+N63+X63 -> 0 | Z63: FGTS | AA63: =M66 -> 0
I64: =SUM(C64:H64) -> 0 | N64: =SUM(J64:M64) -> 0 | Y64: =I64+N64+X64 -> 0 | Z64: Provisão | AA64: =SUM(O66:W66) -> 0
I65: =SUM(C65:H65) -> 0 | N65: =SUM(J65:M65) -> 0 | Y65: =I65+N65+X65 -> 0 | Z65: Total | AA65: =SUM(AA58:AA64) -> 0
C66: =SUM(C58:C65) -> 0 | D66: =SUM(D58:D65) -> 0 | E66: =SUM(E58:E65) -> 0 | F66: =SUM(F58:F65) -> 0 | G66: =SUM(G58:G65) -> 0 | H66: =SUM(H58:H65) -> 0 | I66: =SUM(I58:I65) -> 0 | J66: =SUM(J58:J65) -> 0 | ... X66: =SUM(X58:X65) -> 0 | Y66: =I66+N66+X66 -> 0
B68: COLABORADOR | C68: Salários | D68: Prêmio | E68: Dist. Lucro | F68: Aj. Custo | G68: Alimentação | H68: Plano Saúde | I68: Sub. Total | J68: INSS | K68: RAT | L68: Terceiros | M68: FGTS | N68: T. Encargos | O68: Férias | P68: 1/3 Férias | Q68: FGTS Férias | R68: 13º Sal | S68: FGTS 13º Sal | T68: Aviso Prévio | U68: FGTS Av. | V68: Multa FGTS | W68: Patronal | X68: T. Provisão | Y68: Total | Z68: Custo Total | AA68: 46204
I69: =SUM(C69:H69) -> 0 | J69: =C69*20% -> 0 | K69: =C69*1.5% -> 0 | L69: =C69*5.8% -> 0 | M69: =C69*8% -> 0 | N69: =SUM(J69:M69) -> 0 | O69: =C69/12 -> 0 | P69: =O69/3 -> 0 | Q69: =(O69+P69)*8% -> 0 | R69: =C69/12 -> 0 | S69: =R69*8% -> 0 | T69: =C69/12 -> 0 | U69: =T69*8% -> 0 | V69: =(M69+Q69+S69+U69)*50% -> 0 | W69: =(O69+P69+R69+T69)*27.3% -> 0 | X69: =SUM(O69:W69) -> 0 | Y69: =I69+N69+X69 -> 0 | Z69: Salário | AA69: =C77 -> 0
I70: =SUM(C70:H70) -> 0 | J70: =C70*20% -> 0 | K70: =C70*1.5% -> 0 | L70: =C70*5.8% -> 0 | M70: =C70*8% -> 0 | N70: =SUM(J70:M70) -> 0 | O70: =C70/12 -> 0 | P70: =O70/3 -> 0 | Q70: =(O70+P70)*8% -> 0 | R70: =C70/12 -> 0 | S70: =R70*8% -> 0 | T70: =C70/12 -> 0 | U70: =T70*8% -> 0 | V70: =(M70+Q70+S70+U70)*50% -> 0 | W70: =(O70+P70+R70+T70)*27.3% -> 0 | X70: =SUM(O70:W70) -> 0 | Y70: =I70+N70+X70 -> 0 | Z70: Prolabore | AA70: =D77 -> 0
I71: =SUM(C71:H71) -> 0 | J71: =C71*20% -> 0 | K71: =C71*1.5% -> 0 | L71: =C71*5.8% -> 0 | M71: =C71*8% -> 0 | N71: =SUM(J71:M71) -> 0 | O71: =C71/12 -> 0 | P71: =O71/3 -> 0 | Q71: =(O71+P71)*8% -> 0 | R71: =C71/12 -> 0 | S71: =R71*8% -> 0 | T71: =C71/12 -> 0 | U71: =T71*8% -> 0 | V71: =(M71+Q71+S71+U71)*50% -> 0 | W71: =(O71+P71+R71+T71)*27.3% -> 0 | X71: =SUM(O71:W71) -> 0 | Y71: =I71+N71+X71 -> 0 | Z71: Dist. Lucro | AA71: =E77 -> 0
I72: =SUM(C72:H72) -> 0 | J72: =C72*20% -> 0 | K72: =C72*1.5% -> 0 | L72: =C72*5.8% -> 0 | M72: =C72*8% -> 0 | N72: =SUM(J72:M72) -> 0 | O72: =C72/12 -> 0 | P72: =O72/3 -> 0 | Q72: =(O72+P72)*8% -> 0 | R72: =C72/12 -> 0 | S72: =R72*8% -> 0 | T72: =C72/12 -> 0 | U72: =T72*8% -> 0 | V72: =(M72+Q72+S72+U72)*50% -> 0 | W72: =(O72+P72+R72+T72)*27.3% -> 0 | X72: =SUM(O72:W72) -> 0 | Y72: =I72+N72+X72 -> 0 | Z72: Benefício | AA72: =SUM(F77:H77) -> 0
I73: =SUM(C73:H73) -> 0 | J73: =C73*20% -> 0 | K73: =C73*1.5% -> 0 | L73: =C73*5.8% -> 0 | M73: =C73*8% -> 0 | N73: =SUM(J73:M73) -> 0 | O73: =C73/12 -> 0 | P73: =O73/3 -> 0 | Q73: =(O73+P73)*8% -> 0 | R73: =C73/12 -> 0 | S73: =R73*8% -> 0 | T73: =C73/12 -> 0 | U73: =T73*8% -> 0 | V73: =(M73+Q73+S73+U73)*50% -> 0 | W73: =(O73+P73+R73+T73)*27.3% -> 0 | X73: =SUM(O73:W73) -> 0 | Y73: =I73+N73+X73 -> 0 | Z73: Patronal | AA73: =SUM(J77:L77) -> 0
I74: =SUM(C74:H74) -> 0 | J74: =C74*20% -> 0 | K74: =C74*1.5% -> 0 | L74: =C74*5.8% -> 0 | M74: =C74*8% -> 0 | N74: =SUM(J74:M74) -> 0 | O74: =C74/12 -> 0 | P74: =O74/3 -> 0 | Q74: =(O74+P74)*8% -> 0 | R74: =C74/12 -> 0 | S74: =R74*8% -> 0 | T74: =C74/12 -> 0 | U74: =T74*8% -> 0 | V74: =(M74+Q74+S74+U74)*50% -> 0 | W74: =(O74+P74+R74+T74)*27.3% -> 0 | X74: =SUM(O74:W74) -> 0 | Y74: =I74+N74+X74 -> 0 | Z74: FGTS | AA74: =M77 -> 0
I75: =SUM(C75:H75) -> 0 | N75: =SUM(J75:M75) -> 0 | Y75: =I75+N75+X75 -> 0 | Z75: Provisão | AA75: =SUM(O77:W77) -> 0
I76: =SUM(C76:H76) -> 0 | N76: =SUM(J76:M76) -> 0 | Y76: =I76+N76+X76 -> 0 | Z76: Total | AA76: =SUM(AA69:AA75) -> 0
C77: =SUM(C69:C76) -> 0 | D77: =SUM(D69:D76) -> 0 | E77: =SUM(E69:E76) -> 0 | F77: =SUM(F69:F76) -> 0 | G77: =SUM(G69:G76) -> 0 | H77: =SUM(H69:H76) -> 0 | I77: =SUM(I69:I76) -> 0 | J77: =SUM(J69:J76) -> 0 | ... X77: =SUM(X69:X76) -> 0 | Y77: =I77+N77+X77 -> 0
B79: COLABORADOR | C79: Salários | D79: Prêmio | E79: Dist. Lucro | F79: Aj. Custo | G79: Alimentação | H79: Plano Saúde | I79: Sub. Total | J79: INSS | K79: RAT | L79: Terceiros | M79: FGTS | N79: T. Encargos | O79: Férias | P79: 1/3 Férias | Q79: FGTS Férias | R79: 13º Sal | S79: FGTS 13º Sal | T79: Aviso Prévio | U79: FGTS Av. | V79: Multa FGTS | W79: Patronal | X79: T. Provisão | Y79: Total | Z79: Custo Total | AA79: 46235
I80: =SUM(C80:H80) -> 0 | J80: =C80*20% -> 0 | K80: =C80*1.5% -> 0 | L80: =C80*5.8% -> 0 | M80: =C80*8% -> 0 | N80: =SUM(J80:M80) -> 0 | O80: =C80/12 -> 0 | P80: =O80/3 -> 0 | Q80: =(O80+P80)*8% -> 0 | R80: =C80/12 -> 0 | S80: =R80*8% -> 0 | T80: =C80/12 -> 0 | U80: =T80*8% -> 0 | V80: =(M80+Q80+S80+U80)*50% -> 0 | W80: =(O80+P80+R80+T80)*27.3% -> 0 | X80: =SUM(O80:W80) -> 0 | Y80: =I80+N80+X80 -> 0 | Z80: Salário | AA80: =C88 -> 0
I81: =SUM(C81:H81) -> 0 | J81: =C81*20% -> 0 | K81: =C81*1.5% -> 0 | L81: =C81*5.8% -> 0 | M81: =C81*8% -> 0 | N81: =SUM(J81:M81) -> 0 | O81: =C81/12 -> 0 | P81: =O81/3 -> 0 | Q81: =(O81+P81)*8% -> 0 | R81: =C81/12 -> 0 | S81: =R81*8% -> 0 | T81: =C81/12 -> 0 | U81: =T81*8% -> 0 | V81: =(M81+Q81+S81+U81)*50% -> 0 | W81: =(O81+P81+R81+T81)*27.3% -> 0 | X81: =SUM(O81:W81) -> 0 | Y81: =I81+N81+X81 -> 0 | Z81: Prolabore | AA81: =D88 -> 0
I82: =SUM(C82:H82) -> 0 | J82: =C82*20% -> 0 | K82: =C82*1.5% -> 0 | L82: =C82*5.8% -> 0 | M82: =C82*8% -> 0 | N82: =SUM(J82:M82) -> 0 | O82: =C82/12 -> 0 | P82: =O82/3 -> 0 | Q82: =(O82+P82)*8% -> 0 | R82: =C82/12 -> 0 | S82: =R82*8% -> 0 | T82: =C82/12 -> 0 | U82: =T82*8% -> 0 | V82: =(M82+Q82+S82+U82)*50% -> 0 | W82: =(O82+P82+R82+T82)*27.3% -> 0 | X82: =SUM(O82:W82) -> 0 | Y82: =I82+N82+X82 -> 0 | Z82: Dist. Lucro | AA82: =E88 -> 0
I83: =SUM(C83:H83) -> 0 | J83: =C83*20% -> 0 | K83: =C83*1.5% -> 0 | L83: =C83*5.8% -> 0 | M83: =C83*8% -> 0 | N83: =SUM(J83:M83) -> 0 | O83: =C83/12 -> 0 | P83: =O83/3 -> 0 | Q83: =(O83+P83)*8% -> 0 | R83: =C83/12 -> 0 | S83: =R83*8% -> 0 | T83: =C83/12 -> 0 | U83: =T83*8% -> 0 | V83: =(M83+Q83+S83+U83)*50% -> 0 | W83: =(O83+P83+R83+T83)*27.3% -> 0 | X83: =SUM(O83:W83) -> 0 | Y83: =I83+N83+X83 -> 0 | Z83: Benefício | AA83: =SUM(F88:H88) -> 0
I84: =SUM(C84:H84) -> 0 | J84: =C84*20% -> 0 | K84: =C84*1.5% -> 0 | L84: =C84*5.8% -> 0 | M84: =C84*8% -> 0 | N84: =SUM(J84:M84) -> 0 | O84: =C84/12 -> 0 | P84: =O84/3 -> 0 | Q84: =(O84+P84)*8% -> 0 | R84: =C84/12 -> 0 | S84: =R84*8% -> 0 | T84: =C84/12 -> 0 | U84: =T84*8% -> 0 | V84: =(M84+Q84+S84+U84)*50% -> 0 | W84: =(O84+P84+R84+T84)*27.3% -> 0 | X84: =SUM(O84:W84) -> 0 | Y84: =I84+N84+X84 -> 0 | Z84: Patronal | AA84: =SUM(J88:L88) -> 0
I85: =SUM(C85:H85) -> 0 | J85: =C85*20% -> 0 | K85: =C85*1.5% -> 0 | L85: =C85*5.8% -> 0 | M85: =C85*8% -> 0 | N85: =SUM(J85:M85) -> 0 | O85: =C85/12 -> 0 | P85: =O85/3 -> 0 | Q85: =(O85+P85)*8% -> 0 | R85: =C85/12 -> 0 | S85: =R85*8% -> 0 | T85: =C85/12 -> 0 | U85: =T85*8% -> 0 | V85: =(M85+Q85+S85+U85)*50% -> 0 | W85: =(O85+P85+R85+T85)*27.3% -> 0 | X85: =SUM(O85:W85) -> 0 | Y85: =I85+N85+X85 -> 0 | Z85: FGTS | AA85: =M88 -> 0
I86: =SUM(C86:H86) -> 0 | N86: =SUM(J86:M86) -> 0 | Y86: =I86+N86+X86 -> 0 | Z86: Provisão | AA86: =SUM(O88:W88) -> 0
I87: =SUM(C87:H87) -> 0 | N87: =SUM(J87:M87) -> 0 | Y87: =I87+N87+X87 -> 0 | Z87: Total | AA87: =SUM(AA80:AA86) -> 0
C88: =SUM(C80:C87) -> 0 | D88: =SUM(D80:D87) -> 0 | E88: =SUM(E80:E87) -> 0 | F88: =SUM(F80:F87) -> 0 | G88: =SUM(G80:G87) -> 0 | H88: =SUM(H80:H87) -> 0 | I88: =SUM(I80:I87) -> 0 | J88: =SUM(J80:J87) -> 0 | ... X88: =SUM(X80:X87) -> 0 | Y88: =I88+N88+X88 -> 0
B90: COLABORADOR | C90: Salários | D90: Prêmio | E90: Dist. Lucro | F90: Aj. Custo | G90: Alimentação | H90: Plano Saúde | I90: Sub. Total | J90: INSS | K90: RAT | L90: Terceiros | M90: FGTS | N90: T. Encargos | O90: Férias | P90: 1/3 Férias | Q90: FGTS Férias | R90: 13º Sal | S90: FGTS 13º Sal | T90: Aviso Prévio | U90: FGTS Av. | V90: Multa FGTS | W90: Patronal | X90: T. Provisão | Y90: Total | Z90: Custo Total | AA90: 46266
I91: =SUM(C91:H91) -> 0 | J91: =C91*20% -> 0 | K91: =C91*1.5% -> 0 | L91: =C91*5.8% -> 0 | M91: =C91*8% -> 0 | N91: =SUM(J91:M91) -> 0 | O91: =C91/12 -> 0 | P91: =O91/3 -> 0 | Q91: =(O91+P91)*8% -> 0 | R91: =C91/12 -> 0 | S91: =R91*8% -> 0 | T91: =C91/12 -> 0 | U91: =T91*8% -> 0 | V91: =(M91+Q91+S91+U91)*50% -> 0 | W91: =(O91+P91+R91+T91)*27.3% -> 0 | X91: =SUM(O91:W91) -> 0 | Y91: =I91+N91+X91 -> 0 | Z91: Salário | AA91: =C99 -> 0
I92: =SUM(C92:H92) -> 0 | J92: =C92*20% -> 0 | K92: =C92*1.5% -> 0 | L92: =C92*5.8% -> 0 | M92: =C92*8% -> 0 | N92: =SUM(J92:M92) -> 0 | O92: =C92/12 -> 0 | P92: =O92/3 -> 0 | Q92: =(O92+P92)*8% -> 0 | R92: =C92/12 -> 0 | S92: =R92*8% -> 0 | T92: =C92/12 -> 0 | U92: =T92*8% -> 0 | V92: =(M92+Q92+S92+U92)*50% -> 0 | W92: =(O92+P92+R92+T92)*27.3% -> 0 | X92: =SUM(O92:W92) -> 0 | Y92: =I92+N92+X92 -> 0 | Z92: Prolabore | AA92: =D99 -> 0
I93: =SUM(C93:H93) -> 0 | J93: =C93*20% -> 0 | K93: =C93*1.5% -> 0 | L93: =C93*5.8% -> 0 | M93: =C93*8% -> 0 | N93: =SUM(J93:M93) -> 0 | O93: =C93/12 -> 0 | P93: =O93/3 -> 0 | Q93: =(O93+P93)*8% -> 0 | R93: =C93/12 -> 0 | S93: =R93*8% -> 0 | T93: =C93/12 -> 0 | U93: =T93*8% -> 0 | V93: =(M93+Q93+S93+U93)*50% -> 0 | W93: =(O93+P93+R93+T93)*27.3% -> 0 | X93: =SUM(O93:W93) -> 0 | Y93: =I93+N93+X93 -> 0 | Z93: Dist. Lucro | AA93: =E99 -> 0
I94: =SUM(C94:H94) -> 0 | J94: =C94*20% -> 0 | K94: =C94*1.5% -> 0 | L94: =C94*5.8% -> 0 | M94: =C94*8% -> 0 | N94: =SUM(J94:M94) -> 0 | O94: =C94/12 -> 0 | P94: =O94/3 -> 0 | Q94: =(O94+P94)*8% -> 0 | R94: =C94/12 -> 0 | S94: =R94*8% -> 0 | T94: =C94/12 -> 0 | U94: =T94*8% -> 0 | V94: =(M94+Q94+S94+U94)*50% -> 0 | W94: =(O94+P94+R94+T94)*27.3% -> 0 | X94: =SUM(O94:W94) -> 0 | Y94: =I94+N94+X94 -> 0 | Z94: Benefício | AA94: =SUM(F99:H99) -> 0
I95: =SUM(C95:H95) -> 0 | J95: =C95*20% -> 0 | K95: =C95*1.5% -> 0 | L95: =C95*5.8% -> 0 | M95: =C95*8% -> 0 | N95: =SUM(J95:M95) -> 0 | O95: =C95/12 -> 0 | P95: =O95/3 -> 0 | Q95: =(O95+P95)*8% -> 0 | R95: =C95/12 -> 0 | S95: =R95*8% -> 0 | T95: =C95/12 -> 0 | U95: =T95*8% -> 0 | V95: =(M95+Q95+S95+U95)*50% -> 0 | W95: =(O95+P95+R95+T95)*27.3% -> 0 | X95: =SUM(O95:W95) -> 0 | Y95: =I95+N95+X95 -> 0 | Z95: Patronal | AA95: =SUM(J99:L99) -> 0
I96: =SUM(C96:H96) -> 0 | J96: =C96*20% -> 0 | K96: =C96*1.5% -> 0 | L96: =C96*5.8% -> 0 | M96: =C96*8% -> 0 | N96: =SUM(J96:M96) -> 0 | O96: =C96/12 -> 0 | P96: =O96/3 -> 0 | Q96: =(O96+P96)*8% -> 0 | R96: =C96/12 -> 0 | S96: =R96*8% -> 0 | T96: =C96/12 -> 0 | U96: =T96*8% -> 0 | V96: =(M96+Q96+S96+U96)*50% -> 0 | W96: =(O96+P96+R96+T96)*27.3% -> 0 | X96: =SUM(O96:W96) -> 0 | Y96: =I96+N96+X96 -> 0 | Z96: FGTS | AA96: =M99 -> 0
I97: =SUM(C97:H97) -> 0 | N97: =SUM(J97:M97) -> 0 | Y97: =I97+N97+X97 -> 0 | Z97: Provisão | AA97: =SUM(O99:W99) -> 0
I98: =SUM(C98:H98) -> 0 | N98: =SUM(J98:M98) -> 0 | Y98: =I98+N98+X98 -> 0 | Z98: Total | AA98: =SUM(AA91:AA97) -> 0
C99: =SUM(C91:C98) -> 0 | D99: =SUM(D91:D98) -> 0 | E99: =SUM(E91:E98) -> 0 | F99: =SUM(F91:F98) -> 0 | G99: =SUM(G91:G98) -> 0 | H99: =SUM(H91:H98) -> 0 | I99: =SUM(I91:I98) -> 0 | J99: =SUM(J91:J98) -> 0 | ... X99: =SUM(X91:X98) -> 0 | Y99: =I99+N99+X99 -> 0
B101: COLABORADOR | C101: Salários | D101: Prêmio | E101: Dist. Lucro | F101: Aj. Custo | G101: Alimentação | H101: Plano Saúde | I101: Sub. Total | J101: INSS | K101: RAT | L101: Terceiros | M101: FGTS | N101: T. Encargos | O101: Férias | P101: 1/3 Férias | Q101: FGTS Férias | R101: 13º Sal | S101: FGTS 13º Sal | T101: Aviso Prévio | U101: FGTS Av. | V101: Multa FGTS | W101: Patronal | X101: T. Provisão | Y101: Total | Z101: Custo Total | AA101: 46296
I102: =SUM(C102:H102) -> 0 | J102: =C102*20% -> 0 | K102: =C102*1.5% -> 0 | L102: =C102*5.8% -> 0 | M102: =C102*8% -> 0 | N102: =SUM(J102:M102) -> 0 | O102: =C102/12 -> 0 | P102: =O102/3 -> 0 | Q102: =(O102+P102)*8% -> 0 | R102: =C102/12 -> 0 | S102: =R102*8% -> 0 | T102: =C102/12 -> 0 | U102: =T102*8% -> 0 | V102: =(M102+Q102+S102+U102)*50% -> 0 | W102: =(O102+P102+R102+T102)*27.3% -> 0 | X102: =SUM(O102:W102) -> 0 | Y102: =I102+N102+X102 -> 0 | Z102: Salário | AA102: =C110 -> 0
I103: =SUM(C103:H103) -> 0 | J103: =C103*20% -> 0 | K103: =C103*1.5% -> 0 | L103: =C103*5.8% -> 0 | M103: =C103*8% -> 0 | N103: =SUM(J103:M103) -> 0 | O103: =C103/12 -> 0 | P103: =O103/3 -> 0 | Q103: =(O103+P103)*8% -> 0 | R103: =C103/12 -> 0 | S103: =R103*8% -> 0 | T103: =C103/12 -> 0 | U103: =T103*8% -> 0 | V103: =(M103+Q103+S103+U103)*50% -> 0 | W103: =(O103+P103+R103+T103)*27.3% -> 0 | X103: =SUM(O103:W103) -> 0 | Y103: =I103+N103+X103 -> 0 | Z103: Prolabore | AA103: =D110 -> 0
I104: =SUM(C104:H104) -> 0 | J104: =C104*20% -> 0 | K104: =C104*1.5% -> 0 | L104: =C104*5.8% -> 0 | M104: =C104*8% -> 0 | N104: =SUM(J104:M104) -> 0 | O104: =C104/12 -> 0 | P104: =O104/3 -> 0 | Q104: =(O104+P104)*8% -> 0 | R104: =C104/12 -> 0 | S104: =R104*8% -> 0 | T104: =C104/12 -> 0 | U104: =T104*8% -> 0 | V104: =(M104+Q104+S104+U104)*50% -> 0 | W104: =(O104+P104+R104+T104)*27.3% -> 0 | X104: =SUM(O104:W104) -> 0 | Y104: =I104+N104+X104 -> 0 | Z104: Dist. Lucro | AA104: =E110 -> 0
I105: =SUM(C105:H105) -> 0 | J105: =C105*20% -> 0 | K105: =C105*1.5% -> 0 | L105: =C105*5.8% -> 0 | M105: =C105*8% -> 0 | N105: =SUM(J105:M105) -> 0 | O105: =C105/12 -> 0 | P105: =O105/3 -> 0 | Q105: =(O105+P105)*8% -> 0 | R105: =C105/12 -> 0 | S105: =R105*8% -> 0 | T105: =C105/12 -> 0 | U105: =T105*8% -> 0 | V105: =(M105+Q105+S105+U105)*50% -> 0 | W105: =(O105+P105+R105+T105)*27.3% -> 0 | X105: =SUM(O105:W105) -> 0 | Y105: =I105+N105+X105 -> 0 | Z105: Benefício | AA105: =SUM(F110:H110) -> 0
I106: =SUM(C106:H106) -> 0 | J106: =C106*20% -> 0 | K106: =C106*1.5% -> 0 | L106: =C106*5.8% -> 0 | M106: =C106*8% -> 0 | N106: =SUM(J106:M106) -> 0 | O106: =C106/12 -> 0 | P106: =O106/3 -> 0 | Q106: =(O106+P106)*8% -> 0 | R106: =C106/12 -> 0 | S106: =R106*8% -> 0 | T106: =C106/12 -> 0 | U106: =T106*8% -> 0 | V106: =(M106+Q106+S106+U106)*50% -> 0 | W106: =(O106+P106+R106+T106)*27.3% -> 0 | X106: =SUM(O106:W106) -> 0 | Y106: =I106+N106+X106 -> 0 | Z106: Patronal | AA106: =SUM(J110:L110) -> 0
I107: =SUM(C107:H107) -> 0 | J107: =C107*20% -> 0 | K107: =C107*1.5% -> 0 | L107: =C107*5.8% -> 0 | M107: =C107*8% -> 0 | N107: =SUM(J107:M107) -> 0 | O107: =C107/12 -> 0 | P107: =O107/3 -> 0 | Q107: =(O107+P107)*8% -> 0 | R107: =C107/12 -> 0 | S107: =R107*8% -> 0 | T107: =C107/12 -> 0 | U107: =T107*8% -> 0 | V107: =(M107+Q107+S107+U107)*50% -> 0 | W107: =(O107+P107+R107+T107)*27.3% -> 0 | X107: =SUM(O107:W107) -> 0 | Y107: =I107+N107+X107 -> 0 | Z107: FGTS | AA107: =M110 -> 0
I108: =SUM(C108:H108) -> 0 | N108: =SUM(J108:M108) -> 0 | Y108: =I108+N108+X108 -> 0 | Z108: Provisão | AA108: =SUM(O110:W110) -> 0
I109: =SUM(C109:H109) -> 0 | N109: =SUM(J109:M109) -> 0 | Y109: =I109+N109+X109 -> 0 | Z109: Total | AA109: =SUM(AA102:AA108) -> 0
C110: =SUM(C102:C109) -> 0 | D110: =SUM(D102:D109) -> 0 | E110: =SUM(E102:E109) -> 0 | F110: =SUM(F102:F109) -> 0 | G110: =SUM(G102:G109) -> 0 | H110: =SUM(H102:H109) -> 0 | I110: =SUM(I102:I109) -> 0 | J110: =SUM(J102:J109) -> 0 | ... X110: =SUM(X102:X109) -> 0 | Y110: =I110+N110+X110 -> 0
...

Sheet ADM_Custo
A2: Custo Total (+ Provisões) | B2: ADM 2026 | C2: Janeiro | D2: Fevereiro | E2: Março | F2: Abril | G2: Maio | H2: Junho | I2: Julho | J2: Agosto | K2: Setembro | L2: Outubro | M2: Novembro | N2: Dezembro | O2: Total | Q2: ADM 2026 | R2: Jan | S2: Fev | T2: Mar | U2: Abr | V2: Mai | W2: Jun | X2: Jul | Y2: Ago | Z2: Set | AA2: Out | AB2: Nov | AC2: Dez
B3: Salário | C3: =ADM_Fopag!AA3 -> 13300 | D3: =ADM_Fopag!AA14 -> 19300 | E3: =ADM_Fopag!AA25 -> 20400 | F3: =ADM_Fopag!AA36 -> 19100 | G3: =ADM_Fopag!AA47 -> 0 | H3: =ADM_Fopag!AA58 -> 0 | I3: =ADM_Fopag!AA69 -> 0 | J3: =ADM_Fopag!AA80 -> 0 | K3: =ADM_Fopag!AA91 -> 0 | L3: =ADM_Fopag!AA102 -> 0 | M3: =ADM_Fopag!AA113 -> 0 | N3: =ADM_Fopag!AA124 -> 0 | O3: =SUM(C3:N3) -> 72100 | Q3: Efetivo Inicial (Un) | R3: =ADM_Movimentações!O2 -> 3 | S3: =ADM_Movimentações!O11 -> 4 | T3: =ADM_Movimentações!O20 -> 6 | U3: =ADM_Movimentações!O29 -> 6 | V3: =ADM_Movimentações!O38 -> 5 | W3: =ADM_Movimentações!O47 -> 5 | X3: =ADM_Movimentações!O56 -> 5 | Y3: =ADM_Movimentações!O65 -> 5 | Z3: =ADM_Movimentações!O74 -> 5 | AA3: =ADM_Movimentações!O83 -> 5 | AB3: =ADM_Movimentações!O92 -> 5 | AC3: =ADM_Movimentações!O101 -> 5
B4: Prolabore | C4: =ADM_Fopag!AA4 -> 4863 | D4: =ADM_Fopag!AA15 -> 4863 | E4: =ADM_Fopag!AA26 -> 4863 | F4: =ADM_Fopag!AA37 -> 4863 | G4: =ADM_Fopag!AA48 -> 0 | H4: =ADM_Fopag!AA59 -> 0 | I4: =ADM_Fopag!AA70 -> 0 | J4: =ADM_Fopag!AA81 -> 0 | K4: =ADM_Fopag!AA92 -> 0 | L4: =ADM_Fopag!AA103 -> 0 | M4: =ADM_Fopag!AA114 -> 0 | N4: =ADM_Fopag!AA125 -> 0 | O4: =SUM(C4:N4) -> 19452 | Q4: Afastamentos | R4: =ADM_Movimentações!R5+ADM_Movimentações!U2+ADM_Movimentações!U3 -> 13 | S4: =ADM_Movimentações!R14 -> 12 | T4: =ADM_Movimentações!R23+ADM_Movimentações!U20+ADM_Movimentações!U21 -> 0 | U4: =ADM_Movimentações!R32+ADM_Movimentações!U29+ADM_Movimentações!U30 -> 9 | V4: =ADM_Movimentações!R41+ADM_Movimentações!U38+ADM_Movimentações!U39 -> 0 | W4: =ADM_Movimentações!R50+ADM_Movimentações!U47+ADM_Movimentações!U48 -> 0 | X4: =ADM_Movimentações!R59+ADM_Movimentações!U56+ADM_Movimentações!U57 -> 0 | Y4: =ADM_Movimentações!R68+ADM_Movimentações!U65+ADM_Movimentações!U66 -> 0 | Z4: =ADM_Movimentações!R77+ADM_Movimentações!U74+ADM_Movimentações!U75 -> 0 | AA4: =ADM_Movimentações!R86+ADM_Movimentações!U83+ADM_Movimentações!U84 -> 0 | AB4: =ADM_Movimentações!R95+ADM_Movimentações!U92+ADM_Movimentações!U93 -> 0 | AC4: =ADM_Movimentações!R104+ADM_Movimentações!U101+ADM_Movimentações!U102 -> 0
B5: Dist. Lucro | C5: =ADM_Fopag!AA5 -> 27707 | D5: =ADM_Fopag!AA16 -> 27707 | E5: =ADM_Fopag!AA27 -> 27707 | F5: =ADM_Fopag!AA38 -> 27707 | G5: =ADM_Fopag!AA49 -> 0 | H5: =ADM_Fopag!AA60 -> 0 | I5: =ADM_Fopag!AA71 -> 0 | J5: =ADM_Fopag!AA82 -> 0 | K5: =ADM_Fopag!AA93 -> 0 | L5: =ADM_Fopag!AA104 -> 0 | M5: =ADM_Fopag!AA115 -> 0 | N5: =ADM_Fopag!AA126 -> 0 | O5: =SUM(C5:N5) -> 110828 | Q5: Novas Contratações (Un) | R5: =ADM_Movimentações!R2 -> 1 | S5: =ADM_Movimentações!R11 -> 2 | T5: =ADM_Movimentações!R20 -> 0 | U5: =ADM_Movimentações!R29 -> 0 | V5: =ADM_Movimentações!R38 -> 0 | W5: =ADM_Movimentações!R47 -> 0 | X5: =ADM_Movimentações!R56 -> 0 | Y5: =ADM_Movimentações!R65 -> 0 | Z5: =ADM_Movimentações!R74 -> 0 | AA5: =ADM_Movimentações!R83 -> 0 | AB5: =ADM_Movimentações!R92 -> 0 | AC5: =ADM_Movimentações!R101 -> 0
B6: Benefício | C6: =ADM_Fopag!AA6 -> 8661.88 | D6: =ADM_Fopag!AA17 -> 11761.88 | E6: =ADM_Fopag!AA28 -> 12261.88 | F6: =ADM_Fopag!AA39 -> 11361.88 | G6: =ADM_Fopag!AA50 -> 0 | H6: =ADM_Fopag!AA61 -> 0 | I6: =ADM_Fopag!AA72 -> 0 | J6: =ADM_Fopag!AA83 -> 0 | K6: =ADM_Fopag!AA94 -> 0 | L6: =ADM_Fopag!AA105 -> 0 | M6: =ADM_Fopag!AA116 -> 0 | N6: =ADM_Fopag!AA127 -> 0 | O6: =SUM(C6:N6) -> 44047.52 | Q6: Desligamentos (Un) | R6: =ADM_Movimentações!R3 -> 0 | S6: =ADM_Movimentações!R12 -> 0 | T6: =ADM_Movimentações!R21 -> 0 | U6: =ADM_Movimentações!R30 -> 1 | V6: =ADM_Movimentações!R39 -> 0 | W6: =ADM_Movimentações!R48 -> 0 | X6: =ADM_Movimentações!R57 -> 0 | Y6: =ADM_Movimentações!R66 -> 0 | Z6: =ADM_Movimentações!R75 -> 0 | AA6: =ADM_Movimentações!R84 -> 0 | AB6: =ADM_Movimentações!R93 -> 0 | AC6: =ADM_Movimentações!R102 -> 0
B7: Patronal | C7: =ADM_Fopag!AA7 -> 4165.83 | D7: =ADM_Fopag!AA18 -> 5803.83 | E7: =ADM_Fopag!AA29 -> 6104.13 | F7: =ADM_Fopag!AA40 -> 5749.23 | G7: =ADM_Fopag!AA51 -> 0 | H7: =ADM_Fopag!AA62 -> 0 | I7: =ADM_Fopag!AA73 -> 0 | J7: =ADM_Fopag!AA84 -> 0 | K7: =ADM_Fopag!AA95 -> 0 | L7: =ADM_Fopag!AA106 -> 0 | M7: =ADM_Fopag!AA117 -> 0 | N7: =ADM_Fopag!AA128 -> 0 | O7: =SUM(C7:N7) -> 21823.02 | Q7: Horas Programadas | R7: =ADM_Movimentações!AF4 -> 739.2 | S7: =ADM_Movimentações!AF13 -> 1003.2 | T7: =ADM_Movimentações!AF22 -> 1161.6 | U7: =ADM_Movimentações!AF31 -> 880 | V7: =ADM_Movimentações!AF40 -> 0 | W7: =ADM_Movimentações!AF49 -> 0 | X7: =ADM_Movimentações!AF58 -> 0 | Y7: =ADM_Movimentações!AF67 -> 0 | Z7: =ADM_Movimentações!AF76 -> 0 | AA7: =ADM_Movimentações!AF85 -> 0 | AB7: =ADM_Movimentações!AF94 -> 0 | AC7: =ADM_Movimentações!AF103 -> 0
B8: FGTS | C8: =ADM_Fopag!AA8 -> 1064 | D8: =ADM_Fopag!AA19 -> 1544 | E8: =ADM_Fopag!AA30 -> 1632 | F8: =ADM_Fopag!AA41 -> 1528 | G8: =ADM_Fopag!AA52 -> 0 | H8: =ADM_Fopag!AA63 -> 0 | I8: =ADM_Fopag!AA74 -> 0 | J8: =ADM_Fopag!AA85 -> 0 | K8: =ADM_Fopag!AA96 -> 0 | L8: =ADM_Fopag!AA107 -> 0 | M8: =ADM_Fopag!AA118 -> 0 | N8: =ADM_Fopag!AA129 -> 0 | O8: =SUM(C8:N8) -> 5768 | Q8: Horas não Produtivas | R8: =ADM_Movimentações!AF5 -> 114.4 | S8: =ADM_Movimentações!AF14 -> 105.6 | T8: =ADM_Movimentações!AF23 -> 0 | U8: =ADM_Movimentações!AF32 -> 79.2 | V8: =ADM_Movimentações!AF41 -> 0 | W8: =ADM_Movimentações!AF50 -> 0 | X8: =ADM_Movimentações!AF59 -> 0 | Y8: =ADM_Movimentações!AF68 -> 0 | Z8: =ADM_Movimentações!AF77 -> 0 | AA8: =ADM_Movimentações!AF86 -> 0 | AB8: =ADM_Movimentações!AF95 -> 0 | AC8: =ADM_Movimentações!AF104 -> 0
B9: Provisão | C9: =ADM_Fopag!AA9 -> 5678.3611 | D9: =ADM_Fopag!AA20 -> 8240.0278 | E9: =ADM_Fopag!AA31 -> 8709.6667 | F9: =ADM_Fopag!AA42 -> 8154.6389 | G9: =ADM_Fopag!AA53 -> 0 | H9: =ADM_Fopag!AA64 -> 0 | I9: =ADM_Fopag!AA75 -> 0 | J9: =ADM_Fopag!AA86 -> 0 | K9: =ADM_Fopag!AA97 -> 0 | L9: =ADM_Fopag!AA108 -> 0 | M9: =ADM_Fopag!AA119 -> 0 | N9: =ADM_Fopag!AA130 -> 0 | O9: =SUM(C9:N9) -> 30782.694 | Q9: Efetivo Médio | R9: =ADM_Movimentações!AF6 -> 3.3809524 | S9: =ADM_Movimentações!AF15 -> 5.3684211 | T9: =ADM_Movimentações!AF24 -> 6 | U9: =ADM_Movimentações!AF33 -> 4.55 | V9: =IFERROR(ADM_Movimentações!AF42,0) -> 0 | W9: =IFERROR(ADM_Movimentações!AF51,0) -> 0 | X9: =IFERROR(ADM_Movimentações!AF60,0) -> 0 | Y9: =IFERROR(ADM_Movimentações!AF69,0) -> 0 | Z9: =IFERROR(ADM_Movimentações!AF78,0) -> 0 | AA9: =IFERROR(ADM_Movimentações!AF87,0) -> 0 | AB9: =IFERROR(ADM_Movimentações!AF96,0) -> 0 | AC9: =IFERROR(ADM_Movimentações!AF105,0) -> 0
B10: Total | C10: =SUM(C3:C9) -> 65440.071 | D10: =SUM(D3:D9) -> 79219.738 | E10: =SUM(E3:E9) -> 81677.677 | F10: =SUM(F3:F9) -> 78463.749 | G10: =SUM(G3:G9) -> 0 | H10: =SUM(H3:H9) -> 0 | I10: =SUM(I3:I9) -> 0 | J10: =SUM(J3:J9) -> 0 | ... O10: =SUM(O3:O9) -> 304801.23 | Q10: Efetivo Final | R10: =ADM_Movimentações!R4 -> 4 | S10: =ADM_Movimentações!R13 -> 6 | T10: =ADM_Movimentações!R22 -> 6 | U10: =ADM_Movimentações!R31 -> 5 | V10: =ADM_Movimentações!R40 -> 5 | W10: =ADM_Movimentações!R49 -> 5 | X10: =ADM_Movimentações!R58 -> 5 | Y10: =ADM_Movimentações!R67 -> 5 | Z10: =ADM_Movimentações!R76 -> 5 | AA10: =ADM_Movimentações!R85 -> 5 | AB10: =ADM_Movimentações!R94 -> 5 | AC10: =ADM_Movimentações!R103 -> 5
B13: Mês | C13: Faturam. | D13: Custo | E13: % | F13: Meta | G13: Colab | H13: Fat x Colab
B14: Jan | C14: 1908972 | D14: =C10 -> 65440.071 | E14: =D14/C14 -> 0.034280268 | F14: 0.04 | G14: =R10 -> 4 | H14: =C14/G14 -> 477243
B15: Fev | C15: 1434145 | D15: =D10 -> 79219.738 | E15: =D15/C15 -> 0.055238304 | F15: 0.04 | G15: =S10 -> 6 | H15: =C15/G15 -> 239024.17
B16: Mar | C16: 1661970 | D16: =E10 -> 81677.677 | E16: =D16/C16 -> 0.049145097 | F16: 0.04 | G16: =T10 -> 6 | H16: =C16/G16 -> 276995
B17: Abr | C17: 1747250 | D17: =F10 -> 78463.749 | E17: =D17/C17 -> 0.044906996 | F17: 0.04 | G17: =U10 -> 5 | H17: =C17/G17 -> 349450
B18: Mai | D18: =G10 -> 0
B19: Jun | D19: =H10 -> 0
B20: Jul | D20: =I10 -> 0
B21: Ago | D21: =J10 -> 0
B22: Set | D22: =K10 -> 0
B23: Out | D23: =L10 -> 0
B24: Nov | D24: =M10 -> 0
B25: Dez | D25: =N10 -> 0
B29: Turnover (Rotatividade de Pessoal)
B30: Ano: | E30: 2026 | G30: Meta: | H30: 0.15
B31: Mês | C31: Admissões | D31: Desligamentos | E31: Colaboradores | F31: Turnover | G31: Média | H31: Meta
B32: Jan | C32: =R5 -> 1 | D32: =R6 -> 0 | E32: =R10 -> 4 | F32: =((Table_464[[#This Row],[Desligamentos]]+Table_464[[#This Row],[Admissões]])/2)/Table_464[[#This Row],[Colaboradores]] -> 0.125 | G32: =AVERAGE(F32) -> 0.125 | H32: =$H$30 -> 0.15
B33: Fev | C33: =S5 -> 2 | D33: =S6 -> 0 | E33: =S10 -> 6 | F33: =((Table_464[[#This Row],[Desligamentos]]+Table_464[[#This Row],[Admissões]])/2)/Table_464[[#This Row],[Colaboradores]] -> 0.16666667 | G33: =AVERAGE($F$32:$F33) -> 0.14583333 | H33: =$H$30 -> 0.15
B34: Mar | C34: =T5 -> 0 | D34: =T6 -> 0 | E34: =T10 -> 6 | F34: =((Table_464[[#This Row],[Desligamentos]]+Table_464[[#This Row],[Admissões]])/2)/Table_464[[#This Row],[Colaboradores]] -> 0 | G34: =AVERAGE($F$32:$F34) -> 0.097222222 | H34: =$H$30 -> 0.15
B35: Abr | C35: =U5 -> 0 | D35: =U6 -> 1 | E35: =U10 -> 5 | F35: =((Table_464[[#This Row],[Desligamentos]]+Table_464[[#This Row],[Admissões]])/2)/Table_464[[#This Row],[Colaboradores]] -> 0.1 | G35: =AVERAGE($F$32:$F35) -> 0.097916667 | H35: =$H$30 -> 0.15
B36: Mai | C36: =V5 -> 0 | D36: =V6 -> 0 | E36: =V10 -> 5 | F36: =((Table_464[[#This Row],[Desligamentos]]+Table_464[[#This Row],[Admissões]])/2)/Table_464[[#This Row],[Colaboradores]] -> 0 | G36: =AVERAGE($F$32:$F36) -> 0.078333333 | H36: =$H$30 -> 0.15
B37: Jun | C37: =W5 -> 0 | D37: =W6 -> 0 | E37: =W10 -> 5 | F37: =((Table_464[[#This Row],[Desligamentos]]+Table_464[[#This Row],[Admissões]])/2)/Table_464[[#This Row],[Colaboradores]] -> 0 | G37: =AVERAGE($F$32:$F37) -> 0.065277778 | H37: =$H$30 -> 0.15
B38: Jul | C38: =X5 -> 0 | D38: =X6 -> 0 | E38: =X10 -> 5 | F38: =((Table_464[[#This Row],[Desligamentos]]+Table_464[[#This Row],[Admissões]])/2)/Table_464[[#This Row],[Colaboradores]] -> 0 | G38: =AVERAGE($F$32:$F38) -> 0.055952381 | H38: =$H$30 -> 0.15
B39: Ago | C39: =Y5 -> 0 | D39: =Y6 -> 0 | E39: =Y10 -> 5 | F39: =((Table_464[[#This Row],[Desligamentos]]+Table_464[[#This Row],[Admissões]])/2)/Table_464[[#This Row],[Colaboradores]] -> 0 | G39: =AVERAGE($F$32:$F39) -> 0.048958333 | H39: =$H$30 -> 0.15
B40: Set | C40: =Z5 -> 0 | D40: =Z6 -> 0 | E40: =Z10 -> 5 | F40: =((Table_464[[#This Row],[Desligamentos]]+Table_464[[#This Row],[Admissões]])/2)/Table_464[[#This Row],[Colaboradores]] -> 0 | G40: =AVERAGE($F$32:$F40) -> 0.043518519 | H40: =$H$30 -> 0.15
B41: Out | C41: =AA5 -> 0 | D41: =AA6 -> 0 | E41: =AA10 -> 5 | F41: =((Table_464[[#This Row],[Desligamentos]]+Table_464[[#This Row],[Admissões]])/2)/Table_464[[#This Row],[Colaboradores]] -> 0 | G41: =AVERAGE($F$32:$F41) -> 0.039166667 | H41: =$H$30 -> 0.15
B42: Nov | C42: =AB5 -> 0 | D42: =AB6 -> 0 | E42: =AB10 -> 5 | F42: =((Table_464[[#This Row],[Desligamentos]]+Table_464[[#This Row],[Admissões]])/2)/Table_464[[#This Row],[Colaboradores]] -> 0 | G42: =AVERAGE($F$32:$F42) -> 0.035606061 | H42: =$H$30 -> 0.15
B43: Dez | C43: =AC5 -> 0 | D43: =AC6 -> 0 | E43: =AC10 -> 5 | F43: =((Table_464[[#This Row],[Desligamentos]]+Table_464[[#This Row],[Admissões]])/2)/Table_464[[#This Row],[Colaboradores]] -> 0 | G43: =AVERAGE($F$32:$F43) -> 0.032638889 | H43: =$H$30 -> 0.15
B44: Cálculo: [(Nº de desligados + Nº de admitidos) / 2] / (Nº total de colaboradores).
B46: Absenteísmo (Ausências no Trabalho)
B47: Ano: | E47: 2026 | F47: Meta: | G47: 0.15
B48: Mês | C48: H Program | D48: H. N. Prod. | E48: Absenteísmo | F48: Média | G48: Meta
B49: Jan | C49: =R7 -> 739.2 | D49: =R8 -> 114.4 | E49: =IFERROR(D49/C49,0) -> 0.1547619 | F49: =IFERROR(AVERAGE($E$49:E49),0) -> 0.1547619 | G49: =$G$47 -> 0.15
B50: Fev | C50: =S7 -> 1003.2 | D50: =S8 -> 105.6 | E50: =IFERROR(D50/C50,0) -> 0.10526316 | F50: =IFERROR(AVERAGE($E$49:E50),0) -> 0.13001253 | G50: =$G$47 -> 0.15
B51: Mar | C51: =T7 -> 1161.6 | D51: =T8 -> 0 | E51: =IFERROR(D51/C51,0) -> 0 | F51: =IFERROR(AVERAGE($E$49:E51),0) -> 0.086675021 | G51: =$G$47 -> 0.15
B52: Abr | C52: =U7 -> 880 | D52: =U8 -> 79.2 | E52: =IFERROR(D52/C52,0) -> 0.09 | F52: =IFERROR(AVERAGE($E$49:E52),0) -> 0.087506266 | G52: =$G$47 -> 0.15
B53: Mai | C53: =V7 -> 0 | D53: =V8 -> 0 | E53: =IFERROR(D53/C53,0) -> 0 | F53: =IFERROR(AVERAGE($E$49:E53),0) -> 0.070005013 | G53: =$G$47 -> 0.15
B54: Jun | C54: =W7 -> 0 | D54: =W8 -> 0 | E54: =IFERROR(D54/C54,0) -> 0 | F54: =IFERROR(AVERAGE($E$49:E54),0) -> 0.05833751 | G54: =$G$47 -> 0.15
B55: Jul | C55: =X7 -> 0 | D55: =X8 -> 0 | E55: =IFERROR(D55/C55,0) -> 0 | F55: =IFERROR(AVERAGE($E$49:E55),0) -> 0.05000358 | G55: =$G$47 -> 0.15
B56: Ago | C56: =Y7 -> 0 | D56: =Y8 -> 0 | E56: =IFERROR(D56/C56,0) -> 0 | F56: =IFERROR(AVERAGE($E$49:E56),0) -> 0.043753133 | G56: =$G$47 -> 0.15
B57: Set | C57: =Z7 -> 0 | D57: =Z8 -> 0 | E57: =IFERROR(D57/C57,0) -> 0 | F57: =IFERROR(AVERAGE($E$49:E57),0) -> 0.038891674 | G57: =$G$47 -> 0.15
B58: Out | C58: =AA7 -> 0 | D58: =AA8 -> 0 | E58: =IFERROR(D58/C58,0) -> 0 | F58: =IFERROR(AVERAGE($E$49:E58),0) -> 0.035002506 | G58: =$G$47 -> 0.15
B59: Nov | C59: =AB7 -> 0 | D59: =AB8 -> 0 | E59: =IFERROR(D59/C59,0) -> 0 | F59: =IFERROR(AVERAGE($E$49:E59),0) -> 0.03182046 | G59: =$G$47 -> 0.15
B60: Dez | C60: =AC7 -> 0 | D60: =AC8 -> 0 | E60: =IFERROR(D60/C60,0) -> 0 | F60: =IFERROR(AVERAGE($E$49:E60),0) -> 0.029168755 | G60: =$G$47 -> 0.15

Sheet IND_Cadastro
B2: Funcionário | C2: CPF | D2: Nome do Funcionário | E2: Departamento | F2: Admissão | G2: Demissão
B3: 150 | C3: 20421719729 | D3: AMANDA BEATRIZ ALVES DA SILVA | E3: Telemassas | F3: 11/04/2025 | G3: 25/02/2026
B4: 115 | C4: 17622871702 | D4: ANAILSON DA CONCEICAO RICARTE | E4: Telemassas | F4: 15/04/2024
B5: 160 | C5: 14212723778 | D5: BRENO BERUDIO BARBOZA | E5: Telemassas | F5: 11/03/2026
B6: 130 | C6: 16044643727 | D6: CASSIA COELHO RAMOS | E6: Telemassas | F6: 17/10/2024
B7: 158 | C7: 18596219706 | D7: CASSIO PEREIRA TOMAS | E7: Telemassas | F7: 01/12/2025 | G7: 31/03/2026
B8: 128 | C8: 15560372790 | D8: DAYSA GREGORIO VENANCIO | E8: Telemassas | F8: 15/10/2024 | G8: 25/02/2026
B9: 4 | C9: 12576147704 | D9: DENIZE MOREIRA COELHO MARTINS | E9: Yup | F9: 17/03/2023
B10: 35 | C10: 9621821762 | D10: EDINEIA MARIA LOPES DA SILVA | E10: Telemassas | F10: 03/01/2022
B11: 3 | C11: 86749072704 | D11: EDSON JOSE DE SOUZA | E11: Yup | F11: 20/02/2025
B12: 36 | C12: 7452452771 | D12: ERMINDA MARIA LOPES FACCINI | E12: Telemassas | F12: 03/01/2022
B13: 151 | C13: 14935558717 | D13: FELIPE SANSAO POLETTO | E13: Telemassas | F13: 22/04/2025 | G13: 18/02/2026
B14: 6 | C14: 7728013637 | D14: GIORDANO BRUNO GARIBALDI | E14: Yup | F14: 19/11/2025
B15: 109 | C15: 17911909792 | D15: HUGO BERUDIO AMORIM | E15: Telemassas | F15: 14/08/2023
B16: 156 | C16: 13021410740 | D16: JAMAICA PENA ALIPIO | E16: Telemassas | F16: 01/12/2025 | G16: 09/02/2026
B17: 100 | C17: 21963396790 | D17: JOSE GUILHERME TEIXEIRA BRAGA | E17: Telemassas | F17: 18/05/2023
B18: 133 | C18: 17471881747 | D18: LILIANE APARECIDA CANDIDA DA SILVA | E18: Telemassas | F18: 22/10/2024 | G18: 12/02/2026
B19: 153 | C19: 19379132794 | D19: LORENA BARBOSA BOEQUE | E19: Telemassas | F19: 23/06/2025
B20: 123 | C20: 17622438731 | D20: LORENA DE OLIVEIRA LUZORIO | E20: Telemassas | F20: 10/10/2024 | G20: 04/03/2026
B21: 154 | C21: 17444522707 | D21: LOSAINE LOPES DE OLIVEIRA | E21: Telemassas | F21: 11/09/2025 | G21: 18/02/2026
B22: 63 | C22: 8932910723 | D22: LOURDINHA COELHO BERUDIO | E22: Telemassas | F22: 21/03/2022
B23: 135 | C23: 9823424705 | D23: LUCIENE MENEGUETTI TEDESCO | E23: Telemassas | F23: 01/11/2024
B24: 5 | C24: 14676408757 | D24: LUIZ ZANAO | E24: Yup | F24: 28/04/2025
B25: 147 | C25: 18605506733 | D25: MARCOS EDUARDO DE SOUZA GOMES | E25: Telemassas | F25: 13/03/2025
B26: 99 | C26: 11968033742 | D26: MARIA APARECIDA DANIEL | E26: Telemassas | F26: 10/04/2023
B27: 54 | C27: 540533742 | D27: MARIA APARECIDA LOPES | E27: Telemassas | F27: 03/01/2022
B28: 42 | C28: 8126990767 | D28: MARIA DA PENHA SILVA VIANA | E28: Telemassas | F28: 03/01/2022
B29: 43 | C29: 6143838623 | D29: MARIA ESTER DA ROCHA GARIBALDI | E29: Telemassas | F29: 03/01/2022
B30: 124 | C30: 11779661746 | D30: MARIA JOSE DE SOUZA BRAGA SCHROEDER | E30: Telemassas | F30: 10/10/2024 | G30: 25/02/2026
B31: 148 | C31: 19168959729 | D31: NATAN ALVES DE OLIVEIRA | E31: Telemassas | F31: 13/03/2025
B32: 157 | C32: 18019744703 | D32: RUAN MOREIRA MARTINS | E32: Telemassas | F32: 01/12/2025
B33: 48 | C33: 9825505702 | D33: SANDRA DANIEL | E33: Telemassas | F33: 03/01/2022
B34: 1 | C34: 20832236756 | D34: SARIDIA RAMOS BROEDEL | E34: Yup | F34: 17/03/2023
B35: 155 | C35: 12178701728 | D35: TEREZINHA DE LOURDES OLIVEIRA | E35: Telemassas | F35: 12/09/2025 | G35: 15/01/2026
B36: 159 | C36: 11347893784 | D36: THAIS FRANCELI LOPES DE SOUZA GOMES | E36: Telemassas | F36: 23/02/2026
B37: 144 | C37: 9630506726 | D37: VANUZA DE OLIVEIRA GOMES | E37: Telemassas | F37: 18/02/2025
B38: 126 | C38: 11765503736 | D38: ZILNEIDE DA CONCEICAO | E38: Telemassas | F38: 10/10/2024
B39: 52 | C39: 9922359790 | D39: ZIRLENE APARECIDA DE OLIVEIRA TOMAS DA SILVA | E39: Telemassas | F39: 03/01/2022

Sheet IND_Movimentações
B2: Funcionário | C2: CPF | D2: Nome do Funcionário | E2: Departamento | F2: Admissão | G2: Demissão | H2: Afastamento | I2: Dias | J2: Faltas | K2: Dias | L2: Férias | M2: Dias | O2: Início Colab. | P2: 35 | R2: Admissão | S2: =F38 -> 0 | U2: Faltas | V2: =K38 -> 11 | X2: Janeiro 2026 | AF2: D. Produtivo | AG2: =(V8-V3-V2-S5) -> 653.5
B3: 150 | C3: 20421719729 | D3: AMANDA BEATRIZ ALVES DA SILVA | E3: Telemassas | I3: 0 | K3: 0 | L3: 01 a 04 | M3: 1 | R3: Demissão | S3: =G38 -> 1 | U3: Férias | V3: =M38 -> 50 | X3: Dom | Y3: Seg | Z3: Ter | AA3: Qua | AB3: Qui | AC3: Sex | AD3: Sáb | AF3: D. N. Produt. | AG3: =V8-AG2 -> 71
B4: 115 | C4: 17622871702 | D4: ANAILSON DA CONCEICAO RICARTE | E4: Telemassas | I4: 0 | K4: 0 | L4: 01 a 04 | M4: 1 | R4: Fim Colab | S4: =P2+S2-S3 -> 34 | U4: Colaboradores | V4: =L38 -> 35 | AB4: 46023 | AC4: 46024 | AD4: 46025 | AF4: Horas Program. | AG4: =(S4*8.8)*S7 -> 6283.2
B5: 130 | C5: 16044643727 | D5: CASSIA COELHO RAMOS | E5: Telemassas | I5: 0 | K5: 0 | L5: 01 a 04 | M5: 1 | R5: Afastam. | S5: =I38 -> 10 | X5: 46026 | Y5: 46027 | Z5: 46028 | AA5: 46029 | AB5: 46030 | AC5: 46031 | AD5: 46032 | AF5: H. N. Produtiva | AG5: =AG3*8.8 -> 624.8
B6: 158 | C6: 18596219706 | D6: CASSIO PEREIRA TOMAS | E6: Telemassas | I6: 0 | K6: 0 | L6: 01 a 04 | M6: 1 | X6: 46033 | Y6: 46034 | Z6: 46035 | AA6: 46036 | AB6: 46037 | AC6: 46038 | AD6: 46039 | AF6: Efetivo Pessoal | AG6: =(AG4-AG5)/(8.8*S7) -> 30.619048
B7: 128 | C7: 15560372790 | D7: DAYSA GREGORIO VENANCIO | E7: Telemassas | I7: 0 | K7: 0 | L7: 01 a 04 | M7: 1 | R7: Dias Úteis | S7: 21 | U7: Efet. Méd. | V7: =(P2+S4)/2 -> 34.5 | X7: 46040 | Y7: 46041 | Z7: 46042 | AA7: 46043 | AB7: 46044 | AC7: 46045 | AD7: 46046
B8: 4 | C8: 12576147704 | D8: DENIZE MOREIRA COELHO MARTINS | E8: Yup | I8: 0 | K8: 0 | L8: 01 a 04 | M8: 1 | R8: Não Úteis | S8: 10 | U8: D. Program. | V8: =S7*V7 -> 724.5 | X8: 46047 | Y8: 46048 | Z8: 46049 | AA8: 46050 | AB8: 46051 | AC8: 46052 | AD8: 46053
B9: 35 | C9: 9621821762 | D9: EDINEIA MARIA LOPES DA SILVA | E9: Telemassas | I9: 0 | K9: 0 | L9: 01 a 04 | M9: 1
B10: 3 | C10: 86749072704 | D10: EDSON JOSE DE SOUZA | E10: Yup | H10: 9 | I10: 1 | K10: 0 | L10: 01 a 04 | M10: 1
B11: 36 | C11: 7452452771 | D11: ERMINDA MARIA LOPES FACCINI | E11: Telemassas | I11: 0 | K11: 0 | L11: 01 a 04 | M11: 1
B12: 151 | C12: 14935558717 | D12: FELIPE SANSAO POLETTO | E12: Telemassas | I12: 0 | K12: 0 | L12: 01 a 04 | M12: 1
B13: 6 | C13: 7728013637 | D13: GIORDANO BRUNO GARIBALDI | E13: Yup | I13: 0 | K13: 0 | L13: 01 a 04 | M13: 1
B14: 109 | C14: 17911909792 | D14: HUGO BERUDIO AMORIM | E14: Telemassas | I14: 0 | K14: 0 | L14: 01 a 04 | M14: 1
B15: 156 | C15: 13021410740 | D15: JAMAICA PENA ALIPIO | E15: Telemassas | I15: 0 | K15: 0 | L15: 01 a 04 | M15: 1
B16: 100 | C16: 21963396790 | D16: JOSE GUILHERME TEIXEIRA BRAGA | E16: Telemassas | I16: 0 | K16: 0 | L16: 01 a 04 | M16: 1
B17: 133 | C17: 17471881747 | D17: LILIANE APARECIDA CANDIDA DA SILVA | E17: Telemassas | I17: 0 | K17: 0 | L17: 01 a 18 | M17: 11
B18: 153 | C18: 19379132794 | D18: LORENA BARBOSA BOEQUE | E18: Telemassas | I18: 0 | K18: 0 | L18: 01 a 04 | M18: 1
B19: 123 | C19: 17622438731 | D19: LORENA DE OLIVEIRA LUZORIO | E19: Telemassas | I19: 0 | K19: 0 | L19: 01 a 04 | M19: 1
B20: 154 | C20: 17444522707 | D20: LOSAINE LOPES DE OLIVEIRA | E20: Telemassas | I20: 0 | K20: 0 | L20: 01 a 04 | M20: 1
B21: 63 | C21: 8932910723 | D21: LOURDINHA COELHO BERUDIO | E21: Telemassas | I21: 0 | K21: 0 | L21: 01 a 04 | M21: 1
B22: 135 | C22: 9823424705 | D22: LUCIENE MENEGUETTI TEDESCO | E22: Telemassas | I22: 0 | K22: 0 | L22: 01 a 04 | M22: 1
... B24: 147 | C24: 18605506733 | D24: MARCOS EDUARDO DE SOUZA GOMES | E24: Telemassas | I24: 0 | K24: 0 | L24: 01 a 04 | M24: 1
B25: 99 | C25: 11968033742 | D25: MARIA APARECIDA DANIEL | E25: Telemassas | H25: 01 a 14 | I25: 9 | K25: 0 | L25: 01 a 04 | M25: 1
B26: 54 | C26: 540533742 | D26: MARIA APARECIDA LOPES | E26: Telemassas | I26: 0 | K26: 0 | L26: 01 a 04 | M26: 1
B27: 42 | C27: 8126990767 | D27: MARIA DA PENHA SILVA VIANA | E27: Telemassas | I27: 0 | K27: 0 | L27: 01 a 04 | M27: 1
B28: 43 | C28: 6143838623 | D28: MARIA ESTER DA ROCHA GARIBALDI | E28: Telemassas | I28: 0 | K28: 0 | L28: 01 a 04 | M28: 1
B29: 124 | C29: 11779661746 | D29: MARIA JOSE DE SOUZA BRAGA SCHROEDER | E29: Telemassas | I29: 0 | K29: 0 | L29: 01 a 04 | M29: 1
B30: 148 | C30: 19168959729 | D30: NATAN ALVES DE OLIVEIRA | E30: Telemassas | I30: 0 | K30: 0 | L30: 01 a 04 | M30: 1
B31: 157 | C31: 18019744703 | D31: RUAN MOREIRA MARTINS | E31: Telemassas | I31: 0 | K31: 0 | L31: 01 a 04 | M31: 1
B32: 48 | C32: 9825505702 | D32: SANDRA DANIEL | E32: Telemassas | I32: 0 | K32: 0 | L32: 01 a 04 | M32: 1
B33: 1 | C33: 20832236756 | D33: SARIDIA RAMOS BROEDEL | E33: Yup | I33: 0 | K33: 0 | L33: 01 a 10 | M33: 6
B34: 155 | C34: 12178701728 | D34: TEREZINHA DE LOURDES OLIVEIRA | E34: Telemassas | G34: 46037 | I34: 0 | J34: 16 a31 | K34: 11 | L34: 01 a 04 | M34: 1
B35: 144 | C35: 9630506726 | D35: VANUZA DE OLIVEIRA GOMES | E35: Telemassas | I35: 0 | K35: 0 | L35: 01 a 04 | M35: 1
B36: 126 | C36: 11765503736 | D36: ZILNEIDE DA CONCEICAO | E36: Telemassas | I36: 0 | K36: 0 | L36: 01 a 04 | M36: 1
B37: 52 | C37: 9922359790 | D37: ZIRLENE APARECIDA DE OLIVEIRA TOMAS DA SILVA | E37: Telemassas | I37: 0 | K37: 0 | L37: 01 a 04 | M37: 1
D38: =COUNTA(D3:D37) -> 35 | F38: =COUNTA(F3:F37) -> 0 | G38: =COUNTA(G3:G37) -> 1 | H38: =COUNTA(H3:H37) -> 2 | I38: =SUM(I3:I37) -> 10 | J38: =COUNTA(J3:J37) -> 1 | K38: =SUM(K3:K37) -> 11 | L38: =COUNTA(L3:L37) -> 35 | M38: =SUM(M3:M37) -> 50
B40: Funcionário | C40: CPF | D40: Nome do Funcionário | E40: Departamento | F40: Admissão | G40: Demissão | H40: Afastamento | I40: Dias | J40: Faltas | K40: Dias | L40: Férias | M40: Dias | O40: Início Colab. | P40: =S4 -> 34 | R40: Admissão | S40: =F76 -> 1 | U40: Faltas | V40: =K76 -> 0 | X40: Fevereiro 2026 | AF40: D. Produtivo | AG40: =(V46-V41-V40-S43) -> 529
B41: 150 | C41: 20421719729 | D41: AMANDA BEATRIZ ALVES DA SILVA | E41: Telemassas | G41: 46078 | I41: 0 | K41: 0 | M41: 0 | R41: Demissão | S41: =G76 -> 7 | U41: Férias | V41: =M76 -> 21 | X41: Dom | Y41: Seg | Z41: Ter | AA41: Qua | AB41: Qui | AC41: Sex | AD41: Sáb | AF41: D. N. Produt. | AG41: =V46-AG40 -> 29
B42: 115 | C42: 17622871702 | D42: ANAILSON DA CONCEICAO RICARTE | E42: Telemassas | I42: 0 | K42: 0 | M42: 0 | R42: Fim Colab | S42: =P40+S40-S41 -> 28 | U42: Colaboradores | V42: =L76 -> 2 | X42: 46054 | Y42: 46055 | Z42: 46056 | AA42: 46057 | AB42: 46058 | AC42: 46059 | AD42: 46060 | AF42: Horas Program. | AG42: =(S42*8.8)*S45 -> 4435.2
B43: 130 | C43: 16044643727 | D43: CASSIA COELHO RAMOS | E43: Telemassas | I43: 0 | K43: 0 | M43: 0 | R43: Afastam. | S43: =I76 -> 8 | X43: 46061 | Y43: 46062 | Z43: 46063 | AA43: 46064 | AB43: 46065 | AC43: 46066 | AD43: 46067 | AF43: H. N. Produtiva | AG43: =AG41*8.8 -> 255.2
B44: 158 | C44: 18596219706 | D44: CASSIO PEREIRA TOMAS | E44: Telemassas | I44: 0 | K44: 0 | M44: 0 | X44: 46068 | Y44: 46069 | Z44: 46070 | AA44: 46071 | AB44: 46072 | AC44: 46073 | AD44: 46074 | AF44: Efetivo Pessoal | AG44: =(AG42-AG43)/(8.8*S45) -> 26.388889
B45: 128 | C45: 15560372790 | D45: DAYSA GREGORIO VENANCIO | E45: Telemassas | G45: 46078 | I45: 0 | K45: 0 | M45: 0 | R45: Dias Úteis | S45: 18 | U45: Efet. Méd. | V45: =(P40+S42)/2 -> 31 | X45: 46075 | Y45: 46076 | Z45: 46077 | AA45: 46078 | AB45: 46079 | AC45: 46080 | AD45: 46081
B46: 4 | C46: 12576147704 | D46: DENIZE MOREIRA COELHO MARTINS | E46: Yup | I46: 0 | K46: 0 | M46: 0 | R46: Não Úteis | S46: 10 | U46: D. Program. | V46: =S45*V45 -> 558
B47: 35 | C47: 9621821762 | D47: EDINEIA MARIA LOPES DA SILVA | E47: Telemassas | I47: 0 | K47: 0 | M47: 0
B48: 3 | C48: 86749072704 | D48: EDSON JOSE DE SOUZA | E48: Yup | I48: 0 | K48: 0 | M48: 0
B49: 36 | C49: 7452452771 | D49: ERMINDA MARIA LOPES FACCINI | E49: Telemassas | I49: 0 | K49: 0 | M49: 0
B50: 151 | C50: 14935558717 | D50: FELIPE SANSAO POLETTO | E50: Telemassas | G50: 46071 | I50: 0 | K50: 0 | M50: 0
B51: 6 | C51: 7728013637 | D51: GIORDANO BRUNO GARIBALDI | E51: Yup | I51: 0 | K51: 0 | M51: 0
B52: 109 | C52: 17911909792 | D52: HUGO BERUDIO AMORIM | E52: Telemassas | I52: 0 | K52: 0 | L52: 11 a 26 | M52: 11
B53: 156 | C53: 13021410740 | D53: JAMAICA PENA ALIPIO | E53: Telemassas | G53: 46066 | I53: 0 | K53: 0 | M53: 0
B54: 100 | C54: 21963396790 | D54: JOSE GUILHERME TEIXEIRA BRAGA | E54: Telemassas | I54: 0 | K54: 0 | M54: 0
B55: 133 | C55: 17471881747 | D55: LILIANE APARECIDA CANDIDA DA SILVA | E55: Telemassas | G55: 46065 | I55: 0 | K55: 0 | M55: 0
B56: 153 | C56: 19379132794 | D56: LORENA BARBOSA BOEQUE | E56: Telemassas | I56: 0 | K56: 0 | M56: 0
B57: 123 | C57: 17622438731 | D57: LORENA DE OLIVEIRA LUZORIO | E57: Telemassas | I57: 0 | K57: 0 | M57: 0
B58: 154 | C58: 17444522707 | D58: LOSAINE LOPES DE OLIVEIRA | E58: Telemassas | G58: 46080 | I58: 0 | K58: 0 | M58: 0
B59: 63 | C59: 8932910723 | D59: LOURDINHA COELHO BERUDIO | E59: Telemassas | I59: 0 | K59: 0 | M59: 0
B60: 135 | C60: 9823424705 | D60: LUCIENE MENEGUETTI TEDESCO | E60: Telemassas | I60: 0 | K60: 0 | M60: 0
B61: 5 | C61: 14676408757 | D61: LUIZ ZANAO | E61: Yup | I61: 0 | K61: 0 | M61: 0
B62: 147 | C62: 18605506733 | D62: MARCOS EDUARDO DE SOUZA GOMES | E62: Telemassas | I62: 0 | K62: 0 | M62: 0
B63: 99 | C63: 11968033742 | D63: MARIA APARECIDA DANIEL | E63: Telemassas | H63: 01 a 28 | I63: 5 | K63: 0 | M63: 0
B64: 54 | C64: 540533742 | D64: MARIA APARECIDA LOPES | E64: Telemassas | I64: 0 | K64: 0 | M64: 0
B65: 42 | C65: 8126990767 | D65: MARIA DA PENHA SILVA VIANA | E65: Telemassas | I65: 0 | K65: 0 | M65: 0
B66: 43 | C66: 6143838623 | D66: MARIA ESTER DA ROCHA GARIBALDI | E66: Telemassas | I66: 0 | K66: 0 | M66: 0
B67: 124 | C67: 11779661746 | D67: MARIA JOSE DE SOUZA BRAGA SCHROEDER | E67: Telemassas | G67: 46078 | H67: 26 a28 | I67: 3 | K67: 0 | L67: 09 a 24 | M67: 10
B68: 148 | C68: 19168959729 | D68: NATAN ALVES DE OLIVEIRA | E68: Telemassas | I68: 0 | K68: 0 | M68: 0
B69: 157 | C69: 18019744703 | D69: RUAN MOREIRA MARTINS | E69: Telemassas | I69: 0 | K69: 0 | M69: 0
B70: 48 | C70: 9825505702 | D70: SANDRA DANIEL | E70: Telemassas | I70: 0 | K70: 0 | M70: 0
B71: 1 | C71: 20832236756 | D71: SARIDIA RAMOS BROEDEL | E71: Yup | I71: 0 | K71: 0 | M71: 0
B72: 159 | C72: 11347893784 | D72: THAIS FRANCELI LOPES DE SOUZA GOMES | E72: Telemassas | F72: 46076 | I72: 0 | K72: 0 | M72: 0
B73: 144 | C73: 9630506726 | D73: VANUZA DE OLIVEIRA GOMES | E73: Telemassas | I73: 0 | K73: 0 | M73: 0
B74: 126 | C74: 11765503736 | D74: ZILNEIDE DA CONCEICAO | E74: Telemassas | I74: 0 | K74: 0 | M74: 0
B75: 52 | C75: 9922359790 | D75: ZIRLENE APARECIDA DE OLIVEIRA TOMAS DA SILVA | E75: Telemassas | I75: 0 | K75: 0 | M75: 0
D76: =COUNTA(D41:D75) -> 35 | F76: =COUNTA(F41:F75) -> 1 | G76: =COUNTA(G41:G75) -> 7 | H76: =COUNTA(H41:H75) -> 2 | I76: =SUM(I41:I75) -> 8 | J76: =COUNTA(J41:J75) -> 0 | K76: =SUM(K41:K75) -> 0 | L76: =COUNTA(L41:L75) -> 2 | M76: =SUM(M41:M75) -> 21
B78: Funcionário | C78: CPF | D78: Nome do Funcionário | E78: Departamento | F78: Admissão | G78: Demissão | H78: Afastamento | I78: Dias | J78: Faltas | K78: Dias | L78: Férias | M78: Dias | O78: Início Colab. | P78: =S42 -> 28 | R78: Admissão | S78: =F108 -> 1 | U78: Faltas | V78: =K108 -> 0 | Z78: Março 2026 | AF78: D. Produtivo | AG78: =(V84-V79-V78-S81) -> 567
B79: 115 | C79: 17622871702 | D79: ANAILSON DA CONCEICAO RICARTE | E79: Telemassas | I79: 0 | K79: 0 | M79: 0 | R79: Demissão | S79: =G108 -> 2 | U79: Férias | V79: =M108 -> 0 | X79: Dom | Y79: Seg | Z79: Ter | AA79: Qua | AB79: Qui | AC79: Sex | AD79: Sáb | AF79: D. N. Produt. | AG79: =V84-AG78 -> 38
B80: 160 | C80: 14212723778 | D80: BRENO BERUDIO BARBOZA | E80: Telemassas | F80: 46092 | H80: 1 a 6 | I80: 7 | K80: 0 | M80: 0 | R80: Fim Colab | S80: =P78+S78-S79 -> 27 | U80: Colaboradores | V80: =L108 -> 0 | X80: 46082 | Y80: 46083 | Z80: 46084 | AA80: 46085 | AB80: 46086 | AC80: 46087 | AD80: 46088 | AF80: Horas Program. | AG80: =(S80*8.8)*S83 -> 5227.2
B81: 130 | C81: 16044643727 | D81: CASSIA COELHO RAMOS | E81: Telemassas | I81: 0 | K81: 0 | M81: 0 | R81: Afastam. | S81: =I108 -> 38 | X81: 46089 | Y81: 46090 | Z81: 46091 | AA81: 46092 | AB81: 46093 | AC81: 46094 | AD81: 46095 | AF81: H. N. Produtiva | AG81: =AG79*8.8 -> 334.4
B82: 158 | C82: 18596219706 | D82: CASSIO PEREIRA TOMAS | E82: Telemassas | G82: 46112 | H82: 31 | I82: 1 | K82: 0 | M82: 0 | X82: 46096 | Y82: 46097 | Z82: 46098 | AA82: 46099 | AB82: 46100 | AC82: 46101 | AD82: 46102 | AF82: Efetivo Pessoal | AG82: =(AG80-AG81)/(8.8*S83) -> 25.272727
B83: 4 | C83: 12576147704 | D83: DENIZE MOREIRA COELHO MARTINS | E83: Yup | I83: 0 | K83: 0 | M83: 0 | R83: Dias Úteis | S83: 22 | U83: Efet. Méd. | V83: =(P78+S80)/2 -> 27.5 | X83: 46103 | Y83: 46104 | Z83: 46105 | AA83: 46106 | AB83: 46107 | AC83: 46108 | AD83: 46109
B84: 35 | C84: 9621821762 | D84: EDINEIA MARIA LOPES DA SILVA | E84: Telemassas | I84: 0 | K84: 0 | M84: 0 | R84: Não Úteis | S84: 9 | U84: D. Program. | V84: =S83*V83 -> 605 | X84: 46110 | Y84: 46111 | Z84: 46112
B85: 3 | C85: 86749072704 | D85: EDSON JOSE DE SOUZA | E85: Yup | I85: 0 | K85: 0 | M85: 0
B86: 36 | C86: 7452452771 | D86: ERMINDA MARIA LOPES FACCINI | E86: Telemassas | I86: 0 | K86: 0 | M86: 0
B87: 6 | C87: 7728013637 | D87: GIORDANO BRUNO GARIBALDI | E87: Yup | I87: 0 | K87: 0 | M87: 0
B88: 109 | C88: 17911909792 | D88: HUGO BERUDIO AMORIM | E88: Telemassas | I88: 0 | K88: 0 | M88: 0
B89: 100 | C89: 21963396790 | D89: JOSE GUILHERME TEIXEIRA BRAGA | E89: Telemassas | I89: 0 | K89: 0 | M89: 0
B90: 153 | C90: 19379132794 | D90: LORENA BARBOSA BOEQUE | E90: Telemassas | I90: 0 | K90: 0 | M90: 0
B91: 123 | C91: 17622438731 | D91: LORENA DE OLIVEIRA LUZORIO | E91: Telemassas | G91: 46085 | H91: 05 a 31 | I91: 20 | K91: 0 | M91: 0
B92: 63 | C92: 8932910723 | D92: LOURDINHA COELHO BERUDIO | E92: Telemassas | I92: 0 | K92: 0 | M92: 0
B93: 135 | C93: 9823424705 | D93: LUCIENE MENEGUETTI TEDESCO | E93: Telemassas | I93: 0 | K93: 0 | M93: 0
B94: 5 | C94: 14676408757 | D94: LUIZ ZANAO | E94: Yup | H94: 7 a 21 | I94: 10 | K94: 0 | M94: 0
B95: 147 | C95: 18605506733 | D95: MARCOS EDUARDO DE SOUZA GOMES | E95: Telemassas | I95: 0 | K95: 0 | M95: 0
B96: 99 | C96: 11968033742 | D96: MARIA APARECIDA DANIEL | E96: Telemassas | I96: 0 | K96: 0 | M96: 0
B97: 54 | C97: 540533742 | D97: MARIA APARECIDA LOPES | E97: Telemassas | I97: 0 | K97: 0 | M97: 0
B98: 42 | C98: 8126990767 | D98: MARIA DA PENHA SILVA VIANA | E98: Telemassas | I98: 0 | K98: 0 | M98: 0
B99: 43 | C99: 6143838623 | D99: MARIA ESTER DA ROCHA GARIBALDI | E99: Telemassas | I99: 0 | K99: 0 | M99: 0
B100: 148 | C100: 19168959729 | D100: NATAN ALVES DE OLIVEIRA | E100: Telemassas | I100: 0 | K100: 0 | M100: 0
B101: 157 | C101: 18019744703 | D101: RUAN MOREIRA MARTINS | E101: Telemassas | I101: 0 | K101: 0 | M101: 0
B102: 48 | C102: 9825505702 | D102: SANDRA DANIEL | E102: Telemassas | I102: 0 | K102: 0 | M102: 0
B103: 1 | C103: 20832236756 | D103: SARIDIA RAMOS BROEDEL | E103: Yup | I103: 0 | K103: 0 | M103: 0
B104: 159 | C104: 11347893784 | D104: THAIS FRANCELI LOPES DE SOUZA GOMES | E104: Telemassas | I104: 0 | K104: 0 | M104: 0
...

Sheet IND_Fopag
B2: COLABORADOR | C2: Salários | D2: Prolabore | E2: Dist. Lucro | F2: Anuênio | G2: HE+ DSR | H2: Assiduidade | I2: C. Básica | J2: Seguro | K2: Pl. Odonto | L2: Sub. Total | M2: INSS | N2: RAT | O2: Terceiros | P2: FGTS | Q2: T. Encargos | R2: Férias | S2: 1/3 Férias | T2: FGTS Férias | U2: 13º Sal | V2: FGTS 13º Sal | W2: Aviso Prévio | X2: FGTS Av. | Y2: Multa FGTS | Z2: Patronal | AA2: T. Provisão | AB2: Total | AC2: Custo Total | AD2: 46023
B3: Amanda Beatriz Alves | C3: 2100 | F3: 0 | H3: 600 | I3: 103 | J3: 8.5 | K3: 13 | L3: =SUM(C3:K3) -> 2824.5 | M3: =(C3+F3+G3)*20% -> 420 | N3: =(C3+F3+G3)*1.5% -> 31.5 | O3: =(C3+F3+G3)*5.8% -> 121.8 | P3: =(C3+F3+G3)*8% -> 168 | Q3: =SUM(M3:P3) -> 741.3 | R3: =(C3+F3+G3)/12 -> 175 | S3: =R3/3 -> 58.333333 | T3: =(R3+S3)*8% -> 18.666667 | U3: =(C3+F3+G3)/12 -> 175 | V3: =U3*8% -> 14 | W3: =(C3+F3+G3)/12 -> 175 | X3: =W3*8% -> 14 | Y3: =(P3+T3+V3+X3)*50% -> 107.33333 | Z3: =(R3+S3+U3+W3)*27.3% -> 159.25 | AA3: =SUM(R3:Z3) -> 896.58333 | AB3: =L3+Q3+AA3 -> 4462.3833 | AC3: Salário | AD3: =C40 -> 78662
B4: Anailson da Conceição Ricarte | C4: 2100 | F4: 250 | H4: 600 | I4: 103 | J4: 8.5 | K4: 13 | L4: =SUM(C4:K4) -> 3074.5 | M4: =(C4+F4+G4)*20% -> 470 | N4: =(C4+F4+G4)*1.5% -> 35.25 | O4: =(C4+F4+G4)*5.8% -> 136.3 | P4: =(C4+F4+G4)*8% -> 188 | Q4: =SUM(M4:P4) -> 829.55 | R4: =(C4+F4+G4)/12 -> 195.83333 | S4: =R4/3 -> 65.277778 | T4: =(R4+S4)*8% -> 20.888889 | U4: =(C4+F4+G4)/12 -> 195.83333 | V4: =U4*8% -> 15.666667 | W4: =(C4+F4+G4)/12 -> 195.83333 | X4: =W4*8% -> 15.666667 | Y4: =(P4+T4+V4+X4)*50% -> 120.11111 | Z4: =(R4+S4+U4+W4)*27.3% -> 178.20833 | AA4: =SUM(R4:Z4) -> 1003.3194 | AB4: =L4+Q4+AA4 -> 4907.3694 | AC4: Anuênio | AD4: =F40 -> 6750
B5: Cassia Coelho Ramos | C5: 2100 | F5: 250 | H5: 600 | I5: 103 | J5: 8.5 | K5: 13 | L5: =SUM(C5:K5) -> 3074.5 | M5: =(C5+F5+G5)*20% -> 470 | N5: =(C5+F5+G5)*1.5% -> 35.25 | O5: =(C5+F5+G5)*5.8% -> 136.3 | P5: =(C5+F5+G5)*8% -> 188 | Q5: =SUM(M5:P5) -> 829.55 | R5: =(C5+F5+G5)/12 -> 195.83333 | S5: =R5/3 -> 65.277778 | T5: =(R5+S5)*8% -> 20.888889 | U5: =(C5+F5+G5)/12 -> 195.83333 | V5: =U5*8% -> 15.666667 | W5: =(C5+F5+G5)/12 -> 195.83333 | X5: =W5*8% -> 15.666667 | Y5: =(P5+T5+V5+X5)*50% -> 120.11111 | Z5: =(R5+S5+U5+W5)*27.3% -> 178.20833 | AA5: =SUM(R5:Z5) -> 1003.3194 | AB5: =L5+Q5+AA5 -> 4907.3694 | AC5: H. Extra | AD5: 0
B6: Cassio Pereira Tomas | C6: 2100 | H6: 0 | I6: 103 | J6: 8.5 | L6: =SUM(C6:K6) -> 2211.5 | M6: =(C6+F6+G6)*20% -> 420 | N6: =(C6+F6+G6)*1.5% -> 31.5 | O6: =(C6+F6+G6)*5.8% -> 121.8 | P6: =(C6+F6+G6)*8% -> 168 | Q6: =SUM(M6:P6) -> 741.3 | R6: =(C6+F6+G6)/12 -> 175 | S6: =R6/3 -> 58.333333 | T6: =(R6+S6)*8% -> 18.666667 | U6: =(C6+F6+G6)/12 -> 175 | V6: =U6*8% -> 14 | W6: =(C6+F6+G6)/12 -> 175 | X6: =W6*8% -> 14 | Y6: =(P6+T6+V6+X6)*50% -> 107.33333 | Z6: =(R6+S6+U6+W6)*27.3% -> 159.25 | AA6: =SUM(R6:Z6) -> 896.58333 | AB6: =L6+Q6+AA6 -> 3849.3833 | AC6: Prolabore | AD6: =D40 -> 3242
B7: Daysa Gregorio Venancio | C7: 2100 | F7: 250 | H7: 600 | I7: 103 | J7: 8.5 | K7: 13 | L7: =SUM(C7:K7) -> 3074.5 | M7: =(C7+F7+G7)*20% -> 470 | N7: =(C7+F7+G7)*1.5% -> 35.25 | O7: =(C7+F7+G7)*5.8% -> 136.3 | P7: =(C7+F7+G7)*8% -> 188 | Q7: =SUM(M7:P7) -> 829.55 | R7: =(C7+F7+G7)/12 -> 195.83333 | S7: =R7/3 -> 65.277778 | T7: =(R7+S7)*8% -> 20.888889 | U7: =(C7+F7+G7)/12 -> 195.83333 | V7: =U7*8% -> 15.666667 | W7: =(C7+F7+G7)/12 -> 195.83333 | X7: =W7*8% -> 15.666667 | Y7: =(P7+T7+V7+X7)*50% -> 120.11111 | Z7: =(R7+S7+U7+W7)*27.3% -> 178.20833 | AA7: =SUM(R7:Z7) -> 1003.3194 | AB7: =L7+Q7+AA7 -> 4907.3694 | AC7: Dist. Lucro | AD7: =E40 -> 10844
B8: Edineia Maria Lopes da Silva | C8: 2100 | F8: 250 | H8: 600 | I8: 103 | J8: 8.5 | K8: 13 | L8: =SUM(C8:K8) -> 3074.5 | M8: =(C8+F8+G8)*20% -> 470 | N8: =(C8+F8+G8)*1.5% -> 35.25 | O8: =(C8+F8+G8)*5.8% -> 136.3 | P8: =(C8+F8+G8)*8% -> 188 | Q8: =SUM(M8:P8) -> 829.55 | R8: =(C8+F8+G8)/12 -> 195.83333 | S8: =R8/3 -> 65.277778 | T8: =(R8+S8)*8% -> 20.888889 | U8: =(C8+F8+G8)/12 -> 195.83333 | V8: =U8*8% -> 15.666667 | W8: =(C8+F8+G8)/12 -> 195.83333 | X8: =W8*8% -> 15.666667 | Y8: =(P8+T8+V8+X8)*50% -> 120.11111 | Z8: =(R8+S8+U8+W8)*27.3% -> 178.20833 | AA8: =SUM(R8:Z8) -> 1003.3194 | AB8: =L8+Q8+AA8 -> 4907.3694 | AC8: Benefício | AD8: =SUM(H40:K40) -> 20119.5
B9: Erminda Maria Lopes | C9: 2100 | F9: 250 | H9: 600 | I9: 103 | J9: 8.5 | K9: 13 | L9: =SUM(C9:K9) -> 3074.5 | M9: =(C9+F9+G9)*20% -> 470 | N9: =(C9+F9+G9)*1.5% -> 35.25 | O9: =(C9+F9+G9)*5.8% -> 136.3 | P9: =(C9+F9+G9)*8% -> 188 | Q9: =SUM(M9:P9) -> 829.55 | R9: =(C9+F9+G9)/12 -> 195.83333 | S9: =R9/3 -> 65.277778 | T9: =(R9+S9)*8% -> 20.888889 | U9: =(C9+F9+G9)/12 -> 195.83333 | V9: =U9*8% -> 15.666667 | W9: =(C9+F9+G9)/12 -> 195.83333 | X9: =W9*8% -> 15.666667 | Y9: =(P9+T9+V9+X9)*50% -> 120.11111 | Z9: =(R9+S9+U9+W9)*27.3% -> 178.20833 | AA9: =SUM(R9:Z9) -> 1003.3194 | AB9: =L9+Q9+AA9 -> 4907.3694 | AC9: Patronal | AD9: =SUM(M40:O40) -> 22445.596
B10: Felipe Sanção | C10: 2100 | F10: 0 | H10: 600 | I10: 103 | J10: 8.5 | K10: 13 | L10: =SUM(C10:K10) -> 2824.5 | M10: =(C10+F10+G10)*20% -> 420 | N10: =(C10+F10+G10)*1.5% -> 31.5 | O10: =(C10+F10+G10)*5.8% -> 121.8 | P10: =(C10+F10+G10)*8% -> 168 | Q10: =SUM(M10:P10) -> 741.3 | R10: =(C10+F10+G10)/12 -> 175 | S10: =R10/3 -> 58.333333 | T10: =(R10+S10)*8% -> 18.666667 | U10: =(C10+F10+G10)/12 -> 175 | V10: =U10*8% -> 14 | W10: =(C10+F10+G10)/12 -> 175 | X10: =W10*8% -> 14 | Y10: =(P10+T10+V10+X10)*50% -> 107.33333 | Z10: =(R10+S10+U10+W10)*27.3% -> 159.25 | AA10: =SUM(R10:Z10) -> 896.58333 | AB10: =L10+Q10+AA10 -> 4462.3833 | AC10: FGTS | AD10: =P40 -> 6472.96
B11: Hugo Berudio Amorim | C11: 2100 | F11: 250 | H11: 600 | I11: 103 | J11: 8.5 | K11: 13 | L11: =SUM(C11:K11) -> 3074.5 | M11: =(C11+F11+G11)*20% -> 470 | N11: =(C11+F11+G11)*1.5% -> 35.25 | O11: =(C11+F11+G11)*5.8% -> 136.3 | P11: =(C11+F11+G11)*8% -> 188 | Q11: =SUM(M11:P11) -> 829.55 | R11: =(C11+F11+G11)/12 -> 195.83333 | S11: =R11/3 -> 65.277778 | T11: =(R11+S11)*8% -> 20.888889 | U11: =(C11+F11+G11)/12 -> 195.83333 | V11: =U11*8% -> 15.666667 | W11: =(C11+F11+G11)/12 -> 195.83333 | X11: =W11*8% -> 15.666667 | Y11: =(P11+T11+V11+X11)*50% -> 120.11111 | Z11: =(R11+S11+U11+W11)*27.3% -> 178.20833 | AA11: =SUM(R11:Z11) -> 1003.3194 | AB11: =L11+Q11+AA11 -> 4907.3694 | AC11: Provisão | AD11: =SUM(R40:Z40) -> 34544.929
B12: Jamaica Pena Alipio | C12: 2100 | H12: 600 | I12: 103 | J12: 8.5 | L12: =SUM(C12:K12) -> 2811.5 | M12: =(C12+F12+G12)*20% -> 420 | N12: =(C12+F12+G12)*1.5% -> 31.5 | O12: =(C12+F12+G12)*5.8% -> 121.8 | P12: =(C12+F12+G12)*8% -> 168 | Q12: =SUM(M12:P12) -> 741.3 | R12: =(C12+F12+G12)/12 -> 175 | S12: =R12/3 -> 58.333333 | T12: =(R12+S12)*8% -> 18.666667 | U12: =(C12+F12+G12)/12 -> 175 | V12: =U12*8% -> 14 | W12: =(C12+F12+G12)/12 -> 175 | X12: =W12*8% -> 14 | Y12: =(P12+T12+V12+X12)*50% -> 107.33333 | Z12: =(R12+S12+U12+W12)*27.3% -> 159.25 | AA12: =SUM(R12:Z12) -> 896.58333 | AB12: =L12+Q12+AA12 -> 4449.3833 | AC12: Total | AD12: =SUM(AD3:AD11) -> 183080.98
B13: José Guilherme Teixeira Braga | C13: 2100 | F13: 250 | H13: 600 | I13: 103 | J13: 8.5 | K13: 13 | L13: =SUM(C13:K13) -> 3074.5 | M13: =(C13+F13+G13)*20% -> 470 | N13: =(C13+F13+G13)*1.5% -> 35.25 | O13: =(C13+F13+G13)*5.8% -> 136.3 | P13: =(C13+F13+G13)*8% -> 188 | Q13: =SUM(M13:P13) -> 829.55 | R13: =(C13+F13+G13)/12 -> 195.83333 | S13: =R13/3 -> 65.277778 | T13: =(R13+S13)*8% -> 20.888889 | U13: =(C13+F13+G13)/12 -> 195.83333 | V13: =U13*8% -> 15.666667 | W13: =(C13+F13+G13)/12 -> 195.83333 | X13: =W13*8% -> 15.666667 | Y13: =(P13+T13+V13+X13)*50% -> 120.11111 | Z13: =(R13+S13+U13+W13)*27.3% -> 178.20833 | AA13: =SUM(R13:Z13) -> 1003.3194 | AB13: =L13+Q13+AA13 -> 4907.3694
B14: Liliane Aparecida Candida da Silva | C14: 2100 | F14: 250 | H14: 0 | I14: 103 | J14: 8.5 | K14: 13 | L14: =SUM(C14:K14) -> 2474.5 | M14: =(C14+F14+G14)*20% -> 470 | N14: =(C14+F14+G14)*1.5% -> 35.25 | O14: =(C14+F14+G14)*5.8% -> 136.3 | P14: =(C14+F14+G14)*8% -> 188 | Q14: =SUM(M14:P14) -> 829.55 | R14: =(C14+F14+G14)/12 -> 195.83333 | S14: =R14/3 -> 65.277778 | T14: =(R14+S14)*8% -> 20.888889 | U14: =(C14+F14+G14)/12 -> 195.83333 | V14: =U14*8% -> 15.666667 | W14: =(C14+F14+G14)/12 -> 195.83333 | X14: =W14*8% -> 15.666667 | Y14: =(P14+T14+V14+X14)*50% -> 120.11111 | Z14: =(R14+S14+U14+W14)*27.3% -> 178.20833 | AA14: =SUM(R14:Z14) -> 1003.3194 | AB14: =L14+Q14+AA14 -> 4307.3694
B15: Lorena Barbosa Boeque | C15: 2100 | H15: 0 | I15: 103 | J15: 8.5 | K15: 13 | L15: =SUM(C15:K15) -> 2224.5 | M15: =(C15+F15+G15)*20% -> 420 | N15: =(C15+F15+G15)*1.5% -> 31.5 | O15: =(C15+F15+G15)*5.8% -> 121.8 | P15: =(C15+F15+G15)*8% -> 168 | Q15: =SUM(M15:P15) -> 741.3 | R15: =(C15+F15+G15)/12 -> 175 | S15: =R15/3 -> 58.333333 | T15: =(R15+S15)*8% -> 18.666667 | U15: =(C15+F15+G15)/12 -> 175 | V15: =U15*8% -> 14 | W15: =(C15+F15+G15)/12 -> 175 | X15: =W15*8% -> 14 | Y15: =(P15+T15+V15+X15)*50% -> 107.33333 | Z15: =(R15+S15+U15+W15)*27.3% -> 159.25 | AA15: =SUM(R15:Z15) -> 896.58333 | AB15: =L15+Q15+AA15 -> 3862.3833
B16: Lorena de Oliveira Luzorio | C16: 2100 | F16: 250 | H16: 600 | I16: 103 | J16: 8.5 | K16: 13 | L16: =SUM(C16:K16) -> 3074.5 | M16: =(C16+F16+G16)*20% -> 470 | N16: =(C16+F16+G16)*1.5% -> 35.25 | O16: =(C16+F16+G16)*5.8% -> 136.3 | P16: =(C16+F16+G16)*8% -> 188 | Q16: =SUM(M16:P16) -> 829.55 | R16: =(C16+F16+G16)/12 -> 195.83333 | S16: =R16/3 -> 65.277778 | T16: =(R16+S16)*8% -> 20.888889 | U16: =(C16+F16+G16)/12 -> 195.83333 | V16: =U16*8% -> 15.666667 | W16: =(C16+F16+G16)/12 -> 195.83333 | X16: =W16*8% -> 15.666667 | Y16: =(P16+T16+V16+X16)*50% -> 120.11111 | Z16: =(R16+S16+U16+W16)*27.3% -> 178.20833 | AA16: =SUM(R16:Z16) -> 1003.3194 | AB16: =L16+Q16+AA16 -> 4907.3694
B17: Losaine Lopes | C17: 2100 | H17: 0 | I17: 103 | J17: 8.5 | L17: =SUM(C17:K17) -> 2211.5 | M17: =(C17+F17+G17)*20% -> 420 | N17: =(C17+F17+G17)*1.5% -> 31.5 | O17: =(C17+F17+G17)*5.8% -> 121.8 | P17: =(C17+F17+G17)*8% -> 168 | Q17: =SUM(M17:P17) -> 741.3 | R17: =(C17+F17+G17)/12 -> 175 | S17: =R17/3 -> 58.333333 | T17: =(R17+S17)*8% -> 18.666667 | U17: =(C17+F17+G17)/12 -> 175 | V17: =U17*8% -> 14 | W17: =(C17+F17+G17)/12 -> 175 | X17: =W17*8% -> 14 | Y17: =(P17+T17+V17+X17)*50% -> 107.33333 | Z17: =(R17+S17+U17+W17)*27.3% -> 159.25 | AA17: =SUM(R17:Z17) -> 896.58333 | AB17: =L17+Q17+AA17 -> 3849.3833
B18: Lourdinha Coelho Berudio | C18: 2100 | F18: 250 | H18: 600 | I18: 103 | J18: 8.5 | K18: 13 | L18: =SUM(C18:K18) -> 3074.5 | M18: =(C18+F18+G18)*20% -> 470 | N18: =(C18+F18+G18)*1.5% -> 35.25 | O18: =(C18+F18+G18)*5.8% -> 136.3 | P18: =(C18+F18+G18)*8% -> 188 | Q18: =SUM(M18:P18) -> 829.55 | R18: =(C18+F18+G18)/12 -> 195.83333 | S18: =R18/3 -> 65.277778 | T18: =(R18+S18)*8% -> 20.888889 | U18: =(C18+F18+G18)/12 -> 195.83333 | V18: =U18*8% -> 15.666667 | W18: =(C18+F18+G18)/12 -> 195.83333 | X18: =W18*8% -> 15.666667 | Y18: =(P18+T18+V18+X18)*50% -> 120.11111 | Z18: =(R18+S18+U18+W18)*27.3% -> 178.20833 | AA18: =SUM(R18:Z18) -> 1003.3194 | AB18: =L18+Q18+AA18 -> 4907.3694
B19: Luciene Meneguetti Tedesco | C19: 2100 | F19: 250 | H19: 600 | I19: 103 | J19: 8.5 | K19: 13 | L19: =SUM(C19:K19) -> 3074.5 | M19: =(C19+F19+G19)*20% -> 470 | N19: =(C19+F19+G19)*1.5% -> 35.25 | O19: =(C19+F19+G19)*5.8% -> 136.3 | P19: =(C19+F19+G19)*8% -> 188 | Q19: =SUM(M19:P19) -> 829.55 | R19: =(C19+F19+G19)/12 -> 195.83333 | S19: =R19/3 -> 65.277778 | T19: =(R19+S19)*8% -> 20.888889 | U19: =(C19+F19+G19)/12 -> 195.83333 | V19: =U19*8% -> 15.666667 | W19: =(C19+F19+G19)/12 -> 195.83333 | X19: =W19*8% -> 15.666667 | Y19: =(P19+T19+V19+X19)*50% -> 120.11111 | Z19: =(R19+S19+U19+W19)*27.3% -> 178.20833 | AA19: =SUM(R19:Z19) -> 1003.3194 | AB19: =L19+Q19+AA19 -> 4907.3694
B20: Marcos Eduardo de Souza Gomes | C20: 2100 | F20: 0 | H20: 600 | I20: 103 | J20: 8.5 | K20: 13 | L20: =SUM(C20:K20) -> 2824.5 | M20: =(C20+F20+G20)*20% -> 420 | N20: =(C20+F20+G20)*1.5% -> 31.5 | O20: =(C20+F20+G20)*5.8% -> 121.8 | P20: =(C20+F20+G20)*8% -> 168 | Q20: =SUM(M20:P20) -> 741.3 | R20: =(C20+F20+G20)/12 -> 175 | S20: =R20/3 -> 58.333333 | T20: =(R20+S20)*8% -> 18.666667 | U20: =(C20+F20+G20)/12 -> 175 | V20: =U20*8% -> 14 | W20: =(C20+F20+G20)/12 -> 175 | X20: =W20*8% -> 14 | Y20: =(P20+T20+V20+X20)*50% -> 107.33333 | Z20: =(R20+S20+U20+W20)*27.3% -> 159.25 | AA20: =SUM(R20:Z20) -> 896.58333 | AB20: =L20+Q20+AA20 -> 4462.3833
B21: Maria Aparecida Daniel | C21: 1120 | H21: 0 | I21: 103 | J21: 8.5 | K21: 13 | L21: =SUM(C21:K21) -> 1244.5 | M21: =(C21+F21+G21)*20% -> 224 | N21: =(C21+F21+G21)*1.5% -> 16.8 | O21: =(C21+F21+G21)*5.8% -> 64.96 | P21: =(C21+F21+G21)*8% -> 89.6 | Q21: =SUM(M21:P21) -> 395.36 | R21: =(C21+F21+G21)/12 -> 93.333333 | S21: =R21/3 -> 31.111111 | T21: =(R21+S21)*8% -> 9.9555556 | U21: =(C21+F21+G21)/12 -> 93.333333 | V21: =U21*8% -> 7.4666667 | W21: =(C21+F21+G21)/12 -> 93.333333 | X21: =W21*8% -> 7.4666667 | Y21: =(P21+T21+V21+X21)*50% -> 57.244444 | Z21: =(R21+S21+U21+W21)*27.3% -> 84.933333 | AA21: =SUM(R21:Z21) -> 478.17778 | AB21: =L21+Q21+AA21 -> 2118.0378
B22: Maria Aparecida Lopes | C22: 2100 | F22: 250 | H22: 600 | I22: 103 | J22: 8.5 | K22: 13 | L22: =SUM(C22:K22) -> 3074.5 | M22: =(C22+F22+G22)*20% -> 470 | N22: =(C22+F22+G22)*1.5% -> 35.25 | O22: =(C22+F22+G22)*5.8% -> 136.3 | P22: =(C22+F22+G22)*8% -> 188 | Q22: =SUM(M22:P22) -> 829.55 | R22: =(C22+F22+G22)/12 -> 195.83333 | S22: =R22/3 -> 65.277778 | T22: =(R22+S22)*8% -> 20.888889 | U22: =(C22+F22+G22)/12 -> 195.83333 | V22: =U22*8% -> 15.666667 | W22: =(C22+F22+G22)/12 -> 195.83333 | X22: =W22*8% -> 15.666667 | Y22: =(P22+T22+V22+X22)*50% -> 120.11111 | Z22: =(R22+S22+U22+W22)*27.3% -> 178.20833 | AA22: =SUM(R22:Z22) -> 1003.3194 | AB22: =L22+Q22+AA22 -> 4907.3694
B23: Maria da Penha Silva Viana | C23: 2100 | F23: 250 | H23: 600 | I23: 103 | J23: 8.5 | K23: 13 | L23: =SUM(C23:K23) -> 3074.5 | M23: =(C23+F23+G23)*20% -> 470 | N23: =(C23+F23+G23)*1.5% -> 35.25 | O23: =(C23+F23+G23)*5.8% -> 136.3 | P23: =(C23+F23+G23)*8% -> 188 | Q23: =SUM(M23:P23) -> 829.55 | R23: =(C23+F23+G23)/12 -> 195.83333 | S23: =R23/3 -> 65.277778 | T23: =(R23+S23)*8% -> 20.888889 | U23: =(C23+F23+G23)/12 -> 195.83333 | V23: =U23*8% -> 15.666667 | W23: =(C23+F23+G23)/12 -> 195.83333 | X23: =W23*8% -> 15.666667 | Y23: =(P23+T23+V23+X23)*50% -> 120.11111 | Z23: =(R23+S23+U23+W23)*27.3% -> 178.20833 | AA23: =SUM(R23:Z23) -> 1003.3194 | AB23: =L23+Q23+AA23 -> 4907.3694
B24: Maria Ester da Rocha Garibaldi | C24: 4200 | F24: 250 | H24: 600 | I24: 103 | J24: 8.5 | K24: 13 | L24: =SUM(C24:K24) -> 5174.5 | M24: =(C24+F24+G24)*20% -> 890 | N24: =(C24+F24+G24)*1.5% -> 66.75 | O24: =(C24+F24+G24)*5.8% -> 258.1 | P24: =(C24+F24+G24)*8% -> 356 | Q24: =SUM(M24:P24) -> 1570.85 | R24: =(C24+F24+G24)/12 -> 370.83333 | S24: =R24/3 -> 123.61111 | T24: =(R24+S24)*8% -> 39.555556 | U24: =(C24+F24+G24)/12 -> 370.83333 | V24: =U24*8% -> 29.666667 | W24: =(C24+F24+G24)/12 -> 370.83333 | X24: =W24*8% -> 29.666667 | Y24: =(P24+T24+V24+X24)*50% -> 227.44444 | Z24: =(R24+S24+U24+W24)*27.3% -> 337.45833 | AA24: =SUM(R24:Z24) -> 1899.9028 | AB24: =L24+Q24+AA24 -> 8645.2528
B25: Maria Jose de Souza | C25: 2100 | F25: 250 | H25: 600 | I25: 103 | J25: 8.5 | K25: 13 | L25: =SUM(C25:K25) -> 3074.5 | M25: =(C25+F25+G25)*20% -> 470 | N25: =(C25+F25+G25)*1.5% -> 35.25 | O25: =(C25+F25+G25)*5.8% -> 136.3 | P25: =(C25+F25+G25)*8% -> 188 | Q25: =SUM(M25:P25) -> 829.55 | R25: =(C25+F25+G25)/12 -> 195.83333 | S25: =R25/3 -> 65.277778 | T25: =(R25+S25)*8% -> 20.888889 | U25: =(C25+F25+G25)/12 -> 195.83333 | V25: =U25*8% -> 15.666667 | W25: =(C25+F25+G25)/12 -> 195.83333 | X25: =W25*8% -> 15.666667 | Y25: =(P25+T25+V25+X25)*50% -> 120.11111 | Z25: =(R25+S25+U25+W25)*27.3% -> 178.20833 | AA25: =SUM(R25:Z25) -> 1003.3194 | AB25: =L25+Q25+AA25 -> 4907.3694
B26: Natan Alves | C26: 2100 | F26: 0 | H26: 600 | I26: 103 | J26: 8.5 | K26: 13 | L26: =SUM(C26:K26) -> 2824.5 | M26: =(C26+F26+G26)*20% -> 420 | N26: =(C26+F26+G26)*1.5% -> 31.5 | O26: =(C26+F26+G26)*5.8% -> 121.8 | P26: =(C26+F26+G26)*8% -> 168 | Q26: =SUM(M26:P26) -> 741.3 | R26: =(C26+F26+G26)/12 -> 175 | S26: =R26/3 -> 58.333333 | T26: =(R26+S26)*8% -> 18.666667 | U26: =(C26+F26+G26)/12 -> 175 | V26: =U26*8% -> 14 | W26: =(C26+F26+G26)/12 -> 175 | X26: =W26*8% -> 14 | Y26: =(P26+T26+V26+X26)*50% -> 107.33333 | Z26: =(R26+S26+U26+W26)*27.3% -> 159.25 | AA26: =SUM(R26:Z26) -> 896.58333 | AB26: =L26+Q26+AA26 -> 4462.3833
B27: Ruan Moreira Martins | C27: 2100 | H27: 600 | I27: 103 | J27: 8.5 | L27: =SUM(C27:K27) -> 2811.5 | M27: =(C27+F27+G27)*20% -> 420 | N27: =(C27+F27+G27)*1.5% -> 31.5 | O27: =(C27+F27+G27)*5.8% -> 121.8 | P27: =(C27+F27+G27)*8% -> 168 | Q27: =SUM(M27:P27) -> 741.3 | R27: =(C27+F27+G27)/12 -> 175 | S27: =R27/3 -> 58.333333 | T27: =(R27+S27)*8% -> 18.666667 | U27: =(C27+F27+G27)/12 -> 175 | V27: =U27*8% -> 14 | W27: =(C27+F27+G27)/12 -> 175 | X27: =W27*8% -> 14 | Y27: =(P27+T27+V27+X27)*50% -> 107.33333 | Z27: =(R27+S27+U27+W27)*27.3% -> 159.25 | AA27: =SUM(R27:Z27) -> 896.58333 | AB27: =L27+Q27+AA27 -> 4449.3833
B28: Sandra Daniel | C28: 2100 | F28: 250 | H28: 600 | I28: 103 | J28: 8.5 | K28: 13 | L28: =SUM(C28:K28) -> 3074.5 | M28: =(C28+F28+G28)*20% -> 470 | N28: =(C28+F28+G28)*1.5% -> 35.25 | O28: =(C28+F28+G28)*5.8% -> 136.3 | P28: =(C28+F28+G28)*8% -> 188 | Q28: =SUM(M28:P28) -> 829.55 | R28: =(C28+F28+G28)/12 -> 195.83333 | S28: =R28/3 -> 65.277778 | T28: =(R28+S28)*8% -> 20.888889 | U28: =(C28+F28+G28)/12 -> 195.83333 | V28: =U28*8% -> 15.666667 | W28: =(C28+F28+G28)/12 -> 195.83333 | X28: =W28*8% -> 15.666667 | Y28: =(P28+T28+V28+X28)*50% -> 120.11111 | Z28: =(R28+S28+U28+W28)*27.3% -> 178.20833 | AA28: =SUM(R28:Z28) -> 1003.3194 | AB28: =L28+Q28+AA28 -> 4907.3694
B29: Terezinha de Lourdes | C29: 1120 | H29: 0 | I29: 103 | J29: 8.5 | L29: =SUM(C29:K29) -> 1231.5 | M29: =(C29+F29+G29)*20% -> 224 | N29: =(C29+F29+G29)*1.5% -> 16.8 | O29: =(C29+F29+G29)*5.8% -> 64.96 | P29: =(C29+F29+G29)*8% -> 89.6 | Q29: =SUM(M29:P29) -> 395.36 | R29: =(C29+F29+G29)/12 -> 93.333333 | S29: =R29/3 -> 31.111111 | T29: =(R29+S29)*8% -> 9.9555556 | U29: =(C29+F29+G29)/12 -> 93.333333 | V29: =U29*8% -> 7.4666667 | W29: =(C29+F29+G29)/12 -> 93.333333 | X29: =W29*8% -> 7.4666667 | Y29: =(P29+T29+V29+X29)*50% -> 57.244444 | Z29: =(R29+S29+U29+W29)*27.3% -> 84.933333 | AA29: =SUM(R29:Z29) -> 478.17778 | AB29: =L29+Q29+AA29 -> 2105.0378
B30: Vanuza de Oliveira Gomes | C30: 2100 | F30: 0 | H30: 600 | I30: 103 | J30: 8.5 | K30: 13 | L30: =SUM(C30:K30) -> 2824.5 | M30: =(C30+F30+G30)*20% -> 420 | N30: =(C30+F30+G30)*1.5% -> 31.5 | O30: =(C30+F30+G30)*5.8% -> 121.8 | P30: =(C30+F30+G30)*8% -> 168 | Q30: =SUM(M30:P30) -> 741.3 | R30: =(C30+F30+G30)/12 -> 175 | S30: =R30/3 -> 58.333333 | T30: =(R30+S30)*8% -> 18.666667 | U30: =(C30+F30+G30)/12 -> 175 | V30: =U30*8% -> 14 | W30: =(C30+F30+G30)/12 -> 175 | X30: =W30*8% -> 14 | Y30: =(P30+T30+V30+X30)*50% -> 107.33333 | Z30: =(R30+S30+U30+W30)*27.3% -> 159.25 | AA30: =SUM(R30:Z30) -> 896.58333 | AB30: =L30+Q30+AA30 -> 4462.3833
B31: Zilneide da Conceição | C31: 2100 | F31: 250 | H31: 600 | I31: 103 | J31: 8.5 | K31: 13 | L31: =SUM(C31:K31) -> 3074.5 | M31: =(C31+F31+G31)*20% -> 470 | N31: =(C31+F31+G31)*1.5% -> 35.25 | O31: =(C31+F31+G31)*5.8% -> 136.3 | P31: =(C31+F31+G31)*8% -> 188 | Q31: =SUM(M31:P31) -> 829.55 | R31: =(C31+F31+G31)/12 -> 195.83333 | S31: =R31/3 -> 65.277778 | T31: =(R31+S31)*8% -> 20.888889 | U31: =(C31+F31+G31)/12 -> 195.83333 | V31: =U31*8% -> 15.666667 | W31: =(C31+F31+G31)/12 -> 195.83333 | X31: =W31*8% -> 15.666667 | Y31: =(P31+T31+V31+X31)*50% -> 120.11111 | Z31: =(R31+S31+U31+W31)*27.3% -> 178.20833 | AA31: =SUM(R31:Z31) -> 1003.3194 | AB31: =L31+Q31+AA31 -> 4907.3694
B32: Zirlene Aparecida de Oliveira Tomaz da Silva | C32: 2100 | F32: 250 | H32: 600 | I32: 103 | J32: 8.5 | K32: 13 | L32: =SUM(C32:K32) -> 3074.5 | M32: =(C32+F32+G32)*20% -> 470 | N32: =(C32+F32+G32)*1.5% -> 35.25 | O32: =(C32+F32+G32)*5.8% -> 136.3 | P32: =(C32+F32+G32)*8% -> 188 | Q32: =SUM(M32:P32) -> 829.55 | R32: =(C32+F32+G32)/12 -> 195.83333 | S32: =R32/3 -> 65.277778 | T32: =(R32+S32)*8% -> 20.888889 | U32: =(C32+F32+G32)/12 -> 195.83333 | V32: =U32*8% -> 15.666667 | W32: =(C32+F32+G32)/12 -> 195.83333 | X32: =W32*8% -> 15.666667 | Y32: =(P32+T32+V32+X32)*50% -> 120.11111 | Z32: =(R32+S32+U32+W32)*27.3% -> 178.20833 | AA32: =SUM(R32:Z32) -> 1003.3194 | AB32: =L32+Q32+AA32 -> 4907.3694
B33: Denize Moreira Coelho Martins | C33: 2100 | F33: 250 | H33: 600 | I33: 103 | J33: 8.5 | K33: 13 | L33: =SUM(C33:K33) -> 3074.5 | M33: =(C33+F33+G33)*20% -> 470 | N33: =(C33+F33+G33)*1.5% -> 35.25 | O33: =(C33+F33+G33)*5.8% -> 136.3 | P33: =(C33+F33+G33)*8% -> 188 | Q33: =SUM(M33:P33) -> 829.55 | R33: =(C33+F33+G33)/12 -> 195.83333 | S33: =R33/3 -> 65.277778 | T33: =(R33+S33)*8% -> 20.888889 | U33: =(C33+F33+G33)/12 -> 195.83333 | V33: =U33*8% -> 15.666667 | W33: =(C33+F33+G33)/12 -> 195.83333 | X33: =W33*8% -> 15.666667 | Y33: =(P33+T33+V33+X33)*50% -> 120.11111 | Z33: =(R33+S33+U33+W33)*27.3% -> 178.20833 | AA33: =SUM(R33:Z33) -> 1003.3194 | AB33: =L33+Q33+AA33 -> 4907.3694
B34: Edson Jose de Souza | C34: 3000 | H34: 0 | I34: 103 | J34: 8.5 | K34: 13 | L34: =SUM(C34:K34) -> 3124.5 | M34: =(C34+F34+G34)*20% -> 600 | N34: =(C34+F34+G34)*1.5% -> 45 | O34: =(C34+F34+G34)*5.8% -> 174 | P34: =(C34+F34+G34)*8% -> 240 | Q34: =SUM(M34:P34) -> 1059 | R34: =(C34+F34+G34)/12 -> 250 | S34: =R34/3 -> 83.333333 | T34: =(R34+S34)*8% -> 26.666667 | U34: =(C34+F34+G34)/12 -> 250 | V34: =U34*8% -> 20 | W34: =(C34+F34+G34)/12 -> 250 | X34: =W34*8% -> 20 | Y34: =(P34+T34+V34+X34)*50% -> 153.33333 | Z34: =(R34+S34+U34+W34)*27.3% -> 227.5 | AA34: =SUM(R34:Z34) -> 1280.8333 | AB34: =L34+Q34+AA34 -> 5464.3333
B35: Giordano Bruno Garibaldi | C35: 4200 | H35: 240 | I35: 103 | J35: 8.5 | L35: =SUM(C35:K35) -> 4551.5 | M35: =(C35+F35+G35)*20% -> 840 | N35: =(C35+F35+G35)*1.5% -> 63 | O35: =(C35+F35+G35)*5.8% -> 243.6 | P35: =(C35+F35+G35)*8% -> 336 | Q35: =SUM(M35:P35) -> 1482.6 | R35: =(C35+F35+G35)/12 -> 350 | S35: =R35/3 -> 116.66667 | T35: =(R35+S35)*8% -> 37.333333 | U35: =(C35+F35+G35)/12 -> 350 | V35: =U35*8% -> 28 | W35: =(C35+F35+G35)/12 -> 350 | X35: =W35*8% -> 28 | Y35: =(P35+T35+V35+X35)*50% -> 214.66667 | Z35: =(R35+S35+U35+W35)*27.3% -> 318.5 | AA35: =SUM(R35:Z35) -> 1793.1667 | AB35: =L35+Q35+AA35 -> 7827.2667
B36: Luiz Zanão | C36: 1622 | H36: 0 | I36: 103 | J36: 8.5 | K36: 13 | L36: =SUM(C36:K36) -> 1746.5 | M36: =(C36+F36+G36)*20% -> 324.4 | N36: =(C36+F36+G36)*1.5% -> 24.33 | O36: =(C36+F36+G36)*5.8% -> 94.076 | P36: =(C36+F36+G36)*8% -> 129.76 | Q36: =SUM(M36:P36) -> 572.566 | R36: =(C36+F36+G36)/12 -> 135.16667 | S36: =R36/3 -> 45.055556 | T36: =(R36+S36)*8% -> 14.417778 | U36: =(C36+F36+G36)/12 -> 135.16667 | V36: =U36*8% -> 10.813333 | W36: =(C36+F36+G36)/12 -> 135.16667 | X36: =W36*8% -> 10.813333 | Y36: =(P36+T36+V36+X36)*50% -> 82.902222 | Z36: =(R36+S36+U36+W36)*27.3% -> 123.00167 | AA36: =SUM(R36:Z36) -> 692.50389 | AB36: =L36+Q36+AA36 -> 3011.5699
B37: Sarídia Ramos Broedel | C37: 2100 | H37: 600 | I37: 103 | J37: 8.5 | K37: 13 | L37: =SUM(C37:K37) -> 2824.5 | M37: =(C37+F37+G37)*20% -> 420 | N37: =(C37+F37+G37)*1.5% -> 31.5 | O37: =(C37+F37+G37)*5.8% -> 121.8 | P37: =(C37+F37+G37)*8% -> 168 | Q37: =SUM(M37:P37) -> 741.3 | R37: =(C37+F37+G37)/12 -> 175 | S37: =R37/3 -> 58.333333 | T37: =(R37+S37)*8% -> 18.666667 | U37: =(C37+F37+G37)/12 -> 175 | V37: =U37*8% -> 14 | W37: =(C37+F37+G37)/12 -> 175 | X37: =W37*8% -> 14 | Y37: =(P37+T37+V37+X37)*50% -> 107.33333 | Z37: =(R37+S37+U37+W37)*27.3% -> 159.25 | AA37: =SUM(R37:Z37) -> 896.58333 | AB37: =L37+Q37+AA37 -> 4462.3833
B38: Vanias Schneider | C38: 2500 | L38: =SUM(C38:K38) -> 2500 | Q38: =SUM(M38:P38) -> 0 | AB38: =L38+Q38+AA38 -> 2500
B39: Henrique Gazzinelli Tanure Teixeira | D39: =1621*2 -> 3242 | E39: 10844 | F39: 2000 | L39: =SUM(C39:K39) -> 16086 | M39: =3242*11% -> 356.62 | Q39: =SUM(M39:P39) -> 356.62 | AA39: =SUM(R39:Z39) -> 0 | AB39: =L39+Q39+AA39 -> 16442.62
C40: =SUM(C3:C39) -> 78662 | D40: =SUM(D3:D39) -> 3242 | E40: =SUM(E3:E39) -> 10844 | F40: =SUM(F3:F39) -> 6750 | G40: =SUM(G3:G39) -> 0 | H40: =SUM(H3:H39) -> 15840 | I40: =SUM(I3:I39) -> 3605 | J40: =SUM(J3:J39) -> 297.5 | ... AB40: =SUM(AB3:AB39) -> 183080.98
B42: COLABORADOR | C42: Salários | D42: Prolabore | E42: Dist. Lucro | F42: Anuênio | G42: HE+ DSR | H42: Assiduidade | I42: C. Básica | J42: Seguro | K42: Pl. Odonto | L42: Sub. Total | M42: INSS | N42: RAT | O42: Terceiros | P42: FGTS | Q42: T. Encargos | R42: Férias | S42: 1/3 Férias | T42: FGTS Férias | U42: 13º Sal | V42: FGTS 13º Sal | W42: Aviso Prévio | X42: FGTS Av. | Y42: Multa FGTS | Z42: Patronal | AA42: T. Provisão | AB42: Total | AC42: Custo Total | AD42: 46054
B43: Anailson da Conceição Ricarte | C43: 2100 | F43: 250 | H43: 600 | I43: 82.4 | J43: 8.5 | K43: 13 | L43: =SUM(C43:K43) -> 3053.9 | M43: =(C43+F43+G43)*20% -> 470 | N43: =(C43+F43+G43)*1.5% -> 35.25 | O43: =(C43+F43+G43)*5.8% -> 136.3 | P43: =(C43+F43+G43)*8% -> 188 | Q43: =SUM(M43:P43) -> 829.55 | R43: =(C43+F43+G43)/12 -> 195.83333 | S43: =R43/3 -> 65.277778 | T43: =(R43+S43)*8% -> 20.888889 | U43: =(C43+F43+G43)/12 -> 195.83333 | V43: =U43*8% -> 15.666667 | W43: =(C43+F43+G43)/12 -> 195.83333 | X43: =W43*8% -> 15.666667 | Y43: =(P43+T43+V43+X43)*50% -> 120.11111 | Z43: =(R43+S43+U43+W43)*27.3% -> 178.20833 | AA43: =SUM(R43:Z43) -> 1003.3194 | AB43: =L43+Q43+AA43 -> 4886.7694 | AC43: Salário | AD43: =C80 -> 73062
B44: Amanda Beatriz Alves da Silva | C44: 1750 | I44: 82.4 | J44: 8.5 | K44: 13 | L44: =SUM(C44:K44) -> 1853.9 | M44: =(C44+F44+G44)*20% -> 350 | N44: =(C44+F44+G44)*1.5% -> 26.25 | O44: =(C44+F44+G44)*5.8% -> 101.5 | P44: =(C44+F44+G44)*8% -> 140 | Q44: =SUM(M44:P44) -> 617.75 | R44: =(C44+F44+G44)/12 -> 145.83333 | S44: =R44/3 -> 48.611111 | T44: =(R44+S44)*8% -> 15.555556 | U44: =(C44+F44+G44)/12 -> 145.83333 | V44: =U44*8% -> 11.666667 | W44: =(C44+F44+G44)/12 -> 145.83333 | X44: =W44*8% -> 11.666667 | Y44: =(P44+T44+V44+X44)*50% -> 89.444444 | Z44: =(R44+S44+U44+W44)*27.3% -> 132.70833 | AA44: =SUM(R44:Z44) -> 747.15278 | AB44: =L44+Q44+AA44 -> 3218.8028 | AC44: Anuênio | AD44: =F80 -> 7000
B45: Cassia Coelho Ramos | C45: 2100 | F45: 250 | H45: 600 | I45: 82.4 | J45: 8.5 | K45: 13 | L45: =SUM(C45:K45) -> 3053.9 | M45: =(C45+F45+G45)*20% -> 470 | N45: =(C45+F45+G45)*1.5% -> 35.25 | O45: =(C45+F45+G45)*5.8% -> 136.3 | P45: =(C45+F45+G45)*8% -> 188 | Q45: =SUM(M45:P45) -> 829.55 | R45: =(C45+F45+G45)/12 -> 195.83333 | S45: =R45/3 -> 65.277778 | T45: =(R45+S45)*8% -> 20.888889 | U45: =(C45+F45+G45)/12 -> 195.83333 | V45: =U45*8% -> 15.666667 | W45: =(C45+F45+G45)/12 -> 195.83333 | X45: =W45*8% -> 15.666667 | Y45: =(P45+T45+V45+X45)*50% -> 120.11111 | Z45: =(R45+S45+U45+W45)*27.3% -> 178.20833 | AA45: =SUM(R45:Z45) -> 1003.3194 | AB45: =L45+Q45+AA45 -> 4886.7694 | AC45: H. Extra | AD45: 0
B46: Cassio Pereira Tomas | C46: 2100 | H46: 600 | I46: 82.4 | J46: 8.5 | K46: 0 | L46: =SUM(C46:K46) -> 2790.9 | M46: =(C46+F46+G46)*20% -> 420 | N46: =(C46+F46+G46)*1.5% -> 31.5 | O46: =(C46+F46+G46)*5.8% -> 121.8 | P46: =(C46+F46+G46)*8% -> 168 | Q46: =SUM(M46:P46) -> 741.3 | R46: =(C46+F46+G46)/12 -> 175 | S46: =R46/3 -> 58.333333 | T46: =(R46+S46)*8% -> 18.666667 | U46: =(C46+F46+G46)/12 -> 175 | V46: =U46*8% -> 14 | W46: =(C46+F46+G46)/12 -> 175 | X46: =W46*8% -> 14 | Y46: =(P46+T46+V46+X46)*50% -> 107.33333 | Z46: =(R46+S46+U46+W46)*27.3% -> 159.25 | AA46: =SUM(R46:Z46) -> 896.58333 | AB46: =L46+Q46+AA46 -> 4428.7833 | AC46: Prolabore | AD46: =D80 -> 3242
B47: Daysa Gregório Venancio | C47: 1750 | I47: 82.4 | J47: 8.5 | K47: 13 | L47: =SUM(C47:K47) -> 1853.9 | M47: =(C47+F47+G47)*20% -> 350 | N47: =(C47+F47+G47)*1.5% -> 26.25 | O47: =(C47+F47+G47)*5.8% -> 101.5 | P47: =(C47+F47+G47)*8% -> 140 | Q47: =SUM(M47:P47) -> 617.75 | R47: =(C47+F47+G47)/12 -> 145.83333 | S47: =R47/3 -> 48.611111 | T47: =(R47+S47)*8% -> 15.555556 | U47: =(C47+F47+G47)/12 -> 145.83333 | V47: =U47*8% -> 11.666667 | W47: =(C47+F47+G47)/12 -> 145.83333 | X47: =W47*8% -> 11.666667 | Y47: =(P47+T47+V47+X47)*50% -> 89.444444 | Z47: =(R47+S47+U47+W47)*27.3% -> 132.70833 | AA47: =SUM(R47:Z47) -> 747.15278 | AB47: =L47+Q47+AA47 -> 3218.8028 | AC47: Dist. Lucro | AD47: =E80 -> 10844
B48: Edineia Maria Lopes da Silva | C48: 2100 | F48: 250 | H48: 600 | I48: 82.4 | J48: 8.5 | K48: 13 | L48: =SUM(C48:K48) -> 3053.9 | M48: =(C48+F48+G48)*20% -> 470 | N48: =(C48+F48+G48)*1.5% -> 35.25 | O48: =(C48+F48+G48)*5.8% -> 136.3 | P48: =(C48+F48+G48)*8% -> 188 | Q48: =SUM(M48:P48) -> 829.55 | R48: =(C48+F48+G48)/12 -> 195.83333 | S48: =R48/3 -> 65.277778 | T48: =(R48+S48)*8% -> 20.888889 | U48: =(C48+F48+G48)/12 -> 195.83333 | V48: =U48*8% -> 15.666667 | W48: =(C48+F48+G48)/12 -> 195.83333 | X48: =W48*8% -> 15.666667 | Y48: =(P48+T48+V48+X48)*50% -> 120.11111 | Z48: =(R48+S48+U48+W48)*27.3% -> 178.20833 | AA48: =SUM(R48:Z48) -> 1003.3194 | AB48: =L48+Q48+AA48 -> 4886.7694 | AC48: Benefício | AD48: =SUM(H80:K80) -> 18811.5
B49: Erminda Maria Lopes | C49: 2100 | F49: 250 | H49: 600 | I49: 82.4 | J49: 8.5 | K49: 13 | L49: =SUM(C49:K49) -> 3053.9 | M49: =(C49+F49+G49)*20% -> 470 | N49: =(C49+F49+G49)*1.5% -> 35.25 | O49: =(C49+F49+G49)*5.8% -> 136.3 | P49: =(C49+F49+G49)*8% -> 188 | Q49: =SUM(M49:P49) -> 829.55 | R49: =(C49+F49+G49)/12 -> 195.83333 | S49: =R49/3 -> 65.277778 | T49: =(R49+S49)*8% -> 20.888889 | U49: =(C49+F49+G49)/12 -> 195.83333 | V49: =U49*8% -> 15.666667 | W49: =(C49+F49+G49)/12 -> 195.83333 | X49: =W49*8% -> 15.666667 | Y49: =(P49+T49+V49+X49)*50% -> 120.11111 | Z49: =(R49+S49+U49+W49)*27.3% -> 178.20833 | AA49: =SUM(R49:Z49) -> 1003.3194 | AB49: =L49+Q49+AA49 -> 4886.7694 | AC49: Patronal | AD49: =SUM(M80:O80) -> 20712.046
B50: Flipe Sansão | C50: 1260 | I50: 82.4 | J50: 8.5 | K50: 13 | L50: =SUM(C50:K50) -> 1363.9 | M50: =(C50+F50+G50)*20% -> 252 | N50: =(C50+F50+G50)*1.5% -> 18.9 | O50: =(C50+F50+G50)*5.8% -> 73.08 | P50: =(C50+F50+G50)*8% -> 100.8 | Q50: =SUM(M50:P50) -> 444.78 | R50: =(C50+F50+G50)/12 -> 105 | S50: =R50/3 -> 35 | T50: =(R50+S50)*8% -> 11.2 | U50: =(C50+F50+G50)/12 -> 105 | V50: =U50*8% -> 8.4 | W50: =(C50+F50+G50)/12 -> 105 | X50: =W50*8% -> 8.4 | Y50: =(P50+T50+V50+X50)*50% -> 64.4 | Z50: =(R50+S50+U50+W50)*27.3% -> 95.55 | AA50: =SUM(R50:Z50) -> 537.95 | AB50: =L50+Q50+AA50 -> 2346.63 | AC50: FGTS | AD50: =P80 -> 5964.96
B51: Hugo Berudio Amorim | C51: 2100 | F51: 250 | H51: 240 | I51: 82.4 | J51: 8.5 | K51: 13 | L51: =SUM(C51:K51) -> 2693.9 | M51: =(C51+F51+G51)*20% -> 470 | N51: =(C51+F51+G51)*1.5% -> 35.25 | O51: =(C51+F51+G51)*5.8% -> 136.3 | P51: =(C51+F51+G51)*8% -> 188 | Q51: =SUM(M51:P51) -> 829.55 | R51: =(C51+F51+G51)/12 -> 195.83333 | S51: =R51/3 -> 65.277778 | T51: =(R51+S51)*8% -> 20.888889 | U51: =(C51+F51+G51)/12 -> 195.83333 | V51: =U51*8% -> 15.666667 | W51: =(C51+F51+G51)/12 -> 195.83333 | X51: =W51*8% -> 15.666667 | Y51: =(P51+T51+V51+X51)*50% -> 120.11111 | Z51: =(R51+S51+U51+W51)*27.3% -> 178.20833 | AA51: =SUM(R51:Z51) -> 1003.3194 | AB51: =L51+Q51+AA51 -> 4526.7694 | AC51: Provisão | AD51: =SUM(R80:Z80) -> 31833.832
B52: Jamaica Pena | C52: 630 | I52: 82.4 | J52: 8.5 | K52: 0 | L52: =SUM(C52:K52) -> 720.9 | M52: =(C52+F52+G52)*20% -> 126 | N52: =(C52+F52+G52)*1.5% -> 9.45 | O52: =(C52+F52+G52)*5.8% -> 36.54 | P52: =(C52+F52+G52)*8% -> 50.4 | Q52: =SUM(M52:P52) -> 222.39 | R52: =(C52+F52+G52)/12 -> 52.5 | S52: =R52/3 -> 17.5 | T52: =(R52+S52)*8% -> 5.6 | U52: =(C52+F52+G52)/12 -> 52.5 | V52: =U52*8% -> 4.2 | W52: =(C52+F52+G52)/12 -> 52.5 | X52: =W52*8% -> 4.2 | Y52: =(P52+T52+V52+X52)*50% -> 32.2 | Z52: =(R52+S52+U52+W52)*27.3% -> 47.775 | AA52: =SUM(R52:Z52) -> 268.975 | AB52: =L52+Q52+AA52 -> 1212.265 | AC52: Total | AD52: =SUM(AD43:AD51) -> 171470.34
B53: José Guilherme Teixeira Braga | C53: 2100 | F53: 250 | H53: 600 | I53: 82.4 | J53: 8.5 | K53: 13 | L53: =SUM(C53:K53) -> 3053.9 | M53: =(C53+F53+G53)*20% -> 470 | N53: =(C53+F53+G53)*1.5% -> 35.25 | O53: =(C53+F53+G53)*5.8% -> 136.3 | P53: =(C53+F53+G53)*8% -> 188 | Q53: =SUM(M53:P53) -> 829.55 | R53: =(C53+F53+G53)/12 -> 195.83333 | S53: =R53/3 -> 65.277778 | T53: =(R53+S53)*8% -> 20.888889 | U53: =(C53+F53+G53)/12 -> 195.83333 | V53: =U53*8% -> 15.666667 | W53: =(C53+F53+G53)/12 -> 195.83333 | X53: =W53*8% -> 15.666667 | Y53: =(P53+T53+V53+X53)*50% -> 120.11111 | Z53: =(R53+S53+U53+W53)*27.3% -> 178.20833 | AA53: =SUM(R53:Z53) -> 1003.3194 | AB53: =L53+Q53+AA53 -> 4886.7694
B54: Lorena Barbosa Boeque | C54: 2100 | H54: 600 | I54: 82.4 | J54: 8.5 | K54: 13 | L54: =SUM(C54:K54) -> 2803.9 | M54: =(C54+F54+G54)*20% -> 420 | N54: =(C54+F54+G54)*1.5% -> 31.5 | O54: =(C54+F54+G54)*5.8% -> 121.8 | P54: =(C54+F54+G54)*8% -> 168 | Q54: =SUM(M54:P54) -> 741.3 | R54: =(C54+F54+G54)/12 -> 175 | S54: =R54/3 -> 58.333333 | T54: =(R54+S54)*8% -> 18.666667 | U54: =(C54+F54+G54)/12 -> 175 | V54: =U54*8% -> 14 | W54: =(C54+F54+G54)/12 -> 175 | X54: =W54*8% -> 14 | Y54: =(P54+T54+V54+X54)*50% -> 107.33333 | Z54: =(R54+S54+U54+W54)*27.3% -> 159.25 | AA54: =SUM(R54:Z54) -> 896.58333 | AB54: =L54+Q54+AA54 -> 4441.7833
B55: Lorena de Oliveira Luzorio | C55: 2100 | F55: 250 | H55: 600 | I55: 82.4 | J55: 8.5 | K55: 13 | L55: =SUM(C55:K55) -> 3053.9 | M55: =(C55+F55+G55)*20% -> 470 | N55: =(C55+F55+G55)*1.5% -> 35.25 | O55: =(C55+F55+G55)*5.8% -> 136.3 | P55: =(C55+F55+G55)*8% -> 188 | Q55: =SUM(M55:P55) -> 829.55 | R55: =(C55+F55+G55)/12 -> 195.83333 | S55: =R55/3 -> 65.277778 | T55: =(R55+S55)*8% -> 20.888889 | U55: =(C55+F55+G55)/12 -> 195.83333 | V55: =U55*8% -> 15.666667 | W55: =(C55+F55+G55)/12 -> 195.83333 | X55: =W55*8% -> 15.666667 | Y55: =(P55+T55+V55+X55)*50% -> 120.11111 | Z55: =(R55+S55+U55+W55)*27.3% -> 178.20833 | AA55: =SUM(R55:Z55) -> 1003.3194 | AB55: =L55+Q55+AA55 -> 4886.7694
